Workbook
Name APIdapter_CCP_B: 'Program Config'!#REF!
Name Back_To_Build_Specs: 'Program Config'!$C$33
Name CCP: 'Program Config'!#REF!
Name Client_URL: 'Program Config'!$C$34
Name Go_Back_to_Build_Specs: 'DemoData3 CCP Tab'!$C$1
Name Link_Back_To_Build_Specs: 'Program Config'!$C$34
Name Link_to_APIdapter_Common_Custom_Parameters: 'Program Config'!$H$33
Name Time_Zone_Map: 'Program Config'!$B$2024

Sheet Program Contacts & Kickoff
A1: Implementation Manager | B1: Victoria Lane | E1: =IFERROR(IF(AND($B1<>"",VLOOKUP($B1,$O:$P,2,FALSE)<>""),VLOOKUP($B1,$O:$P,2,FALSE),$B1),IF($B1<>"",$B1,"")) -> victoria.lane@FakeDemoData.com | N1: Group | O1: Contact | P1: PRODCUT4 | Q1: Initials
A2: Customer Success Manager | B2: Leah Adler | E2: =IFERROR(IF(AND($B2<>"",VLOOKUP($B2,$O:$P,2,FALSE)<>""),VLOOKUP($B2,$O:$P,2,FALSE),$B2),IF($B2<>"",$B2,"")) -> leah.adler@FakeDemoData.com | N2: CSM | O2: Ava Mitchell | P2: ava.mitchell@FakeDemoData.com | Q2: AM
A3: Sales Representative | B3: Gavin Park | E3: =IFERROR(IF(AND($B3<>"",VLOOKUP($B3,$O:$P,2,FALSE)<>""),VLOOKUP($B3,$O:$P,2,FALSE),$B3),IF($B3<>"",$B3,"")) -> gavin.park@FakeDemoData.com | N3: CSM | O3: Liam Carter | P3: liam.carter@FakeDemoData.com | Q3: LC
N4: IM | O4: Sofia Ramirez | P4: sofia.ramirez@FakeDemoData.com | Q4: SR
B5: Contact PRODCUT4 | C5: Contact Category | D5: Primary | H5: All PRODCUT4 | I5: Full Name | J5: First Name | K5: Second Name | L5: L,F | N5: CSM | O5: Noah Bennett | P5: noah.bennett@FakeDemoData.com | Q5: NB | R5: New! Primary Radial & All PRODCUT4 Check Boxes!
A6: Identify additional people who should be copied on program PRODCUT4 (including client PRODCUT4 addresses): | B6: w.barnes@demodata.com | C6: Technical Contact | D6: 3 | E6: =IFERROR(IF(AND($B6<>"",VLOOKUP($B6,$O:$P,2,FALSE)<>""),VLOOKUP($B6,$O:$P,2,FALSE),$B6),IF($B6<>"",$B6,"")) -> w.barnes@demodata.com | H6: TRUE | I6: =_xlfn.TEXTJOIN(" ",TRUE,J6,K6) -> William Barnes | J6: {=IFERROR(IF(AND($B$16<>"",$H$16<>""),_xlfn.LET( _xlpm.result, IF($H$16="First Name", INDEX($E$18:$E$27,MATCH(TRUE,INDEX(ISNUMBER(SEARCH(LOWER($E$18:$E$27),LOWER(B6))),0),0)), INDEX($E$18:$E$27,MATCH(TRUE,INDEX(ISNUMBER(SEARCH(LOWER($F$18:$F$27),LOWER(B6))),0),0)) ), IF(_xlpm.result=0,"",_xlpm.result) ),""),"")} -> William | K6: {=IFERROR(IF(AND($B$16<>"",$H$16<>""), _xlfn.LET( _xlpm.result, IF($H$16="Second Name", INDEX($F$18:$F$27,MATCH(TRUE,INDEX(ISNUMBER(SEARCH(LOWER($F$18:$F$27),LOWER(B6))),0),0)), INDEX($E$18:$E$27,MATCH(TRUE,INDEX(ISNUMBER(SEARCH(LOWER($E$18:$E$27),LOWER(B6))),0),0)) ), IF(_xlpm.result=0,"",_xlpm.result) ), ""),"")} -> Barnes | L6: =_xlfn.TEXTJOIN(", ",TRUE,K6,J6) -> Barnes, William | N6: Sales | O6: Mia Thompson | P6: mia.thompson@FakeDemoData.com | Q6: MT | S6: Choosing a primary contact will populate their information on the LK Frontloader Tab
B7: m.chen@demodata.com | C7: JLB (Not on List) | D7: 1 | E7: =IFERROR(IF(AND($B7<>"",VLOOKUP($B7,$O:$P,2,FALSE)<>""),VLOOKUP($B7,$O:$P,2,FALSE),$B7),IF($B7<>"",$B7,"")) -> m.chen@demodata.com | H7: FALSE | I7: =_xlfn.TEXTJOIN(" ",TRUE,J7,K7) -> Maya Chen | J7: {=IFERROR(IF(AND($B$16<>"",$H$16<>""),_xlfn.LET( _xlpm.result, IF($H$16="First Name", INDEX($E$18:$E$27,MATCH(TRUE,INDEX(ISNUMBER(SEARCH(LOWER($E$18:$E$27),LOWER(B7))),0),0)), INDEX($E$18:$E$27,MATCH(TRUE,INDEX(ISNUMBER(SEARCH(LOWER($F$18:$F$27),LOWER(B7))),0),0)) ), IF(_xlpm.result=0,"",_xlpm.result) ),""),"")} -> Maya | K7: {=IFERROR(IF(AND($B$16<>"",$H$16<>""), _xlfn.LET( _xlpm.result, IF($H$16="Second Name", INDEX($F$18:$F$27,MATCH(TRUE,INDEX(ISNUMBER(SEARCH(LOWER($F$18:$F$27),LOWER(B7))),0),0)), INDEX($E$18:$E$27,MATCH(TRUE,INDEX(ISNUMBER(SEARCH(LOWER($E$18:$E$27),LOWER(B7))),0),0)) ), IF(_xlpm.result=0,"",_xlpm.result) ), ""),"")} -> Chen | L7: =_xlfn.TEXTJOIN(", ",TRUE,K7,J7) -> Chen, Maya | N7: IM | O7: Jackson Hughes | P7: jackson.hughes@FakeDemoData.com | Q7: JH
A8: • Enter up to 10 PRODCUT4 addresses OR names | B8: t.navarro@demodata.com | C8: Program Contact | E8: =IFERROR(IF(AND($B8<>"",VLOOKUP($B8,$O:$P,2,FALSE)<>""),VLOOKUP($B8,$O:$P,2,FALSE),$B8),IF($B8<>"",$B8,"")) -> t.navarro@demodata.com | H8: TRUE | I8: =_xlfn.TEXTJOIN(" ",TRUE,J8,K8) -> Theo Navarro | J8: {=IFERROR(IF(AND($B$16<>"",$H$16<>""),_xlfn.LET( _xlpm.result, IF($H$16="First Name", INDEX($E$18:$E$27,MATCH(TRUE,INDEX(ISNUMBER(SEARCH(LOWER($E$18:$E$27),LOWER(B8))),0),0)), INDEX($E$18:$E$27,MATCH(TRUE,INDEX(ISNUMBER(SEARCH(LOWER($F$18:$F$27),LOWER(B8))),0),0)) ), IF(_xlpm.result=0,"",_xlpm.result) ),""),"")} -> Theo | K8: {=IFERROR(IF(AND($B$16<>"",$H$16<>""), _xlfn.LET( _xlpm.result, IF($H$16="Second Name", INDEX($F$18:$F$27,MATCH(TRUE,INDEX(ISNUMBER(SEARCH(LOWER($F$18:$F$27),LOWER(B8))),0),0)), INDEX($E$18:$E$27,MATCH(TRUE,INDEX(ISNUMBER(SEARCH(LOWER($E$18:$E$27),LOWER(B8))),0),0)) ), IF(_xlpm.result=0,"",_xlpm.result) ), ""),"")} -> Navarro | L8: =_xlfn.TEXTJOIN(", ",TRUE,K8,J8) -> Navarro, Theo | N8: IM | O8: Isabella Flores | P8: isabella.flores@FakeDemoData.com | Q8: IF
A9: • @DemoData.com & @demodata.com PRODCUT4 will automagically be added to all PRODCUT4 CCs & Tags | B9: n.reed@demodata.com | C9: Program Contact | E9: =IFERROR(IF(AND($B9<>"",VLOOKUP($B9,$O:$P,2,FALSE)<>""),VLOOKUP($B9,$O:$P,2,FALSE),$B9),IF($B9<>"",$B9,"")) -> n.reed@demodata.com | H9: TRUE | I9: =_xlfn.TEXTJOIN(" ",TRUE,J9,K9) -> Noaln Reed | J9: {=IFERROR(IF(AND($B$16<>"",$H$16<>""),_xlfn.LET( _xlpm.result, IF($H$16="First Name", INDEX($E$18:$E$27,MATCH(TRUE,INDEX(ISNUMBER(SEARCH(LOWER($E$18:$E$27),LOWER(B9))),0),0)), INDEX($E$18:$E$27,MATCH(TRUE,INDEX(ISNUMBER(SEARCH(LOWER($F$18:$F$27),LOWER(B9))),0),0)) ), IF(_xlpm.result=0,"",_xlpm.result) ),""),"")} -> Noaln | K9: {=IFERROR(IF(AND($B$16<>"",$H$16<>""), _xlfn.LET( _xlpm.result, IF($H$16="Second Name", INDEX($F$18:$F$27,MATCH(TRUE,INDEX(ISNUMBER(SEARCH(LOWER($F$18:$F$27),LOWER(B9))),0),0)), INDEX($E$18:$E$27,MATCH(TRUE,INDEX(ISNUMBER(SEARCH(LOWER($E$18:$E$27),LOWER(B9))),0),0)) ), IF(_xlpm.result=0,"",_xlpm.result) ), ""),"")} -> Reed | L9: =_xlfn.TEXTJOIN(", ",TRUE,K9,J9) -> Reed, Noaln | N9: Sales | O9: Lucas Morgan | P9: lucas.morgan@FakeDemoData.com | Q9: LM
E10: =IFERROR(IF(AND($B10<>"",VLOOKUP($B10,$O:$P,2,FALSE)<>""),VLOOKUP($B10,$O:$P,2,FALSE),$B10),IF($B10<>"",$B10,"")) | H10: FALSE | I10: =_xlfn.TEXTJOIN(" ",TRUE,J10,K10) | J10: {=IFERROR(IF(AND($B$16<>"",$H$16<>""),_xlfn.LET( _xlpm.result, IF($H$16="First Name", INDEX($E$18:$E$27,MATCH(TRUE,INDEX(ISNUMBER(SEARCH(LOWER($E$18:$E$27),LOWER(B10))),0),0)), INDEX($E$18:$E$27,MATCH(TRUE,INDEX(ISNUMBER(SEARCH(LOWER($F$18:$F$27),LOWER(B10))),0),0)) ), IF(_xlpm.result=0,"",_xlpm.result) ),""),"")} | K10: {=IFERROR(IF(AND($B$16<>"",$H$16<>""), _xlfn.LET( _xlpm.result, IF($H$16="Second Name", INDEX($F$18:$F$27,MATCH(TRUE,INDEX(ISNUMBER(SEARCH(LOWER($F$18:$F$27),LOWER(B10))),0),0)), INDEX($E$18:$E$27,MATCH(TRUE,INDEX(ISNUMBER(SEARCH(LOWER($E$18:$E$27),LOWER(B10))),0),0)) ), IF(_xlpm.result=0,"",_xlpm.result) ), ""),"")} | L10: =_xlfn.TEXTJOIN(", ",TRUE,K10,J10) | N10: CSM | O10: Charlotte Price | P10: charlotte.price@FakeDemoData.com | Q10: CP | R10: New! Client Name String & Matching Component!
A11: • All PRODCUT4 from other PRODUCT4 will be added to TO lines according to the Client Contact Type* selected from the drop down, see list below | E11: =IFERROR(IF(AND($B11<>"",VLOOKUP($B11,$O:$P,2,FALSE)<>""),VLOOKUP($B11,$O:$P,2,FALSE),$B11),IF($B11<>"",$B11,"")) | H11: FALSE | I11: =_xlfn.TEXTJOIN(" ",TRUE,J11,K11) | J11: {=IFERROR(IF(AND($B$16<>"",$H$16<>""),_xlfn.LET( _xlpm.result, IF($H$16="First Name", INDEX($E$18:$E$27,MATCH(TRUE,INDEX(ISNUMBER(SEARCH(LOWER($E$18:$E$27),LOWER(B11))),0),0)), INDEX($E$18:$E$27,MATCH(TRUE,INDEX(ISNUMBER(SEARCH(LOWER($F$18:$F$27),LOWER(B11))),0),0)) ), IF(_xlpm.result=0,"",_xlpm.result) ),""),"")} | K11: {=IFERROR(IF(AND($B$16<>"",$H$16<>""), _xlfn.LET( _xlpm.result, IF($H$16="Second Name", INDEX($F$18:$F$27,MATCH(TRUE,INDEX(ISNUMBER(SEARCH(LOWER($F$18:$F$27),LOWER(B11))),0),0)), INDEX($E$18:$E$27,MATCH(TRUE,INDEX(ISNUMBER(SEARCH(LOWER($E$18:$E$27),LOWER(B11))),0),0)) ), IF(_xlpm.result=0,"",_xlpm.result) ), ""),"")} | L11: =_xlfn.TEXTJOIN(", ",TRUE,K11,J11) | N11: Sales | O11: Ethan Rivera | P11: ethan.rivera@FakeDemoData.com | Q11: ER | S11: Dropping a text string of all client contacts & selecting if their first name or second names match their PRODCUT4 will populate their full names.
E12: =IFERROR(IF(AND($B12<>"",VLOOKUP($B12,$O:$P,2,FALSE)<>""),VLOOKUP($B12,$O:$P,2,FALSE),$B12),IF($B12<>"",$B12,"")) | H12: FALSE | I12: =_xlfn.TEXTJOIN(" ",TRUE,J12,K12) | J12: {=IFERROR(IF(AND($B$16<>"",$H$16<>""),_xlfn.LET( _xlpm.result, IF($H$16="First Name", INDEX($E$18:$E$27,MATCH(TRUE,INDEX(ISNUMBER(SEARCH(LOWER($E$18:$E$27),LOWER(B12))),0),0)), INDEX($E$18:$E$27,MATCH(TRUE,INDEX(ISNUMBER(SEARCH(LOWER($F$18:$F$27),LOWER(B12))),0),0)) ), IF(_xlpm.result=0,"",_xlpm.result) ),""),"")} | K12: {=IFERROR(IF(AND($B$16<>"",$H$16<>""), _xlfn.LET( _xlpm.result, IF($H$16="Second Name", INDEX($F$18:$F$27,MATCH(TRUE,INDEX(ISNUMBER(SEARCH(LOWER($F$18:$F$27),LOWER(B12))),0),0)), INDEX($E$18:$E$27,MATCH(TRUE,INDEX(ISNUMBER(SEARCH(LOWER($E$18:$E$27),LOWER(B12))),0),0)) ), IF(_xlpm.result=0,"",_xlpm.result) ), ""),"")} | L12: =_xlfn.TEXTJOIN(", ",TRUE,K12,J12) | N12: CSM | O12: Amelia Howard | P12: amelia.howard@FakeDemoData.com | Q12: AH
A13: Technical Contact --> Integration / Migration + Whitelist + Rostering/PRODUCT2 Program Contact --> Program Preferences All Client PRODCUT4 --> All Client PRODCUT4 | E13: =IFERROR(IF(AND($B13<>"",VLOOKUP($B13,$O:$P,2,FALSE)<>""),VLOOKUP($B13,$O:$P,2,FALSE),$B13),IF($B13<>"",$B13,"")) | H13: FALSE | I13: =_xlfn.TEXTJOIN(" ",TRUE,J13,K13) | J13: {=IFERROR(IF(AND($B$16<>"",$H$16<>""),_xlfn.LET( _xlpm.result, IF($H$16="First Name", INDEX($E$18:$E$27,MATCH(TRUE,INDEX(ISNUMBER(SEARCH(LOWER($E$18:$E$27),LOWER(B13))),0),0)), INDEX($E$18:$E$27,MATCH(TRUE,INDEX(ISNUMBER(SEARCH(LOWER($F$18:$F$27),LOWER(B13))),0),0)) ), IF(_xlpm.result=0,"",_xlpm.result) ),""),"")} | K13: {=IFERROR(IF(AND($B$16<>"",$H$16<>""), _xlfn.LET( _xlpm.result, IF($H$16="Second Name", INDEX($F$18:$F$27,MATCH(TRUE,INDEX(ISNUMBER(SEARCH(LOWER($F$18:$F$27),LOWER(B13))),0),0)), INDEX($E$18:$E$27,MATCH(TRUE,INDEX(ISNUMBER(SEARCH(LOWER($E$18:$E$27),LOWER(B13))),0),0)) ), IF(_xlpm.result=0,"",_xlpm.result) ), ""),"")} | L13: =_xlfn.TEXTJOIN(", ",TRUE,K13,J13) | N13: CSM | O13: Oliver Brooks | P13: oliver.brooks@FakeDemoData.com | Q13: OB
E14: =IFERROR(IF(AND($B14<>"",VLOOKUP($B14,$O:$P,2,FALSE)<>""),VLOOKUP($B14,$O:$P,2,FALSE),$B14),IF($B14<>"",$B14,"")) | H14: FALSE | I14: =_xlfn.TEXTJOIN(" ",TRUE,J14,K14) | J14: {=IFERROR(IF(AND($B$16<>"",$H$16<>""),_xlfn.LET( _xlpm.result, IF($H$16="First Name", INDEX($E$18:$E$27,MATCH(TRUE,INDEX(ISNUMBER(SEARCH(LOWER($E$18:$E$27),LOWER(B14))),0),0)), INDEX($E$18:$E$27,MATCH(TRUE,INDEX(ISNUMBER(SEARCH(LOWER($F$18:$F$27),LOWER(B14))),0),0)) ), IF(_xlpm.result=0,"",_xlpm.result) ),""),"")} | K14: {=IFERROR(IF(AND($B$16<>"",$H$16<>""), _xlfn.LET( _xlpm.result, IF($H$16="Second Name", INDEX($F$18:$F$27,MATCH(TRUE,INDEX(ISNUMBER(SEARCH(LOWER($F$18:$F$27),LOWER(B14))),0),0)), INDEX($E$18:$E$27,MATCH(TRUE,INDEX(ISNUMBER(SEARCH(LOWER($E$18:$E$27),LOWER(B14))),0),0)) ), IF(_xlpm.result=0,"",_xlpm.result) ), ""),"")} | L14: =_xlfn.TEXTJOIN(", ",TRUE,K14,J14) | N14: Sales | O14: Harper Sloan | P14: harper.sloan@FakeDemoData.com | Q14: HS | S14: Pro Tip: Grab client PRODCUT4 and names string from the meeting invite in the Outlook Schedule Assistant.
A15: *If no Client Contact Type is selected and the PRODUCT4 is not @DemoData.com or @demodata.com, the contact will be added to all client PRODCUT4 | E15: =IFERROR(IF(AND($B15<>"",VLOOKUP($B15,$O:$P,2,FALSE)<>""),VLOOKUP($B15,$O:$P,2,FALSE),$B15),IF($B15<>"",$B15,"")) | H15: FALSE | I15: =_xlfn.TEXTJOIN(" ",TRUE,J15,K15) | J15: {=IFERROR(IF(AND($B$16<>"",$H$16<>""),_xlfn.LET( _xlpm.result, IF($H$16="First Name", INDEX($E$18:$E$27,MATCH(TRUE,INDEX(ISNUMBER(SEARCH(LOWER($E$18:$E$27),LOWER(B15))),0),0)), INDEX($E$18:$E$27,MATCH(TRUE,INDEX(ISNUMBER(SEARCH(LOWER($F$18:$F$27),LOWER(B15))),0),0)) ), IF(_xlpm.result=0,"",_xlpm.result) ),""),"")} | K15: {=IFERROR(IF(AND($B$16<>"",$H$16<>""), _xlfn.LET( _xlpm.result, IF($H$16="Second Name", INDEX($F$18:$F$27,MATCH(TRUE,INDEX(ISNUMBER(SEARCH(LOWER($F$18:$F$27),LOWER(B15))),0),0)), INDEX($E$18:$E$27,MATCH(TRUE,INDEX(ISNUMBER(SEARCH(LOWER($E$18:$E$27),LOWER(B15))),0),0)) ), IF(_xlpm.result=0,"",_xlpm.result) ), ""),"")} | L15: =_xlfn.TEXTJOIN(", ",TRUE,K15,J15) | N15: CSM | O15: Elijah Myers | P15: elijah.myers@FakeDemoData.com | Q15: EM
A16: Paste Client Names String & Select Matching Component | B16: Barnes,William; Chen, Maya; Navarro,Theo; Reed,Noaln; | H16: Second Name | N16: CSM | O16: Evelyn Grant | P16: evelyn.grant@FakeDemoData.com | Q16: EG
E17: FN | F17: LN | G17: Full Name | N17: IM | O17: Jameson Cole | P17: jameson.cole@FakeDemoData.com | Q17: JC | R17: Note: If client PRODCUT4 do not use either first or second name, you can still use the client name string and then manually assign each full name from the drop-down menu. The auto populate formula will not work once a select is made from the drop-down menu.
A18: Kick Off Call PRODUCT4 ls (If Known) | E18: {=_xlfn.LET( _xlpm.names, _xlfn.TEXTSPLIT($B$16,, ";", TRUE), _xlpm.trimmed, TRIM(_xlpm.names), _xlpm.fixed, IF(ISNUMBER(SEARCH(",", _xlpm.trimmed)), TRIM(_xlfn.TEXTAFTER(_xlpm.trimmed, ",") & " " & _xlfn.TEXTBEFORE(_xlpm.trimmed, ",")), _xlpm.trimmed), _xlpm.first, _xlfn.TEXTBEFORE(_xlpm.fixed, " "), _xlpm.last, _xlfn.TEXTAFTER(_xlpm.fixed, " ", -1), _xlfn.HSTACK(_xlpm.first, _xlpm.last) )} -> William | F18: Barnes | G18: {=TRANSPOSE(_xlfn.TEXTSPLIT(B16,";",TRUE,TRUE))} -> Barnes,William | N18: CSM | O18: Scarlett Wells | P18: scarlett.wells@FakeDemoData.com | Q18: SW
A19: Date | B19: 46079 | E19: Maya | F19: Chen | G19: Chen, Maya | N19: CSM | O19: Benjamin Fox | P19: benjamin.fox@FakeDemoData.com | Q19: BF
A20: Time | B20: 1:00 PM EST | E20: Theo | F20: Navarro | G20: Navarro,Theo | N20: Sales | O20: Grace Turner | P20: grace.turner@FakeDemoData.com | Q20: GT
E21: Noaln | F21: Reed | G21: Reed,Noaln | N21: IM | O21: Michael Dawson | P21: michael.dawson@FakeDemoData.com | Q21: MD
A22: Most Recent Build Specs Edit: | B22: Updated on 2025-08-20 @ 9:23 AM by JLB | N22: Sales | O22: Lily DemoData2el | P22: lily.DemoData2el@FakeDemoData.com | Q22: LP
N23: IM | O23: Alexander Ruiz | P23: alexander.ruiz@FakeDemoData.com | Q23: AR
N24: CSM | O24: Chloe Kim | P24: chloe.kim@FakeDemoData.com | Q24: CK
N25: CSM | O25: Daniel Ortiz | P25: daniel.ortiz@FakeDemoData.com | Q25: DO
N26: Sales | O26: Zoe Parker | P26: zoe.parker@FakeDemoData.com | Q26: ZP
N27: Sales | O27: Matthew Stone | P27: matthew.stone@FakeDemoData.com | Q27: MS
E28: Primary Name | F28: =CHOOSE($D6,IF(I6<>"",I6,""),IF(I7<>"",I7,""),IF(I8<>"",I8,""),IF(I9<>"",I9,""),IF(I10<>"",I10,""),IF(I11<>"",I11,""),IF(I12<>"",I12,""),IF(I13<>"",I13,""),IF(I14<>"",I14,""),IF(I15<>"",I15,"")) -> Theo Navarro | N28: CSM | O28: Nora Greene | P28: nora.greene@FakeDemoData.com | Q28: NG
E29: Primary PRODCUT4 | F29: =CHOOSE($D6,IF(B6<>"",B6,""),IF(B7<>"",B7,""),IF(B8<>"",B8,""),IF(B9<>"",B9,""),IF(B10<>"",B10,""),IF(B11<>"",B11,""),IF(B12<>"",B12,""),IF(B13<>"",B13,""),IF(B14<>"",B14,""),IF(B15<>"",B15,"")) -> t.navarro@demodata.com | N29: IM | O29: Samuel Lowe | P29: samuel.lowe@FakeDemoData.com | Q29: SL
N30: CSM | O30: Audrey Kimball | P30: audrey.kimball@FakeDemoData.com | Q30: AK
N31: Sales | O31: William Barnes | P31: william.barnes@FakeDemoData.com | Q31: WB
N32: CSM | O32: Penelope Hart | P32: penelope.hart@FakeDemoData.com | Q32: PH
N33: Sales | O33: Henry Vega | P33: henry.vega@FakeDemoData.com | Q33: HV
N34: CSM | O34: Victoria Lane | P34: victoria.lane@FakeDemoData.com | Q34: VL
N35: CSM | O35: Caleb Bishop | P35: caleb.bishop@FakeDemoData.com | Q35: CB
N36: CSM | O36: Leah Adler | P36: leah.adler@FakeDemoData.com | Q36: LA
N37: Sales | O37: Owen Pratt | P37: owen.pratt@FakeDemoData.com | Q37: OP
N38: Sales | O38: Ruby Ellis | P38: ruby.ellis@FakeDemoData.com | Q38: RE
N39: CSM | O39: Gavin Park | P39: gavin.park@FakeDemoData.com | Q39: GP
N40: CSM | O40: Maya Chen | P40: maya.chen@FakeDemoData.com | Q40: MC
N41: IM | O41: Nolan Reed | P41: nolan.reed@FakeDemoData.com | Q41: NR
... N44: IM | O44: Clara Doyle | P44: clara.doyle@FakeDemoData.com | Q44: CD

Sheet Program Config
A1: {=IF($C$8="","Client Build Specs",_xlfn.IFS($C$27=0,$C$8,$C$27="n/a",$C$8,$C$27>0,IFERROR(_xlfn.CONCAT(""&(C8)&IF(C27<>""," - "&($C$27),"")&IF(H2<>""," - "&(H2)&"")),"c8")))} -> INTEGRATION_AUTO_SHEET - 2026 - New Build | G1: Market: | H1: MARKET4 | I1: Platform: | J1: LATEST (Default) | M1: =IF(OR($L$2='Drop Down Lists'!$AV$20,$L$2='Drop Down Lists'!$AV$21,$L$2='Drop Down Lists'!$AV$22,$L$2='Drop Down Lists'!$AV$24,$L$2='Drop Down Lists'!$AV$23),"Pick Follow Up Date & Reason from Drop-Down Lists ⬇️⬇️","")
A2: Client Build Folder Link: | C2: https://www.linkedin.com/in/jo-ann-balsamo/ | G2: SPEC Type: | H2: New Build | L2: =IFERROR(VLOOKUP($I$2,'Drop Down Lists'!$AU$20:$AW$24,2,FALSE),IF(AND(I2="",I4<>""),'Drop Down Lists'!$AV$24,"")) | N2: =_xlfn.CONCAT(""&(TEXT(TODAY()+7,"YYYY-MM-DD"))&" - 1 Week") -> 2026-03-05 - 1 Week
A3: Client Build Specs Edit Link: | C3: https://www.linkedin.com/in/jo-ann-balsamo/ | G3: Build Specs View Only Link: | H3: https://www.linkedin.com/in/jo-ann-balsamo/ | N3: =_xlfn.CONCAT(""&(TEXT(TODAY()+14,"YYYY-MM-DD"))&" - 2 Weeks") -> 2026-03-12 - 2 Weeks
A4: DOC1 Data Source | C4: https://www.linkedin.com/in/jo-ann-balsamo/ | G4: =IF(OR($I$2="Ticket",$I$2="GENINTEGRATION 31 Migration",$J$14<>"",$J$14<>"n/a"),"JLB Ticket Link:", "") -> JLB Ticket Link: | L4: {=_xlfn.IFS(OR($L$2='Drop Down Lists'!$AV$20:$AV$24),_xlfn.CONCAT("Additional Notes / Comments to be included:"&"",""))} -> #N/A | N4: =_xlfn.CONCAT(""&(TEXT(TODAY()+21,"YYYY-MM-DD"))&" - 3 Weeks") -> 2026-03-19 - 3 Weeks
A5: =IF($H$2<>"New Build","CRM Account Link", "CRM Opportunity Link") -> CRM Opportunity Link | C5: https://www.linkedin.com/in/jo-ann-balsamo/ | G5: Program LK Link: | L5: =IFERROR(VLOOKUP($L$2,'Drop Down Lists'!$AV$20:$AW$24,2,FALSE),"") | N5: =_xlfn.CONCAT(""&(TEXT(TODAY()+30,"YYYY-MM-DD"))&" - 30 Days") -> 2026-03-28 - 30 Days
A6: =IF($H$2<>"New Build","DOC1 Link", "DOC1 Transfer Form Link") -> DOC1 Transfer Form Link | C6: https://www.linkedin.com/in/jo-ann-balsamo/ | G6: PRODUCT2 MARKET2 Link: | N6: =_xlfn.CONCAT(""&(TEXT(TODAY()+60,"YYYY-MM-DD"))&" - 60 Days") -> 2026-04-27 - 60 Days
N7: =_xlfn.CONCAT(""&(TEXT(TODAY()+90,"YYYY-MM-DD"))&" - 90 Days") -> 2026-05-27 - 90 Days
A8: Opportunity/File Name | C8: {=LEFT(MID(CELL("filename"),SEARCH("[",CELL("filename"))+1, SEARCH("]",CELL("filename"))-SEARCH("[",CELL("filename"))-1),LEN(MID(CELL("filename"),SEARCH("[",CELL("filename"))+1, SEARCH("]",CELL("filename"))-SEARCH("[",CELL("filename"))-1))-17)} -> INTEGRATION_AUTO_SHEET | G8: Product(s): | H8: PRODUCT2 | I8: Rostering: | J8: LMS3 Rostering + PROD7 | N8: Client Requested Date:
A9: Institution Name (Finance Name): | C9: JLB Integration DEMO | G9: User Name Formats: | H9: Type1 | I9: Provide User Name Format:
A10: DOC1/Account Name: | C10: DEMO | E10: Program Name & Default AP: | F10: =TRIM(IFERROR(IF(C10<>"", _xlfn.TEXTBEFORE(C10, "("), ""), C10)) -> DEMO | H10: New✨ Program Name, AP, & IPR | I10: www IPR: | J10: =TRIM(IFERROR(IF(AND(C10<>"",F10<>""),"0.0.0.0:255.255.255.255",""),"")) -> 0.0.0.0:255.255.255.255
A11: =HYPERLINK(_xlfn.CONCAT("https://www.google.com/search?q="&(SUBSTITUTE($C$8," ","+"))&"+Address"),"State") -> State | C11: Alabama (AL) | E11: =HYPERLINK(_xlfn.CONCAT("https://www.google.com/search?q="&(SUBSTITUTE($C$8," ","+"))&"+Address"),"Zip Code:") -> Zip Code:
A12: =HYPERLINK(_xlfn.CONCAT("https://www.google.com/search?q="&(SUBSTITUTE($C$9," ","+"))&"+Address"),"Client Homepage URL") -> Client Homepage URL | C12: https://www.linkedin.com/in/jo-ann-balsamo/ | E12: =IFERROR(IF($C$32="","AUTO /PUBLIC/:",$A$32),"/PUBLIC/") -> AUTO /PUBLIC/: | F12: =TRIM( IFERROR( IF($C$32<>"", IF(AND(LEFT($C$32,1)="/",RIGHT($C$32,1)="/"), $C$32, "/" & TRIM($C$32) & "/" ), IF(ISNUMBER(SEARCH("www.",$C$12)), "/" & _xlfn.TEXTBEFORE(_xlfn.TEXTAFTER($C$12,"www."),".") & "/", "/" & _xlfn.TEXTBEFORE(_xlfn.TEXTAFTER($C$12,"https://"),".") & "/" ) ), "") ) -> /linkedin/ | H12: New✨ The AUTO /PUBLIC/ will be generated from the client's URL; override this by entering a /PUBLIC/ in C32
A13: Time Zone | C13: (GMT -8.0) Pacific Time (US & Canada)
A14: Client Integration Method | C14: LMS1 - GENINTEGRATION 31 Link & Course NAV | E14: 3-Letter Initials: | G14: LMS/Launchpad Environment:
A15: JLB Contract | L15: {=_xlfn.IFS(OR($L$2='Drop Down Lists'!$AV$20:$AV$23),_xlfn.CONCAT("⬆️⬆️ Copy this note into you Outlook Calendar as a follow up reminder!")&IF(AND(I4<>"",L$16='Drop Down Lists'!$AV$24),_xlfn.CONCAT(" 📢 A simplified note is included below for JLB ⬇️⬇️"),""),TRUE,IF($L$2='Drop Down Lists'!$AV$24,"⬆️⬆️ Copy this note into your JLB Ticket"),"","")} -> FALSE
A16: Primary Contract Dates | C16: Start Date: | D16: 46023 | E16: End Date: | F16: 46387 | G16: Target Launch Date: | H16: 46081 | L16: =IF(AND($I$2<>"", $I$4<>""),'Drop Down Lists'!$AV$24,"")
A17: Primary Contract Group | Type | C17: Per Hour | F17: Contract Group Name | H17: User Session Limit | I17: User Session Timeframe | J17: Concurrent Session Cap | L17: =IFERROR(VLOOKUP($L$16,'Drop Down Lists'!$AV$24:$AW$24,2,FALSE),"")
A18: Revenue | C18: 100 | D18: =HYPERLINK("https://www.linkedin.com/in/jo-ann-balsamo","PAGE2:") -> PAGE2: | E18: No | F18: =TRIM(IF(AND($C$17="Sessions - Per Student",$C$20<>""),(_xlfn.CONCAT("^"&($C$20)&"$ License")),IF(AND($C$17="Sessions - Per Student",$C$18<>"",$C$19<>""),(_xlfn.CONCAT("^"&($C$18/$C$19)&"$ Student Licenses")),IF(AND($C$17="DemoData1 Sessions",$C$20<>""),(_xlfn.CONCAT("^"&($C$20)&"$ DemoData1 License Program")),IF(AND($C$17="DemoData1 Sessions",$C$18<>"",$C$19<>""),(_xlfn.CONCAT("^"&($C$18/$C$19)&"$ DemoData1 License Program")),IF(OR($C$17="Sessions - Contract 1",$C$17="Sessions - Site Licenses"),"Contract 1",IF($C$17="PRODUCT2","PRODUCT2",IF($C$17="Sessions - DemoDataPlus","DemoDataPlus",IF($C$17="Per Hour","Default",IF($C$17="Sessions - Per Student","Check Inputs for Number of Sessions",IF($C$17="DemoData1 Sessions","Check Inputs for Number of Enrollment",""))))))))))) -> Default | J18: =IF($C$17<>"",_xlfn.UNICHAR(9744), _xlfn.UNICHAR(9744)) -> ☐
A19: {=_xlfn.IFS(LEFT($C$17,8)="Sessions","Cost Per Session", $C$17="DemoData1 Sessions", "Cost Per Session",$C$17="Per Hour", "Cost Per Hour",$C$17="PRODUCT2", "",TRUE,"Cost Per Hour")} -> Cost Per Hour | C19: 1 | D19: Monthly Billing: | E19: No | F19: Revenue | G19: Start Date | End Date | H19: Type | I19: Target | J19: IsBilledMonthly
A20: {=_xlfn.IFS(LEFT($C$17,8)="Sessions","Number of Sessions", $C$17="DemoData1 Sessions", "Number of School Enrollment",$C$17="PRODUCT2","",$C$17="Per Hour", "Number of Hours",TRUE,"Number of Hours")} -> Number of Hours | C20: 100 | D20: PROD187: | E20: Yes | F20: =IF(AND($C$18<>"",$C$19<>"",$C$20<>"",$C$17<>"PRODUCT2"),IF(ROUND(SUM($C$19*$C$20),2)=ROUND(SUM($C$18),2),ROUND(SUM($C$18),2),_xlfn.CONCAT("Math is not mathing! Check "&($A$18)&", "&($A$19)&" & "&($A$20)&"")),IF($C$18<>"",ROUND(SUM($C$18),2),IF(AND($C$19<>"",$C$20<>"",$C$17<>"PRODUCT2"),($C$19*$C$20),_xlfn.CONCAT("You need data! Check "&IF($C$18="",_xlfn.CONCAT(""&($A$18),IF(AND($C$19="",$C$20=""),_xlfn.CONCAT(", "&($A$19)&" & "&($A$20)&""),IF(OR($C$19="",$C$20=""),_xlfn.CONCAT(" & "&IF($C$19="",$A$19,$A$20))))),IF(AND($C$19="",$C$20=""),_xlfn.CONCAT(""&($A$19)&" & "&($A$20)&""),IF(OR($C$19="",$C$20=""),_xlfn.CONCAT(""&IF($C$19="",$A$19,$A$20))))))))) -> 100 | G20: =TRIM(IF(AND($D$16<>"",$F$16<>""),_xlfn.CONCAT(""&TEXT($D$16,"mm/dd/yyy")&" | "&TEXT($F$16,"mm/dd/yyy")&""),"Check Dates")) -> 01/01/2026 | 12/31/2026 | H20: {=TRIM(_xlfn.IFS(LEFT($C$17,8)="Sessions","Per Session",$C$17="DemoData1 Sessions","Per Session",$C$17="PRODUCT2","Per Session",$C$17="Per Hour","Per Hour",$C$17="n/a","Check Type",TRUE,""))} -> Per Hour | I20: =TRIM(IF(AND($C$18<>"",$C$19<>"",$C$20<>"",$C$17<>"PRODUCT2",ROUND(SUM($C$19*$C$20),2)=ROUND(SUM($C$18),2),OR(LEFT($C$17,8)="Sessions",LEFT($C$17,5)="DemoData1")),ROUND(SUM($C$18/'Drop Down Lists'!$AV$2),2),IF(AND(LEFT($C$17,8)<>"Sessions",LEFT($C$17,5)<>"DemoData1",$C$20<>"",$C$18<>"",$C$19<>"",$C$17<>"PRODUCT2"),ROUND(SUM($C$20),2),IF(AND($C$18<>"",OR(LEFT($C$17,8)="Sessions",LEFT($C$17,5)="DemoData1")),ROUND(SUM($C$18/'Drop Down Lists'!$AV$2),2),IF(AND($C$20<>"",$C$19<>"",OR(LEFT($C$17,8)="Sessions",LEFT($C$17,5)="DemoData1")),ROUND(SUM($C$19*$C$20)/'Drop Down Lists'!$AV$2,2),IF(AND($C$20<>"",$C$17="Per Hour"),ROUND(SUM($C$20),2),IF(AND($C$17="PRODUCT2",$C$18<>""),ROUND(SUM($C$18/'Drop Down Lists'!$AV$2),2),IF(AND($C$18<>"",$C$19<>"",$C$17="Per Hour"),ROUND(SUM($C$18/$C$19),2),_xlfn.CONCAT("You need data! Check "&IF($C$18="",_xlfn.CONCAT(""&($A$18),IF(AND($C$19="",$C$20=""),_xlfn.CONCAT(", "&($A$19)&" & "&($A$20)&""),IF(OR($C$19="",$C$20=""),_xlfn.CONCAT(" & "&IF($C$19="",$A$19,$A$20))))),IF(AND($C$19="",$C$20=""),_xlfn.CONCAT(""&($A$19)&" & "&($A$20)&""),IF(OR($C$19="",$C$20=""),_xlfn.CONCAT(""&IF($C$19="",$A$19,$A$20)))))))))))))) -> 100 | J20: =IF($E$19="Yes", _xlfn.UNICHAR(9745),_xlfn.UNICHAR(9744)) -> ☐
A21: Secondary Contract Dates | C21: Start Date: | E21: End Date: | G21: Target Launch Date:
A22: Secondary Contract Group | Type | F22: Contract Group Name | H22: User Session Limit | I22: User Session Timeframe | J22: Concurrent Session Cap
A23: Revenue | D23: =HYPERLINK("https://www.linkedin.com/in/jo-ann-balsamo","PAGE2:") -> PAGE2: | F23: =IF(AND($C$22="Sessions - Per Student",$C$25<>""),(_xlfn.CONCAT("^"&($C$25)&"$ License")),IF(AND($C$22="Sessions - Per Student",$C$23<>"",$C$24<>""),(_xlfn.CONCAT("^"&($C$23/$C$24)&"$ License")),IF(AND($C$22="DemoData1 Sessions",$C$25<>""),(_xlfn.CONCAT("^"&($C$25)&"$ DemoData1 License Program")),IF(AND($C$22="DemoData1 Sessions",$C$23<>"",$C$24<>""),(_xlfn.CONCAT("^"&($C$23/$C$24)&"$ DemoData1 License Program")),IF(OR($C$22="Sessions - Advanced Per Year",$C$22="Sessions - Site Licenses"),"Contract 1",IF($C$22="PRODUCT2","PRODUCT2",IF($C$22="Sessions - DemoDataPlus","DemoDataPlus",IF($C$22="Per Hour","Default",IF($C$22="Sessions - Per Student","Check Inputs for Number of Sessions",IF($C$22="DemoData1 Sessions","Check Inputs for Number of Enrollment","")))))))))) | J23: =IF($C$22<>"",_xlfn.UNICHAR(9744), _xlfn.UNICHAR(9744)) -> ☐
A24: {=_xlfn.IFS(LEFT($C$22,8)="Sessions","Cost Per Session", $C$22="DemoData1 Sessions", "Cost Per Session",$C$22="PRODUCT2","",$C$22="Per Hour", "Cost Per Hour",TRUE,"Cost Per Hour")} -> Cost Per Hour | D24: Monthly Billing: | F24: Revenue | G24: Start Date | End Date | H24: Type | I24: Target | J24: IsBilledMonthly
A25: {=_xlfn.IFS(LEFT($C$22,8)="Sessions","Number of Sessions", $C$22="DemoData1 Sessions", "Number of School Enrollment",$C$22="PRODUCT2","",$C$22="Per Hour", "Number of Hours",TRUE,"Number of Hours")} -> Number of Hours | D25: PROD187: | F25: =IF(AND($C$23<>"",$C$24<>"",$C$25<>"",$C$22<>"PRODUCT2"),IF(ROUND(SUM($C$24*$C$25),2)=ROUND(SUM($C$23),2),ROUND(SUM($C$23),2),_xlfn.CONCAT("Math is not mathing! Check "&($A$23)&", "&($A$24)&" & "&($A$25)&"")),IF($C$23<>"",ROUND(SUM($C$23),2),IF(AND($C$24<>"",$C$25<>"",$C$22<>"PRODUCT2"),($C$24*$C$25),_xlfn.CONCAT("You need data! Check "&IF($C$23="",_xlfn.CONCAT(""&($A$23),IF(AND($C$24="",$C$25=""),_xlfn.CONCAT(", "&($A$24)&" & "&($A$25)&""),IF(OR($C$24="",$C$25=""),_xlfn.CONCAT(" & "&IF($C$24="",$A$24,$A$25))))),IF(AND($C$24="",$C$25=""),_xlfn.CONCAT(""&($A$24)&" & "&($A$25)&""),IF(OR($C$24="",$C$25=""),_xlfn.CONCAT(""&IF($C$24="",$A$24,$A$25))))))))) -> You need data! Check Revenue, Cost Per Hour & Number of Hours | G25: =IF(AND($D$21<>"",$F$21<>""),_xlfn.CONCAT(""&TEXT($D$21,"mm/dd/yyy")&" | "&TEXT($F$21,"mm/dd/yyy")&""),"Check Dates") -> Check Dates | H25: {=_xlfn.IFS(LEFT($C$22,8)="Sessions","Per Session", $C$22="DemoData1 Sessions", "Per Session",$C$22="PRODUCT2", "Per Session",$C$22="Per Hour", "Per Hour",$C$22="n/a", "Check Type",TRUE,"")} | I25: =IF(AND($C$23<>"",$C$24<>"",$C$25<>"",$C$22<>"PRODUCT2",ROUND(SUM($C$24*$C$25),2)=ROUND(SUM($C$23),2),OR(LEFT($C$22,8)="Sessions",LEFT($C$22,5)="DemoData1")),ROUND(SUM($C$23/20),2),IF(AND(LEFT($C$22,8)<>"Sessions",LEFT($C$22,5)<>"DemoData1",$C$25<>"",$C$23<>"",$C$24<>"",$C$22<>"PRODUCT2"),ROUND(SUM($C$25),2),IF(AND($C$23<>"",OR(LEFT($C$22,8)="Sessions",LEFT($C$22,5)="DemoData1")),ROUND(SUM($C$23/'Drop Down Lists'!$AV$2),2),IF(AND($C$25<>"",$C$24<>"",OR(LEFT($C$22,8)="Sessions",LEFT($C$22,5)="DemoData1")),ROUND(SUM($C$24*$C$25)/'Drop Down Lists'!$AV$2,2),IF(AND($C$25<>"",$C$22="Per Hour"),ROUND(SUM($C$25),2),IF(AND($C$22="PRODUCT2",$C$23<>""),ROUND(SUM($C$23/'Drop Down Lists'!$AV$2),2),IF(AND($C$23<>"",$C$24<>"",$C$22="Per Hour"),ROUND(SUM($C$23/$C$24),2),_xlfn.CONCAT("You need data! Check "&IF($C$23="",_xlfn.CONCAT(""&($A$23),IF(AND($C$24="",$C$25=""),_xlfn.CONCAT(", "&($A$23)&" & "&($A$25)&""),IF(OR($C$24="",$C$25=""),_xlfn.CONCAT(" & "&IF($C$24="",$A$24,$A$25))))),IF(AND($C$24="",$C$25=""),_xlfn.CONCAT(""&($A$24)&" & "&($A$25)&""),IF(OR($C$24="",$C$25=""),_xlfn.CONCAT(""&IF($C$24="",$A$24,$A$25))))))))))))) -> You need data! Check Revenue, Revenue & Number of Hours | J25: =IF($E$24="Yes", _xlfn.UNICHAR(9745),_xlfn.UNICHAR(9744)) -> ☐
A26: DemoData2 Configuration | H26: Link to CST | L26: {=_xlfn.IFS($C$14="LM7 - GENINTEGRATION 31",HYPERLINK("https://www.linkedin.com/in/jo-ann-balsamo","LM7 Developer Configuration"), $C$14="LMS8 - GENINTEGRATION 31", "LMS8 Client Response Collection", $C$14="LMS5 - GENINTEGRATION 31", "LMS5 Client Response Collection", $C$14="LMS6 - GENINTEGRATION 31", "LMS6 Client Response Collection",TRUE,"")} | M26: {=_xlfn.IFS($C$14="LM7 - GENINTEGRATION 31",HYPERLINK("https://www.linkedin.com/in/jo-ann-balsamo","https://www.linkedin.com/in/jo-ann-balsamo"), $C$14="LMS8 - GENINTEGRATION 31", "Update LMS9 / LMS8 Components 1-5 Once Response is Received from Client",$C$14="LMS5 - GENINTEGRATION 31", "Update LMS5 Components 1-6 Once Response is Received from Client",$C$14="LMS6 - GENINTEGRATION 31", "", TRUE,"")}
A27: DemoData2 Program ID | C27: 2026 | H27: DemoData2 Monthly Report CSM PRODCUT4: | I27: =TRIM(IFERROR(IF(AND('Program Contacts & Kickoff'!B2<>"",VLOOKUP('Program Contacts & Kickoff'!B2,'Program Contacts & Kickoff'!$I:$J,2,FALSE)<>""),VLOOKUP('Program Contacts & Kickoff'!B2,'Program Contacts & Kickoff'!$I:$J,2,FALSE),'Program Contacts & Kickoff'!E2),IF('Program Contacts & Kickoff'!B2<>"",'Program Contacts & Kickoff'!E2,""))) -> leah.adler@FakeDemoData.com | L27: {=_xlfn.IFS($C$14="LM7 - GENINTEGRATION 31","Username",$C$14="LMS5 - GENINTEGRATION 31","(1) LMS5 CID",$C$14="LMS8 - GENINTEGRATION 31",IF(F34="","DomPRODUCT4 n","Unique PRODUCT4"),$C$14="LMS6 - GENINTEGRATION 31", "(1) LMS6 Platform ID",TRUE,"")} | M27: {=_xlfn.IFS($C$14="LM7 - GENINTEGRATION 31","joann.balsamo@ PRODUCT4.com", $C$14="LMS5 - GENINTEGRATION 31", "= DemoData3 CID",$C$14="LMS8 - GENINTEGRATION 31", IF($F$34<>"",$F$34,"https://www.linkedin.com/in/jo-ann-balsamo"),$C$14="LMS6 - GENINTEGRATION 31", "= DemoData3 Issuer", TRUE,"")}
A28: DemoData727 | C28: NONCE-nonce-NONCE2-nonce3-nonce | H28: DemoData2 Monthly Report Sales PRODCUT4: | I28: =TRIM(IFERROR(IF(AND('Program Contacts & Kickoff'!B3<>"",VLOOKUP('Program Contacts & Kickoff'!B3,'Program Contacts & Kickoff'!$I:$J,2,FALSE)<>""),VLOOKUP('Program Contacts & Kickoff'!B3,'Program Contacts & Kickoff'!$I:$J,2,FALSE),'Program Contacts & Kickoff'!E3),IF('Program Contacts & Kickoff'!B3<>"",'Program Contacts & Kickoff'!E3,""))) -> gavin.park@FakeDemoData.com | L28: {=_xlfn.IFS($C$14="LM7 - GENINTEGRATION 31","PW", $C$14="LMS8 - GENINTEGRATION 31", "(1) LMS9 / LMS8 CID", $C$14="LMS5 - GENINTEGRATION 31", "(2) LMS5 Issuer", $C$14="LMS6 - GENINTEGRATION 31", "(2) LMS6 CID",TRUE,"")} | M28: {=_xlfn.IFS($C$14="LM7 - GENINTEGRATION 31","DemoData2023LATEST1$", $C$14="LMS5 - GENINTEGRATION 31", "= DemoData3 Issuer", $C$14="LMS8 - GENINTEGRATION 31", "= DemoData3 CID", $C$14="LMS6 - GENINTEGRATION 31", "= DemoData3 CID",TRUE,"")}
A29: Uppercase DemoData727 | C29: =UPPER(C28) -> NONCE-NONCE-NONCE2-NONCE3-NONCE | H29: {=_xlfn.IFS($C$14="LM7 - GENINTEGRATION 31","", $C$14="LMS8 - GENINTEGRATION 31", "", $C$14="LMS4", "X.509 Certificate File Name:", $C$14="LMS10", "X.509 Certificate File Name:", $C$14="LMS3", "LMS3 ID File Name:",TRUE,"")} | I29: {=_xlfn.IFS($C$14="LM7 - GENINTEGRATION 31","",$C$14="LMS8 - GENINTEGRATION 31","",$C$14="LMS4",IF(Concats!$A$8<>"",_xlfn.CONCAT(""&(SUBSTITUTE(UPPER(Concats!$A$8),"/",""))&"_LMS4_x509_Cert"),"Please Provide a PUBLIC DemoData2h"),$C$14="LMS10",IF(Concats!$A$8<>"",_xlfn.CONCAT(""&(SUBSTITUTE(UPPER(Concats!$A$8),"/",""))&"_GENINTEGRATION_x509_Cert"),"Please Provide a PUBLIC DemoData2h"),$C$14="LMS3",IF(Concats!$A$8<>"",_xlfn.CONCAT(""&(SUBSTITUTE(UPPER(Concats!$A$8),"/",""))&"_LMS3_ID"),"Please Provide a PUBLIC DemoData2h"),TRUE,"")} | L29: {=_xlfn.IFS($C$14="LM7 - GENINTEGRATION 31","Manual Registration >> Register a new Application", $C$14="LMS5 - GENINTEGRATION 31", "(3) LMS5 Public DemoData27set URL", $C$14="LMS8 - GENINTEGRATION 31", "(2) LMS9 / LMS8 DemoData27set URL", $C$14="LMS6 - GENINTEGRATION 31", "(3) LMS6 Deployment ID",TRUE,"")} | M29: {=_xlfn.IFS($C$14="LM7 - GENINTEGRATION 31","", $C$14="LMS8 - GENINTEGRATION 31", " = DemoData3 DemoData27set URL", $C$14="LMS5 - GENINTEGRATION 31", " = DemoData3 DemoData27set URL", $C$14="LMS6 - GENINTEGRATION 31", "= DemoData3 Deployment ID",TRUE,"")}
A30: {=_xlfn.IFS($C$14="LMS4", (HYPERLINK("https://www.linkedin.com/in/jo-ann-balsamo","X.509 Certificate:")), $C$14="LMS10",(HYPERLINK("https://www.linkedin.com/in/jo-ann-balsamo","x.509 Certificate:")),$C$14="LMS3",(HYPERLINK("https://www.linkedin.com/in/jo-ann-balsamo","LMS3 District ID:")), $C$14="LMS11","", TRUE, (HYPERLINK("https://www.linkedin.com/in/jo-ann-balsamo","DemoData27:")))} -> DemoData27: | C30: Nonce7 | H30: {=_xlfn.IFS($C$14="LM7 - GENINTEGRATION 31","LM7 Developer Application DemoData27", $C$14="LMS8 - GENINTEGRATION 31", "", $C$14="LMS4", "Link to Client X.509 File:", $C$14="LMS10", "Link to Client X.509 File:",$C$14="LMS3", "Link to LMS3 ID File:",TRUE,"")} | L30: {=_xlfn.IFS($C$14="LM7 - GENINTEGRATION 31","Application ID", $C$14="LMS5 - GENINTEGRATION 31", "(4) LMS5 Open ID Connect EP", $C$14="LMS8 - GENINTEGRATION 31", "(3) LMS9 / LMS8 OpenID Connect OA EP", $C$14="LMS6 - GENINTEGRATION 31", "(4) LMS6 Public DemoData27set URL",TRUE,"")} | M30: {=_xlfn.IFS($C$14="LM7 - GENINTEGRATION 31","Enter LM7 Developer Application ID-->", $C$14="LMS8 - GENINTEGRATION 31", "= DemoData3 ALU", $C$14="LMS5 - GENINTEGRATION 31", "= DemoData3 ALU", $C$14="LMS6 - GENINTEGRATION 31", "= DemoData3 DemoData27set URL",TRUE,"")}
A31: {=_xlfn.IFS($C$14="LMS4", "", $C$14="LMS3", "",$C$14="LMS11", "",$C$14="LMS10", "",TRUE, (HYPERLINK("https://www.linkedin.com/in/jo-ann-balsamo","DemoData72:")))} -> DemoData72: | C31: Nocne8 | H31: {=_xlfn.IFS($C$14="LM7 - GENINTEGRATION 31","LM7 Developer DemoData72", $C$14="LMS8 - GENINTEGRATION 31", "", TRUE,"")} | L31: {=_xlfn.IFS($C$14="LM7 - GENINTEGRATION 31","Application Name", $C$14="LMS5 - GENINTEGRATION 31", "(5) LMS5 Access Token URL", $C$14="LMS8 - GENINTEGRATION 31", "(4) LMS9 / LMS8 Issuer", $C$14="LMS6 - GENINTEGRATION 31", "(5) LMS6 Access Token URL",TRUE,"")} | M31: {=_xlfn.IFS($C$14="LM7 - GENINTEGRATION 31",_xlfn.CONCAT("DemoData.com "&UPPER(SUBSTITUTE(Concats!$A$8,"/",""))&" GENINTEGRATION 31"), $C$14="LMS5 - GENINTEGRATION 31", "NOT used in DemoData3 Build", $C$14="LMS8 - GENINTEGRATION 31", "= DemoData3 Issuer",$C$14="LMS6 - GENINTEGRATION 31", "NOT used in DemoData3 Build", TRUE,"")}
A32: Manual /PUBLIC/ Override: | D32: New ✨ The AUTO /PUBLIC/ will be used unless over-ridden with a manually entered /PUBLIC/ in C32; if not overriding the AUTO /PUBLIC/, this manual field can be left blank | L32: {=_xlfn.IFS($C$14="LM7 - GENINTEGRATION 31","Description", $C$14="LMS5 - GENINTEGRATION 31", "(6) LMS5 Deployment ID", $C$14="LMS8 - GENINTEGRATION 31", "(5) LMS9 / LMS8 Deployment ID", $C$14="LMS6 - GENINTEGRATION 31", "(6) LMS6 OA Request URL",TRUE,"")} | M32: {=_xlfn.IFS(C14="LM7 - GENINTEGRATION 31",IF(C8<>"",_xlfn.CONCAT("LM7 GENINTEGRATION 31 for DemoData.com and "&(SUBSTITUTE(SUBSTITUTE($C$8,"(",""),")",""))&""),"This component requires the Client/Program Name"),$C$14="LMS5 - GENINTEGRATION 31", "= DemoData3 Deployment ID", $C$14="LMS8 - GENINTEGRATION 31","=DemoData3 Deployment ID",$C$14="LMS6 - GENINTEGRATION 31", "= DemoData3 ALU",TRUE,"")}
A33: {=_xlfn.IFS($C$14="LMS4","",$C$14="LMS10","",C14="LMS3",(""),$C$14="LMS11","", TRUE,(HYPERLINK("https://www.linkedin.com/in/jo-ann-balsamo","DemoData3 Configuration")))} -> DemoData3 Configuration | C33: {=_xlfn.IFS($C$14="LMS4","",$C$14="LMS10","",C14="LMS3",(""),$C$14="LMS11","",TRUE,"DemoData3 Common Custom Parameters & Recommended Build Note configured on the DemoData3 CCP Tab ⬇️⬇️")} -> DemoData3 Common Custom Parameters & Recommended Build Note configured on the DemoData3 CCP Tab ⬇️⬇️ | H33: {=_xlfn.IFS($C$14="LMS4","",$C$14="LMS10","",C14="LMS3",(""),$C$14="LMS11","",TRUE,"Link to DemoData3 Common Custom Parameters")} -> Link to DemoData3 Common Custom Parameters | L33: {=IF(H34="",_xlfn.IFS($C$14="LM7 - GENINTEGRATION 31","DomPRODUCT4 n",$C$14="LMS8 - GENINTEGRATION 31","",$C$14="LMS1 - GENINTEGRATION 31 Link & Course NAV","",$C$14="LMS1 - GENINTEGRATION 31 - All Types of Placement","",TRUE,""),"Unique PRODUCT4")} -> Unique PRODUCT4 | M33: {=_xlfn.IFS($C$14="LM7 - GENINTEGRATION 31",IF($F$34="","api.DemoData3.com",RIGHT($F$34,21)),$C$14="LMS8 - GENINTEGRATION 31","",$C$14="LMS1 - GENINTEGRATION 31 Link & Course NAV","",$C$14="LMS1 - GENINTEGRATION 31 - All Types of Placement","",TRUE,"")}
A34: {=_xlfn.IFS($C$14="LMS4","",$C$14="LMS10","",$C$14="LMS3",(""),$C$14="LMS11","",TRUE,"Client URL:")} -> Client URL: | C34: https://www.linkedin.com/in/jo-ann-balsamo/ | E34: Unique PRODUCT4 (If Needed) | H34: Program Info for Unique PRODUCT4 Spreadsheet | I34: =IF(F34<>"",IF(AND($F$10<>"",$C$27<>""),(_xlfn.CONCAT($F$10)&" | "&($C$27)&" | "&($C$14)&" "&IF($I$2="GENINTEGRATION 31 Migration","Migration",_xlfn.CONCAT(" | "&($I$2)))&IF('Program Contacts & Kickoff'!B1<>"", _xlfn.CONCAT(" IM: "&('Program Contacts & Kickoff'!B1)&" | "&(TEXT(TODAY(),"YYYY-MM-DD"))&""),"")&" "&IF($C$35<>"",_xlfn.CONCAT("DemoData3 Property: "&($C$35)),"")&" "&IF($I$4<>"",_xlfn.CONCAT("JLB Ticket Link: "&($I$4)),"")),"This component requires a Unique PRODUCT4 and the Program Name & ID"),"") | L34: {=_xlfn.IFS($C$14="LM7 - GENINTEGRATION 31","My Inegration Supports (Toggle)", $C$14="LMS8 - GENINTEGRATION 31", "", $C$14="LMS1 - GENINTEGRATION 31 Link & Course NAV", "",$C$14="LMS1 - GENINTEGRATION 31 - All Types of Placement", "",TRUE,"")} | M34: {=_xlfn.IFS($C$14="LM7 - GENINTEGRATION 31","Enable GENINTEGRATION 31", $C$14="LMS8 - GENINTEGRATION 31", "", $C$14="LMS1 - GENINTEGRATION 31 Link & Course NAV", "", $C$14="LMS1 - GENINTEGRATION 31 - All Types of Placement", "",TRUE,"")}
A35: {=_xlfn.IFS($C$14="LMS4", "", $C$14="LMS3", "",$C$14="LMS10", "",$C$14="LMS11","",TRUE, "DemoData3 Property Link:")} -> DemoData3 Property Link: | C35: https://www.linkedin.com/in/jo-ann-balsamo/ | E35: DemoData3 Property Name: | F35: =IF(AND($F$10<>"",$C$27<>""),(_xlfn.CONCAT($F$10)&" | "&($C$27)),"This component requires the Program Name & the Program ID") -> DEMO | 2026 | G35: DemoData3 Name: | H35: =IF(AND(Concats!$A$8<>"",$C$14<>""),(_xlfn.CONCAT(UPPER(SUBSTITUTE(Concats!$A$8,"/","")))&" | "&($C$14)),"This component requires the PUBLIC & the Integration Method") -> LINKEDIN | LMS1 - GENINTEGRATION 31 Link & Course NAV | L35: {=_xlfn.IFS($C$14="LM7 - GENINTEGRATION 31","LI InitiPRODUCT4 tion URL", $C$14="LMS8 - GENINTEGRATION 31", "", $C$14="LMS1 - GENINTEGRATION 31 Link & Course NAV", "",$C$14="LMS1 - GENINTEGRATION 31 - All Types of Placement", "",TRUE,"")} | M35: {=_xlfn.IFS($C$14="LM7 - GENINTEGRATION 31",IF(C34<>"",C34,"This component requires the DemoData3 Client URL"), $C$14="LMS8 - GENINTEGRATION 31", "", $C$14="LMS1 - GENINTEGRATION 31 Link & Course NAV", "",$C$14="LMS1 - GENINTEGRATION 31 - All Types of Placement", "",TRUE,"")}
A36: {=_xlfn.IFS($C$14=0, "", $C$14="n/a", "", $C$14>0, IFERROR(VLOOKUP($C$14,'Drop Down Lists'!$B$4:$AO$63,2,FALSE),""))} -> GENINTEGRATION 31 Handler | C36: {=IFERROR(_xlfn.IFS($C$14=0,"",$C$14="n/a","",$C$14='Drop Down Lists'!B14,IFERROR(VLOOKUP($C$14,'Drop Down Lists'!$B$4:$AO$63,2,FALSE),"")),"")} | L36: Tool Redirect URL(s) | M36: =IF(C34<>"",C34,"This component requires the DemoData3 Client URL") -> https://www.linkedin.com/in/jo-ann-balsamo/
A37: {=_xlfn.IFS($C$14=0, "", $C$14="n/a", "", $C$14>0, IFERROR(VLOOKUP($C$14,'Drop Down Lists'!$B$4:$AO$63,3,FALSE),""))} -> GENINTEGRATION 31 Issuer | G37: {=TRIM(_xlfn.IFS($C$14=0,"",$C$14="n/a","",$C$14>0,IFERROR(VLOOKUP($C$14,'Drop Down Lists'!$B$4:$AO$63,4,FALSE),"This Component has not been configured yet")))} -> https://www.linkedin.com/in/jo-ann-balsamo | L37: Tool JWKS URL | M37: =IF(C34<>"",_xlfn.CONCAT(""&($C$34)&"/DemoData27set"&""),"This component requires the DemoData3 Client URL") -> https://www.linkedin.com/in/jo-ann-balsamo//DemoData27set
A38: {=_xlfn.IFS($C$14=0, "", $C$14="n/a", "", $C$14>0, IFERROR(VLOOKUP($C$14,'Drop Down Lists'!$B$4:$AO$63,5,FALSE),""))} -> CID | G38: {=TRIM(_xlfn.IFS($C$14=0,"",$C$14="n/a","",$C$14>0,IFERROR(VLOOKUP($C$14,'Drop Down Lists'!$B$4:$AO$63,6,FALSE),"")))} -> This component to be provided by the client | L38: Signing Algorithm | M38: RS256
A39: {=_xlfn.IFS($C$14=0, "", $C$14="n/a", "", $C$14>0, IFERROR(VLOOKUP($C$14,'Drop Down Lists'!$B$4:$AO$63,7,FALSE),""))} -> ALU | G39: {=TRIM(_xlfn.IFS($C$14=0,"",$C$14="n/a","",$C$14>0,IFERROR(VLOOKUP($C$14,'Drop Down Lists'!$B$4:$AO$63,8,FALSE),"This Component has not been configured yet")))} -> Please Selct an LMS Environment from the drop-down menu | L39: Manage Placements >> Register
A40: {=_xlfn.IFS($C$14=0, "", $C$14="n/a", "", $C$14>0, IFERROR(VLOOKUP($C$14,'Drop Down Lists'!$B$4:$AO$63,9,FALSE),""))} -> DemoData27 Set URL | G40: {=TRIM(_xlfn.IFS($C$14=0,"",$C$14="n/a","",$C$14>0,IFERROR(VLOOKUP($C$14,'Drop Down Lists'!$B$4:$AO$63,10,FALSE),"This Component has not been configured yet")))} -> Please Selct an LMS Environment from the drop-down menu | L40: Placement Name | M40: {=_xlfn.IFS($C$14="LM7 - GENINTEGRATION 31",_xlfn.CONCAT("DemoData.com "&UPPER(SUBSTITUTE(Concats!$A$8,"/",""))&" GENINTEGRATION 31"), $C$14="LMS8 - GENINTEGRATION 31", "= DemoData3 Deployment ID", TRUE,"")}
A41: {=_xlfn.IFS($C$14=0, "", $C$14="n/a", "", $C$14>0, IFERROR(VLOOKUP($C$14,'Drop Down Lists'!$B$4:$AO$63,11,FALSE),""))} -> Deployment ID | G41: {=TRIM(_xlfn.IFS($C$14=0,"",$C$14="n/a","",$C$14>0,IFERROR(VLOOKUP($C$14,'Drop Down Lists'!$B$4:$AO$63,12,FALSE),"")))} -> This component to be provided by the client | L41: Description | M41: =IF(C8<>"",_xlfn.CONCAT("LM7 GENINTEGRATION 31 for DemoData.com and "&SUBSTITUTE($C$8,"_"," ")&""),"This component requires the Client/Program Name") -> LM7 GENINTEGRATION 31 for DemoData.com and INTEGRATION AUTO SHEET
A42: {=_xlfn.IFS($C$14=0, "", $C$14="n/a", "", $C$14>0, IFERROR(VLOOKUP($C$14,'Drop Down Lists'!$B$4:$AO$63,13,FALSE),""))} -> GENINTEGRATION 31 Response | L42: Type | M42: Select "Course Tool" from the Drop Down
A43: {=_xlfn.IFS($C$14=0, "", $C$14="n/a", "", $C$14>0, IFERROR(VLOOKUP($C$14,'Drop Down Lists'!$B$4:$AO$63,14,FALSE),""))} -> Issuer | C43: {=TRIM(IFERROR(_xlfn.IFS($C$14=0,"",$C$14="n/a","",$C$14>0,IFERROR(VLOOKUP($C$14,'Drop Down Lists'!$B$4:$AO$63,15,FALSE),"This Component has not been configured yet")),"This component has not been configured yet"))} -> https://www.linkedin.com/in/jo-ann-balsamo//NONCE-nonce-NONCE2-nonce3-nonce | L43: Allow Student Access | M43: Toggle ON
A44: {=_xlfn.IFS($C$14=0, "", $C$14="n/a", "", $C$14>0, IFERROR(VLOOKUP($C$14,'Drop Down Lists'!$B$4:$AO$63,16,FALSE),""))} -> CID | C44: {=TRIM(_xlfn.IFS($C$14=0,"",$C$14="n/a","",$C$14>0,IFERROR(VLOOKUP($C$14,'Drop Down Lists'!$B$4:$AO$63,17,FALSE),"This Component has not been configured yet")))} -> This component will be configured by DemoData3 | E44: {=_xlfn.IFS($C$14="LM7 - GENINTEGRATION 31","Record DemoData3 Response HERE -->", $C$14="LMS8 - GENINTEGRATION 31", "Record DemoData3 Response HERE -->", $C$14="LMS1 - GENINTEGRATION 31 Link & Course NAV", "Record DemoData3 Response HERE -->",$C$14="LMS1 - GENINTEGRATION 31 - All Types of Placement", "Record DemoData3 Response HERE -->",$C$14="LMS6 - GENINTEGRATION 31", "Record DemoData3 Response HERE -->",TRUE,"")} -> Record DemoData3 Response HERE --> | L44: Launch in New Window | M44: Toggle ON
A45: {=_xlfn.IFS($C$14=0, "", $C$14="n/a", "", $C$14>0, IFERROR(VLOOKUP($C$14,'Drop Down Lists'!$B$4:$AO$63,18,FALSE),""))} -> Deployment ID | C45: {=TRIM(_xlfn.IFS($C$14=0,"",$C$14="n/a","",$C$14>0,IFERROR(IF(J1="LEGACY",VLOOKUP($C$14,'Drop Down Lists'!$B$4:$AO$63,19,FALSE),VLOOKUP($C$14,'Drop Down Lists'!$B$4:$AO$63,20,FALSE)),"This Component has not been configured yet")))} -> This component will be configured by DemoData3 | E45: {=_xlfn.IFS($C$14="LM7 - GENINTEGRATION 31","Record DemoData3 Response HERE -->", $C$14="LMS8 - GENINTEGRATION 31", "Record DemoData3 Response HERE -->", $C$14="LMS1 - GENINTEGRATION 31 Link & Course NAV", "Record DemoData3 Response HERE -->",$C$14="LMS1 - GENINTEGRATION 31 - All Types of Placement", "Record DemoData3 Response HERE -->",$C$14="LMS6 - GENINTEGRATION 31", "Record DemoData3 Response HERE -->",TRUE,"")} -> Record DemoData3 Response HERE --> | L45: Target Link URI | M45: =IF(C34<>"",C34,"This componet requires the DemoData3 Client URL") -> https://www.linkedin.com/in/jo-ann-balsamo/
A46: {=_xlfn.IFS($C$14=0,"",$C$14="n/a","",$C$14>0,IFERROR(IF(VLOOKUP($C$14,'Drop Down Lists'!$B$4:$AO$63,21,FALSE)<>"This Component is not neccessary",VLOOKUP($C$14,'Drop Down Lists'!$B$4:$AO$63,21,FALSE),""),""))} -> LATEST ILU | C46: {=TRIM(_xlfn.IFS($C$14=0,"",$C$14="n/a","",$C$14>0,IFERROR(IF(J1="LEGACY",VLOOKUP($C$14,'Drop Down Lists'!$B$4:$AO$63,22,FALSE),VLOOKUP($C$14,'Drop Down Lists'!$B$4:$AO$63,23,FALSE)),"This Component has not been configured yet")))} -> https://www.linkedin.com/in/jo-ann-balsamo | L46: Icon URL (Optional - Can be left blank) | M46: https://www.linkedin.com/in/jo-ann-balsamo
A47: {=_xlfn.IFS($C$14=0,"",$C$14="n/a","",$C$14>0,IFERROR(IF(VLOOKUP($C$14,'Drop Down Lists'!$B$4:$AO$63,24,FALSE)<>"This Component is not neccessary",VLOOKUP($C$14,'Drop Down Lists'!$B$4:$AO$63,24,FALSE),""),""))} -> LATEST Redirection URL | C47: {=TRIM(_xlfn.IFS($C$14=0,"",$C$14="n/a","",$C$14>0,IFERROR(IF(J1="LEGACY",VLOOKUP($C$14,'Drop Down Lists'!$B$4:$AO$63,25,FALSE),VLOOKUP($C$14,'Drop Down Lists'!$B$4:$AO$63,26,FALSE)),"This Component has not been configured yet")))} -> https://www.linkedin.com/in/jo-ann-balsamo | L47: Common Custom Parameters for Global or Placement Level
A48: JLB AM. & Access Links | L48: oath_custom_DemoData27 | M48: =IF(C14="LM7 - GENINTEGRATION 31",IF(C30<>"",_xlfn.CONCAT("OA_consumer_DemoData27="&($C$30)&""),"This componet requires the Client DemoData27"),"")
A49: =IF($J$2="LEGACY","Link to LEGACY", "Link to LATEST") -> Link to LATEST | C49: {=TRIM(_xlfn.IFS($C$28=0,"This component has not been configured yet",$C$28="n/a","n/a",$C$28>0,IF($J$1="LEGACY",HYPERLINK("https://www.linkedin.com/in/jo-ann-balsamo"),HYPERLINK("https://www.linkedin.com/in/jo-ann-balsamo"))))} -> https://www.linkedin.com/in/jo-ann-balsamo | L49: custom_ap | N49: =IF($C$14="LM7 - GENINTEGRATION 31",IF(M49<>"",_xlfn.CONCAT("custom_ap="&($M$49)&"")," <-- This component requires a Custom AP to be entered"),"")
A50: Link to Client AM | C50: {=TRIM(_xlfn.IFS($C$28=0,"This component has not been configured yet",$C$28="n/a","n/a",$C$28>0,HYPERLINK(_xlfn.CONCAT("https://www.linkedin.com/in/"&(Concats!$A$8)&"AM"))))} -> https://www.linkedin.com/in//linkedin/AM | L50: LM7 Developer & DemoData3 Crosswalk
A51: PUBLIC Name (Not Valid for SSO Programs) | C51: =TRIM(IF(Concats!$A$8<>"",HYPERLINK(_xlfn.CONCAT("https://www.linkedin.com/in/"&(SUBSTITUTE(Concats!$A$8,"/",""))&"")),"This component has not been configured yet")) -> https://www.linkedin.com/in/linkedin | L51: LM7 Issuer (=DemoData3 Issuer) | M51: {=_xlfn.IFS($C$14=0, "", $C$14="n/a", "", $C$14>0, IFERROR(VLOOKUP($C$14,'Drop Down Lists'!$B$4:$AO$63,4,FALSE),"This Component has not been configured yet"))} -> https://www.linkedin.com/in/jo-ann-balsamo
A52: UAU AM Username | C52: {=TRIM(_xlfn.IFS(Concats!$A$8="","This component has not been configured yet",Concats!$A$8="n/a","n/a",Concats!$A$8<>"",_xlfn.CONCAT(""&(SUBSTITUTE(SUBSTITUTE(Concats!$A$8,"/",""),"-",".")&"@PRODUCT4.com"))))} -> linkedin@PRODUCT4.com | L52: LM7 Public DemoData27set URL (=DemoData3 DemoData27set URL) | M52: {=IF($C$14="LM7 - GENINTEGRATION 31",(_xlfn.IFS($N$30=0,"This component requires the LM7 Developer Application ID",$N$30="n/a","",$N$30>0,_xlfn.CONCAT("https://www.linkedin.com/in/jo-ann-balsamo"&($N$30)&"/jwks.json"))),"")}
A53: UAP | C53: =TRIM(IF(C27>0,_xlfn.CONCAT("DemoData"&(C27)&""),"This component has not been configured yet")) -> DemoData2026 | L53: LM7 ATE (Not Captured in DemoData3) | M53: https://www.linkedin.com/in/jo-ann-balsamo
L54: LM7 OIDC OA Request EP (=DemoData3 ALU) | M54: {=_xlfn.IFS($C$14=0, "", $C$14="n/a", "", $C$14>0, IFERROR(VLOOKUP($C$14,'Drop Down Lists'!$B$4:$AO$63,8,FALSE),"This Component has not been configured yet"))} -> Please Selct an LMS Environment from the drop-down menu
L55: {=_xlfn.IFS($C$14="LM7 - GENINTEGRATION 31","", $C$14="LMS8 - GENINTEGRATION 31", "", $C$14="LMS1 - GENINTEGRATION 31 Link & Course NAV", "",$C$14="LMS1 - GENINTEGRATION 31 - All Types of Placement", "",TRUE,"")} | M55: {=_xlfn.IFS($C$14="LM7 - GENINTEGRATION 31","", $C$14="LMS8 - GENINTEGRATION 31", "", $C$14="LMS1 - GENINTEGRATION 31 Link & Course NAV", "",$C$14="LMS1 - GENINTEGRATION 31 - All Types of Placement", "",TRUE,"")}
A56: MARKET2 Special Course Hours | Normed to MARKET2 Templates #### & 3418 on 7/25/2025 | D56: Sunday | E56: Monday | F56: Tuesday | G56: Wednesday | H56: Thursday | I56: Friday | J56: Saturday | L56: {=_xlfn.IFS($C$14="LM7 - GENINTEGRATION 31","", $C$14="LMS8 - GENINTEGRATION 31", "", $C$14="LMS1 - GENINTEGRATION 31 Link & Course NAV", "",$C$14="LMS1 - GENINTEGRATION 31 - All Types of Placement", "",TRUE,"")} | M56: {=_xlfn.IFS($C$14="LM7 - GENINTEGRATION 31","", $C$14="LMS8 - GENINTEGRATION 31", "", $C$14="LMS1 - GENINTEGRATION 31 Link & Course NAV", "",$C$14="LMS1 - GENINTEGRATION 31 - All Types of Placement", "",TRUE,"")}
A57: 2nd Subject1 | C57: Open | D57: {=_xlfn.IFS($C$13='Drop Down Lists'!$AS$3,"6 PM",$C$13='Drop Down Lists'!$AS$4,"5 PM",$C$13='Drop Down Lists'!$AS$5,"4 PM",$C$13='Drop Down Lists'!$AS$6,"3 PM",$C$13='Drop Down Lists'!$AS$7,"3 PM",$C$13='Drop Down Lists'!$AS$8,"7 PM",TRUE,"6 PM")} -> 3 PM | E57: {=_xlfn.IFS($C$13='Drop Down Lists'!$AS$3,"6 PM",$C$13='Drop Down Lists'!$AS$4,"5 PM",$C$13='Drop Down Lists'!$AS$5,"4 PM",$C$13='Drop Down Lists'!$AS$6,"3 PM",$C$13='Drop Down Lists'!$AS$7,"3 PM",$C$13='Drop Down Lists'!$AS$8,"7 PM",TRUE,"6 PM")} -> 3 PM | F57: {=_xlfn.IFS($C$13='Drop Down Lists'!$AS$3,"6 PM",$C$13='Drop Down Lists'!$AS$4,"5 PM",$C$13='Drop Down Lists'!$AS$5,"4 PM",$C$13='Drop Down Lists'!$AS$6,"3 PM",$C$13='Drop Down Lists'!$AS$7,"3 PM",$C$13='Drop Down Lists'!$AS$8,"7 PM",TRUE,"6 PM")} -> 3 PM | G57: {=_xlfn.IFS($C$13='Drop Down Lists'!$AS$3,"6 PM",$C$13='Drop Down Lists'!$AS$4,"5 PM",$C$13='Drop Down Lists'!$AS$5,"4 PM",$C$13='Drop Down Lists'!$AS$6,"3 PM",$C$13='Drop Down Lists'!$AS$7,"3 PM",$C$13='Drop Down Lists'!$AS$8,"7 PM",TRUE,"6 PM")} -> 3 PM | H57: {=_xlfn.IFS($C$13='Drop Down Lists'!$AS$3,"6 PM",$C$13='Drop Down Lists'!$AS$4,"5 PM",$C$13='Drop Down Lists'!$AS$5,"4 PM",$C$13='Drop Down Lists'!$AS$6,"3 PM",$C$13='Drop Down Lists'!$AS$7,"3 PM",$C$13='Drop Down Lists'!$AS$8,"7 PM",TRUE,"6 PM")} -> 3 PM | I57: {=_xlfn.IFS($C$13='Drop Down Lists'!$AS$3,"6 PM",$C$13='Drop Down Lists'!$AS$4,"5 PM",$C$13='Drop Down Lists'!$AS$5,"4 PM",$C$13='Drop Down Lists'!$AS$6,"3 PM",$C$13='Drop Down Lists'!$AS$7,"3 PM",$C$13='Drop Down Lists'!$AS$8,"7 PM",TRUE,"6 PM")} -> 3 PM | J57: {=_xlfn.IFS($C$13='Drop Down Lists'!$AS$3,"6 PM",$C$13='Drop Down Lists'!$AS$4,"5 PM",$C$13='Drop Down Lists'!$AS$5,"4 PM",$C$13='Drop Down Lists'!$AS$6,"3 PM",$C$13='Drop Down Lists'!$AS$7,"3 PM",$C$13='Drop Down Lists'!$AS$8,"7 PM",TRUE,"6 PM")} -> 3 PM | L57: {=_xlfn.IFS($C$14="LM7 - GENINTEGRATION 31","", $C$14="LMS8 - GENINTEGRATION 31", "", $C$14="LMS1 - GENINTEGRATION 31 Link & Course NAV", "",$C$14="LMS1 - GENINTEGRATION 31 - All Types of Placement", "",TRUE,"")} | M57: {=_xlfn.IFS($C$14="LM7 - GENINTEGRATION 31","", $C$14="LMS8 - GENINTEGRATION 31", "", $C$14="LMS1 - GENINTEGRATION 31 Link & Course NAV", "",$C$14="LMS1 - GENINTEGRATION 31 - All Types of Placement", "",TRUE,"")}
C58: Close | D58: {=_xlfn.IFS($C$13='Drop Down Lists'!$AS$3,"12 AM",$C$13='Drop Down Lists'!$AS$4,"11 PM",$C$13='Drop Down Lists'!$AS$5,"10 PM",$C$13='Drop Down Lists'!$AS$6,"9 PM",$C$13='Drop Down Lists'!$AS$7,"9 PM",$C$13='Drop Down Lists'!$AS$8,"1 AM",TRUE,"12 AM")} -> 9 PM | E58: {=_xlfn.IFS($C$13='Drop Down Lists'!$AS$3,"12 AM",$C$13='Drop Down Lists'!$AS$4,"11 PM",$C$13='Drop Down Lists'!$AS$5,"10 PM",$C$13='Drop Down Lists'!$AS$6,"9 PM",$C$13='Drop Down Lists'!$AS$7,"9 PM",$C$13='Drop Down Lists'!$AS$8,"1 AM",TRUE,"12 AM")} -> 9 PM | F58: {=_xlfn.IFS($C$13='Drop Down Lists'!$AS$3,"12 AM",$C$13='Drop Down Lists'!$AS$4,"11 PM",$C$13='Drop Down Lists'!$AS$5,"10 PM",$C$13='Drop Down Lists'!$AS$6,"9 PM",$C$13='Drop Down Lists'!$AS$7,"9 PM",$C$13='Drop Down Lists'!$AS$8,"1 AM",TRUE,"12 AM")} -> 9 PM | G58: {=_xlfn.IFS($C$13='Drop Down Lists'!$AS$3,"12 AM",$C$13='Drop Down Lists'!$AS$4,"11 PM",$C$13='Drop Down Lists'!$AS$5,"10 PM",$C$13='Drop Down Lists'!$AS$6,"9 PM",$C$13='Drop Down Lists'!$AS$7,"9 PM",$C$13='Drop Down Lists'!$AS$8,"1 AM",TRUE,"12 AM")} -> 9 PM | H58: {=_xlfn.IFS($C$13='Drop Down Lists'!$AS$3,"12 AM",$C$13='Drop Down Lists'!$AS$4,"11 PM",$C$13='Drop Down Lists'!$AS$5,"10 PM",$C$13='Drop Down Lists'!$AS$6,"9 PM",$C$13='Drop Down Lists'!$AS$7,"9 PM",$C$13='Drop Down Lists'!$AS$8,"1 AM",TRUE,"12 AM")} -> 9 PM | I58: {=_xlfn.IFS($C$13='Drop Down Lists'!$AS$3,"12 AM",$C$13='Drop Down Lists'!$AS$4,"11 PM",$C$13='Drop Down Lists'!$AS$5,"10 PM",$C$13='Drop Down Lists'!$AS$6,"9 PM",$C$13='Drop Down Lists'!$AS$7,"9 PM",$C$13='Drop Down Lists'!$AS$8,"1 AM",TRUE,"12 AM")} -> 9 PM | J58: {=_xlfn.IFS($C$13='Drop Down Lists'!$AS$3,"12 AM",$C$13='Drop Down Lists'!$AS$4,"11 PM",$C$13='Drop Down Lists'!$AS$5,"10 PM",$C$13='Drop Down Lists'!$AS$6,"9 PM",$C$13='Drop Down Lists'!$AS$7,"9 PM",$C$13='Drop Down Lists'!$AS$8,"1 AM",TRUE,"12 AM")} -> 9 PM
A60: 2nd Subject2 | C60: Open | D60: {=_xlfn.IFS($C$13='Drop Down Lists'!$AS$3,"6 PM",$C$13='Drop Down Lists'!$AS$4,"5 PM",$C$13='Drop Down Lists'!$AS$5,"4 PM",$C$13='Drop Down Lists'!$AS$6,"3 PM",$C$13='Drop Down Lists'!$AS$7,"3 PM",$C$13='Drop Down Lists'!$AS$8,"7 PM",TRUE,"6 PM")} -> 3 PM | E60: {=_xlfn.IFS($C$13='Drop Down Lists'!$AS$3,"6 PM",$C$13='Drop Down Lists'!$AS$4,"5 PM",$C$13='Drop Down Lists'!$AS$5,"4 PM",$C$13='Drop Down Lists'!$AS$6,"3 PM",$C$13='Drop Down Lists'!$AS$7,"3 PM",$C$13='Drop Down Lists'!$AS$8,"7 PM",TRUE,"6 PM")} -> 3 PM | F60: {=_xlfn.IFS($C$13='Drop Down Lists'!$AS$3,"6 PM",$C$13='Drop Down Lists'!$AS$4,"5 PM",$C$13='Drop Down Lists'!$AS$5,"4 PM",$C$13='Drop Down Lists'!$AS$6,"3 PM",$C$13='Drop Down Lists'!$AS$7,"3 PM",$C$13='Drop Down Lists'!$AS$8,"7 PM",TRUE,"6 PM")} -> 3 PM | G60: {=_xlfn.IFS($C$13='Drop Down Lists'!$AS$3,"6 PM",$C$13='Drop Down Lists'!$AS$4,"5 PM",$C$13='Drop Down Lists'!$AS$5,"4 PM",$C$13='Drop Down Lists'!$AS$6,"3 PM",$C$13='Drop Down Lists'!$AS$7,"3 PM",$C$13='Drop Down Lists'!$AS$8,"7 PM",TRUE,"6 PM")} -> 3 PM | H60: {=_xlfn.IFS($C$13='Drop Down Lists'!$AS$3,"6 PM",$C$13='Drop Down Lists'!$AS$4,"5 PM",$C$13='Drop Down Lists'!$AS$5,"4 PM",$C$13='Drop Down Lists'!$AS$6,"3 PM",$C$13='Drop Down Lists'!$AS$7,"3 PM",$C$13='Drop Down Lists'!$AS$8,"7 PM",TRUE,"6 PM")} -> 3 PM | I60: {=_xlfn.IFS($C$13='Drop Down Lists'!$AS$3,"6 PM",$C$13='Drop Down Lists'!$AS$4,"5 PM",$C$13='Drop Down Lists'!$AS$5,"4 PM",$C$13='Drop Down Lists'!$AS$6,"3 PM",$C$13='Drop Down Lists'!$AS$7,"3 PM",$C$13='Drop Down Lists'!$AS$8,"7 PM",TRUE,"6 PM")} -> 3 PM | J60: {=_xlfn.IFS($C$13='Drop Down Lists'!$AS$3,"6 PM",$C$13='Drop Down Lists'!$AS$4,"5 PM",$C$13='Drop Down Lists'!$AS$5,"4 PM",$C$13='Drop Down Lists'!$AS$6,"3 PM",$C$13='Drop Down Lists'!$AS$7,"3 PM",$C$13='Drop Down Lists'!$AS$8,"7 PM",TRUE,"6 PM")} -> 3 PM
C61: Close | D61: {=_xlfn.IFS($C$13='Drop Down Lists'!$AS$3,"12 AM",$C$13='Drop Down Lists'!$AS$4,"11 PM",$C$13='Drop Down Lists'!$AS$5,"10 PM",$C$13='Drop Down Lists'!$AS$6,"9 PM",$C$13='Drop Down Lists'!$AS$7,"9 PM",$C$13='Drop Down Lists'!$AS$8,"1 AM",TRUE,"12 AM")} -> 9 PM | E61: {=_xlfn.IFS($C$13='Drop Down Lists'!$AS$3,"12 AM",$C$13='Drop Down Lists'!$AS$4,"11 PM",$C$13='Drop Down Lists'!$AS$5,"10 PM",$C$13='Drop Down Lists'!$AS$6,"9 PM",$C$13='Drop Down Lists'!$AS$7,"9 PM",$C$13='Drop Down Lists'!$AS$8,"1 AM",TRUE,"12 AM")} -> 9 PM | F61: {=_xlfn.IFS($C$13='Drop Down Lists'!$AS$3,"12 AM",$C$13='Drop Down Lists'!$AS$4,"11 PM",$C$13='Drop Down Lists'!$AS$5,"10 PM",$C$13='Drop Down Lists'!$AS$6,"9 PM",$C$13='Drop Down Lists'!$AS$7,"9 PM",$C$13='Drop Down Lists'!$AS$8,"1 AM",TRUE,"12 AM")} -> 9 PM | G61: {=_xlfn.IFS($C$13='Drop Down Lists'!$AS$3,"12 AM",$C$13='Drop Down Lists'!$AS$4,"11 PM",$C$13='Drop Down Lists'!$AS$5,"10 PM",$C$13='Drop Down Lists'!$AS$6,"9 PM",$C$13='Drop Down Lists'!$AS$7,"9 PM",$C$13='Drop Down Lists'!$AS$8,"1 AM",TRUE,"12 AM")} -> 9 PM | H61: {=_xlfn.IFS($C$13='Drop Down Lists'!$AS$3,"12 AM",$C$13='Drop Down Lists'!$AS$4,"11 PM",$C$13='Drop Down Lists'!$AS$5,"10 PM",$C$13='Drop Down Lists'!$AS$6,"9 PM",$C$13='Drop Down Lists'!$AS$7,"9 PM",$C$13='Drop Down Lists'!$AS$8,"1 AM",TRUE,"12 AM")} -> 9 PM | I61: {=_xlfn.IFS($C$13='Drop Down Lists'!$AS$3,"12 AM",$C$13='Drop Down Lists'!$AS$4,"11 PM",$C$13='Drop Down Lists'!$AS$5,"10 PM",$C$13='Drop Down Lists'!$AS$6,"9 PM",$C$13='Drop Down Lists'!$AS$7,"9 PM",$C$13='Drop Down Lists'!$AS$8,"1 AM",TRUE,"12 AM")} -> 9 PM | J61: {=_xlfn.IFS($C$13='Drop Down Lists'!$AS$3,"12 AM",$C$13='Drop Down Lists'!$AS$4,"11 PM",$C$13='Drop Down Lists'!$AS$5,"10 PM",$C$13='Drop Down Lists'!$AS$6,"9 PM",$C$13='Drop Down Lists'!$AS$7,"9 PM",$C$13='Drop Down Lists'!$AS$8,"1 AM",TRUE,"12 AM")} -> 9 PM
A63: Subject3 | C63: Open | D63: {=_xlfn.IFS($C$13='Drop Down Lists'!$AS$3,"6 PM",$C$13='Drop Down Lists'!$AS$4,"5 PM",$C$13='Drop Down Lists'!$AS$5,"4 PM",$C$13='Drop Down Lists'!$AS$6,"3 PM",$C$13='Drop Down Lists'!$AS$7,"3 PM",$C$13='Drop Down Lists'!$AS$8,"7 PM",TRUE,"6 PM")} -> 3 PM | E63: {=_xlfn.IFS($C$13='Drop Down Lists'!$AS$3,"6 PM",$C$13='Drop Down Lists'!$AS$4,"5 PM",$C$13='Drop Down Lists'!$AS$5,"4 PM",$C$13='Drop Down Lists'!$AS$6,"3 PM",$C$13='Drop Down Lists'!$AS$7,"3 PM",$C$13='Drop Down Lists'!$AS$8,"7 PM",TRUE,"6 PM")} -> 3 PM | F63: {=_xlfn.IFS($C$13='Drop Down Lists'!$AS$3,"6 PM",$C$13='Drop Down Lists'!$AS$4,"5 PM",$C$13='Drop Down Lists'!$AS$5,"4 PM",$C$13='Drop Down Lists'!$AS$6,"3 PM",$C$13='Drop Down Lists'!$AS$7,"3 PM",$C$13='Drop Down Lists'!$AS$8,"7 PM",TRUE,"6 PM")} -> 3 PM | G63: {=_xlfn.IFS($C$13='Drop Down Lists'!$AS$3,"6 PM",$C$13='Drop Down Lists'!$AS$4,"5 PM",$C$13='Drop Down Lists'!$AS$5,"4 PM",$C$13='Drop Down Lists'!$AS$6,"3 PM",$C$13='Drop Down Lists'!$AS$7,"3 PM",$C$13='Drop Down Lists'!$AS$8,"7 PM",TRUE,"6 PM")} -> 3 PM | H63: {=_xlfn.IFS($C$13='Drop Down Lists'!$AS$3,"6 PM",$C$13='Drop Down Lists'!$AS$4,"5 PM",$C$13='Drop Down Lists'!$AS$5,"4 PM",$C$13='Drop Down Lists'!$AS$6,"3 PM",$C$13='Drop Down Lists'!$AS$7,"3 PM",$C$13='Drop Down Lists'!$AS$8,"7 PM",TRUE,"6 PM")} -> 3 PM | I63: {=_xlfn.IFS($C$13='Drop Down Lists'!$AS$3,"6 PM",$C$13='Drop Down Lists'!$AS$4,"5 PM",$C$13='Drop Down Lists'!$AS$5,"4 PM",$C$13='Drop Down Lists'!$AS$6,"3 PM",$C$13='Drop Down Lists'!$AS$7,"3 PM",$C$13='Drop Down Lists'!$AS$8,"7 PM",TRUE,"6 PM")} -> 3 PM | J63: {=_xlfn.IFS($C$13='Drop Down Lists'!$AS$3,"6 PM",$C$13='Drop Down Lists'!$AS$4,"5 PM",$C$13='Drop Down Lists'!$AS$5,"4 PM",$C$13='Drop Down Lists'!$AS$6,"3 PM",$C$13='Drop Down Lists'!$AS$7,"3 PM",$C$13='Drop Down Lists'!$AS$8,"7 PM",TRUE,"6 PM")} -> 3 PM
C64: Close | D64: {=_xlfn.IFS($C$13='Drop Down Lists'!$AS$3,"12 AM",$C$13='Drop Down Lists'!$AS$4,"11 PM",$C$13='Drop Down Lists'!$AS$5,"10 PM",$C$13='Drop Down Lists'!$AS$6,"9 PM",$C$13='Drop Down Lists'!$AS$7,"9 PM",$C$13='Drop Down Lists'!$AS$8,"1 AM",TRUE,"12 AM")} -> 9 PM | E64: {=_xlfn.IFS($C$13='Drop Down Lists'!$AS$3,"12 AM",$C$13='Drop Down Lists'!$AS$4,"11 PM",$C$13='Drop Down Lists'!$AS$5,"10 PM",$C$13='Drop Down Lists'!$AS$6,"9 PM",$C$13='Drop Down Lists'!$AS$7,"9 PM",$C$13='Drop Down Lists'!$AS$8,"1 AM",TRUE,"12 AM")} -> 9 PM | F64: {=_xlfn.IFS($C$13='Drop Down Lists'!$AS$3,"12 AM",$C$13='Drop Down Lists'!$AS$4,"11 PM",$C$13='Drop Down Lists'!$AS$5,"10 PM",$C$13='Drop Down Lists'!$AS$6,"9 PM",$C$13='Drop Down Lists'!$AS$7,"9 PM",$C$13='Drop Down Lists'!$AS$8,"1 AM",TRUE,"12 AM")} -> 9 PM | G64: {=_xlfn.IFS($C$13='Drop Down Lists'!$AS$3,"12 AM",$C$13='Drop Down Lists'!$AS$4,"11 PM",$C$13='Drop Down Lists'!$AS$5,"10 PM",$C$13='Drop Down Lists'!$AS$6,"9 PM",$C$13='Drop Down Lists'!$AS$7,"9 PM",$C$13='Drop Down Lists'!$AS$8,"1 AM",TRUE,"12 AM")} -> 9 PM | H64: {=_xlfn.IFS($C$13='Drop Down Lists'!$AS$3,"12 AM",$C$13='Drop Down Lists'!$AS$4,"11 PM",$C$13='Drop Down Lists'!$AS$5,"10 PM",$C$13='Drop Down Lists'!$AS$6,"9 PM",$C$13='Drop Down Lists'!$AS$7,"9 PM",$C$13='Drop Down Lists'!$AS$8,"1 AM",TRUE,"12 AM")} -> 9 PM | I64: {=_xlfn.IFS($C$13='Drop Down Lists'!$AS$3,"12 AM",$C$13='Drop Down Lists'!$AS$4,"11 PM",$C$13='Drop Down Lists'!$AS$5,"10 PM",$C$13='Drop Down Lists'!$AS$6,"9 PM",$C$13='Drop Down Lists'!$AS$7,"9 PM",$C$13='Drop Down Lists'!$AS$8,"1 AM",TRUE,"12 AM")} -> 9 PM | J64: {=_xlfn.IFS($C$13='Drop Down Lists'!$AS$3,"12 AM",$C$13='Drop Down Lists'!$AS$4,"11 PM",$C$13='Drop Down Lists'!$AS$5,"10 PM",$C$13='Drop Down Lists'!$AS$6,"9 PM",$C$13='Drop Down Lists'!$AS$7,"9 PM",$C$13='Drop Down Lists'!$AS$8,"1 AM",TRUE,"12 AM")} -> 9 PM
B2060: https://www.time-zones-map.com/

Sheet DemoData3 CCP Tab
A1: =IF('Program Config'!$C$14<>"",IF(AND('Program Config'!$C$14<>"LMS3",'Program Config'!$C$14<>"LMS4",'Program Config'!$C$14<>"LMS11",'Program Config'!$C$14<>"LMS10"),"DemoData3 Build Notes",""),"") -> DemoData3 Build Notes | C1: Go Back to Build Specs | E1: {=IF('Program Config'!$C$14<>"",IF(AND('Program Config'!$C$14<>"LMS3",'Program Config'!$C$14<>"LMS4",'Program Config'!$C$14<>"LMS11",'Program Config'!$C$14<>"LMS10"),_xlfn.IFS('Program Config'!$C$14="LMS1 - GENINTEGRATION 31 - All Types of Placement","GENINTEGRATION 22 Parameters",'Program Config'!$C$14="LMS1 - GENINTEGRATION 31 Link & Course NAV","GENINTEGRATION 22 Parameters",'Program Config'!$C$14="LMS8 - GENINTEGRATION 31","GENINTEGRATION 22 Parameters",'Program Config'!$C$14="LMS5 - GENINTEGRATION 31","GENINTEGRATION 22 Parameters",'Program Config'!$C$14="LMS2 - GENINTEGRATION 31","GENINTEGRATION 22 Parameters",'Program Config'!$C$14="LM7 - GENINTEGRATION 31","GENINTEGRATION 22 Parameters",'Program Config'!$C$14="LMS6 - GENINTEGRATION 31","GENINTEGRATION 22 Parameters",TRUE,"GENINTEGRATION 22 Attributes"),""),"")} -> GENINTEGRATION 22 Parameters | F1: {=_xlfn.IFS('Program Config'!$C$14="LMS1 - GENINTEGRATION 31 - All Types of Placement","LMS1 31 ClPRODUCT4 ms", 'Program Config'!$C$14="LMS1 - GENINTEGRATION 31 Link & Course NAV","LMS1 31 ClPRODUCT4 ms", 'Program Config'!$C$14="LMS5 - GENINTEGRATION 31","LMS5 31 ClPRODUCT4 ms", 'Program Config'!$C$14="LMS8 - GENINTEGRATION 31","LMS8 31 ClPRODUCT4 ms",'Program Config'!$C$14="LMS2 - GENINTEGRATION 31","LMS2 31 ClPRODUCT4 ms",'Program Config'!$C$14="LM7 - GENINTEGRATION 31","LM7 31 ClPRODUCT4 ms",'Program Config'!$C$14="LMS6 - GENINTEGRATION 31","LMS6 31 ClPRODUCT4 ms",TRUE,"")} -> LMS1 31 ClPRODUCT4 ms | H1: GENINTEGRATION 22 Parameters | I1: GENINTEGRATION 31 ClPRODUCT4 ms | J1: LM7 | K1: CV | L1: LMS8 | M1: MD | N1: CL | O1: JZ | P1: LM7 Matching | Q1: LM7 31 ClPRODUCT4 ms | R1: LMS1 Matching | S1: LMS1 31 ClPRODUCT4 ms | T1: LMS8 31 Matching | U1: LMS8 31 ClPRODUCT4 ms | V1: LMS6 31 Matching | W1: LMS6 31 ClPRODUCT4 ms | X1: LMS2 31 Matching | Y1: LMS2 31 ClPRODUCT4 ms | Z1: LMS5 31 Matching | AA1: LMS5 31 ClPRODUCT4 ms | AC1: Common Custom Parameters for GENINTEGRATION 22
A2: =IF('Program Config'!$C$14<>"",IF(AND('Program Config'!$C$14<>"LMS3",'Program Config'!$C$14<>"LMS4",'Program Config'!$C$14<>"LMS11",'Program Config'!$C$14<>"LMS10"),"DemoData3 Property Name",""),"") -> DemoData3 Property Name | B2: =IF('Program Config'!$C$14<>"",(IF(AND('Program Config'!$C$14<>"LMS3",'Program Config'!$C$14<>"LMS4",'Program Config'!$C$14<>"LMS11",'Program Config'!$C$14<>"LMS10"),IF(AND('Program Config'!$F$10<>"",'Program Config'!$C$27<>""),_xlfn.CONCAT('Program Config'!$F$10)&" | "&('Program Config'!$C$27),"This component requires the Program Name & the Program ID"),"This Build Configuration does not require an DemoData3")),"") -> DEMO | 2026 | E2: {=IFERROR(_xlfn.IFS($E$1="GENINTEGRATION 22 Parameters",(_xlfn.IFS($F$1=$Q$1,INDEX($P$2:$P$100,MATCH(0,INDEX(COUNTIF($E$1:$E1,$P$2:$P$100)+(COUNTIF($P$2:$P$100,$P$2:$P$100)<>1),0,0),0)),$F$1=$S$1,INDEX($R$2:$R$100,MATCH(0,INDEX(COUNTIF($E$1:$E1,$R$2:$R$100)+(COUNTIF($R$2:$R$100,$R$2:$R$100)<>1),0,0),0)),$F$1=$U$1,INDEX($T$2:$T$100,MATCH(0,INDEX(COUNTIF($E$1:$E1,$T$2:$T$100)+(COUNTIF($T$2:$T$100,$T$2:$T$100)<>1),0,0),0)),$F$1=$W$1,INDEX($V$2:$V$100,MATCH(0,INDEX(COUNTIF($E$1:$E1,$V$2:$V$100)+(COUNTIF($V$2:$V$100,$V$2:$V$100)<>1),0,0),0)),$F$1=$Y$1,INDEX($X$2:$X$100,MATCH(0,INDEX(COUNTIF($E$1:$E1,$X$2:$X$100)+(COUNTIF($X$2:$X$100,$X$2:$X$100)<>1),0,0),0)),$F$1=$AA$1,INDEX($Z$2:$Z$100,MATCH(0,INDEX(COUNTIF($E$1:$E1,$Z$2:$Z$100)+(COUNTIF($Z$2:$Z$100,$Z$2:$Z$100)<>1),0,0),0)),TRUE,"")),$E$1="GENINTEGRATION 22 Attributes",INDEX($H$2:$H$100,MATCH(0,INDEX(COUNTIF($E$1:$E1,$H$2:$H$100)+(COUNTIF($H$2:$H$100,$H$2:$H$100)<>1),0,0),0)),TRUE,""),"")} -> context_id | F2: {=IFERROR(_xlfn.IFS($F$1=$Q$1,_xlfn.XLOOKUP($E2,$P$2:$P$100,Q$2:Q$100)&"",$F$1=$S$1,_xlfn.XLOOKUP($E2,$R$2:$R$100,$S$2:$S$100)&"",$F$1=$Y$1,_xlfn.XLOOKUP($E2,$X$2:$X$100,$Y$2:$Y$100)&"",$F$1=$U$1,_xlfn.XLOOKUP($E2,$T$2:$T$100,$U$2:$U$100)&"",$F$1=$W$1,_xlfn.XLOOKUP($E2,$V$2:$V$100,$W$2:$W$100)&"",$F$1=$AA$1,_xlfn.XLOOKUP($E2,$Z$2:$Z$100,$AA$2:$AA$100)&"",TRUE, ""),"")} -> https://purl.demodata7.org/spec/GENINTEGRATION/clPRODUCT4 m/context|id | G2: {=IFERROR(IF($F2<>"",_xlfn.IFS($F$1="LM7 31 ClPRODUCT4 ms","LM7",$F$1="LMS1 31 ClPRODUCT4 ms","CV",$F$1="LMS2 31 ClPRODUCT4 ms","CL",$F$1="LMS5 31 ClPRODUCT4 ms","JZ",$F$1="LMS8 31 ClPRODUCT4 ms","DL",$F$1="LMS6 31 ClPRODUCT4 ms","MD",TRUE, ""),IF(AND($E$1="GENINTEGRATION 22 Attributes",$E2<>""),"22","")),"")} -> CV | H2: context_id | I2: https://purl.demodata7.org/spec/GENINTEGRATION/clPRODUCT4 m/context|id | J2: Yes | K2: Yes | L2: Yes | M2: Yes | N2: Yes | O2: Yes | P2: =IF(AND($H2<>"",Q2<>""),$H2,"") -> context_id | Q2: =IF($J2="yes",$I2,"") -> https://purl.demodata7.org/spec/GENINTEGRATION/clPRODUCT4 m/context|id | R2: =IF(AND($H2<>"",S2<>""),$H2,"") -> context_id | S2: =IF($K2="yes",$I2,"") -> https://purl.demodata7.org/spec/GENINTEGRATION/clPRODUCT4 m/context|id | T2: =IF(AND($H2<>"",U2<>""),$H2,"") -> context_id | U2: =IF($L2="yes",$I2,"") -> https://purl.demodata7.org/spec/GENINTEGRATION/clPRODUCT4 m/context|id | V2: =IF(AND($H2<>"",W2<>""),$H2,"") -> context_id | W2: =IF($M2="yes",$I2,"") -> https://purl.demodata7.org/spec/GENINTEGRATION/clPRODUCT4 m/context|id | X2: =IF(AND($H2<>"",Y2<>""),$H2,"") -> context_id | Y2: =IF($N2="yes",$I2,"") -> https://purl.demodata7.org/spec/GENINTEGRATION/clPRODUCT4 m/context|id | Z2: =IF(AND($H2<>"",AA2<>""),$H2,"") -> context_id | AA2: =IF($L2="yes",$I2,"") -> https://purl.demodata7.org/spec/GENINTEGRATION/clPRODUCT4 m/context|id | AC2: Copy Context Title to Context ID
A3: =IF('Program Config'!$C$14<>"",IF(AND('Program Config'!$C$14<>"LMS3",'Program Config'!$C$14<>"LMS4",'Program Config'!$C$14<>"LMS11",'Program Config'!$C$14<>"LMS10"),"Adapter Name",""),"") -> Adapter Name | B3: =IF('Program Config'!$C$14<>"",IF(AND('Program Config'!$C$14<>"LMS3",'Program Config'!$C$14<>"LMS4",'Program Config'!$C$14<>"LMS11",'Program Config'!$C$14<>"LMS10"),IF(AND(Concats!$A$8<>"",'Program Config'!$C$14<>""),(_xlfn.CONCAT(UPPER(SUBSTITUTE(Concats!$A$8,"/","")))&" | "&('Program Config'!$C$14)),"This component requires the PUBLIC & the Integration Method"),""),"") -> LINKEDIN | LMS1 - GENINTEGRATION 31 Link & Course NAV | E3: {=IFERROR(_xlfn.IFS($E$1="GENINTEGRATION 22 Parameters",(_xlfn.IFS($F$1=$Q$1,INDEX($P$2:$P$100,MATCH(0,INDEX(COUNTIF($E$1:$E2,$P$2:$P$100)+(COUNTIF($P$2:$P$100,$P$2:$P$100)<>1),0,0),0)),$F$1=$S$1,INDEX($R$2:$R$100,MATCH(0,INDEX(COUNTIF($E$1:$E2,$R$2:$R$100)+(COUNTIF($R$2:$R$100,$R$2:$R$100)<>1),0,0),0)),$F$1=$U$1,INDEX($T$2:$T$100,MATCH(0,INDEX(COUNTIF($E$1:$E2,$T$2:$T$100)+(COUNTIF($T$2:$T$100,$T$2:$T$100)<>1),0,0),0)),$F$1=$W$1,INDEX($V$2:$V$100,MATCH(0,INDEX(COUNTIF($E$1:$E2,$V$2:$V$100)+(COUNTIF($V$2:$V$100,$V$2:$V$100)<>1),0,0),0)),$F$1=$Y$1,INDEX($X$2:$X$100,MATCH(0,INDEX(COUNTIF($E$1:$E2,$X$2:$X$100)+(COUNTIF($X$2:$X$100,$X$2:$X$100)<>1),0,0),0)),$F$1=$AA$1,INDEX($Z$2:$Z$100,MATCH(0,INDEX(COUNTIF($E$1:$E2,$Z$2:$Z$100)+(COUNTIF($Z$2:$Z$100,$Z$2:$Z$100)<>1),0,0),0)),TRUE,"")),$E$1="GENINTEGRATION 22 Attributes",INDEX($H$2:$H$100,MATCH(0,INDEX(COUNTIF($E$1:$E2,$H$2:$H$100)+(COUNTIF($H$2:$H$100,$H$2:$H$100)<>1),0,0),0)),TRUE,""),"")} -> context_label | F3: {=IFERROR(_xlfn.IFS($F$1=$Q$1,_xlfn.XLOOKUP($E3,$P$2:$P$100,Q$2:Q$100)&"",$F$1=$S$1,_xlfn.XLOOKUP($E3,$R$2:$R$100,$S$2:$S$100)&"",$F$1=$Y$1,_xlfn.XLOOKUP($E3,$X$2:$X$100,$Y$2:$Y$100)&"",$F$1=$U$1,_xlfn.XLOOKUP($E3,$T$2:$T$100,$U$2:$U$100)&"",$F$1=$W$1,_xlfn.XLOOKUP($E3,$V$2:$V$100,$W$2:$W$100)&"",$F$1=$AA$1,_xlfn.XLOOKUP($E3,$Z$2:$Z$100,$AA$2:$AA$100)&"",TRUE, ""),"")} -> https://purl.demodata7.org/spec/GENINTEGRATION/clPRODUCT4 m/context|label | G3: {=IFERROR(IF($F3<>"",_xlfn.IFS($F$1="LM7 31 ClPRODUCT4 ms","LM7",$F$1="LMS1 31 ClPRODUCT4 ms","CV",$F$1="LMS2 31 ClPRODUCT4 ms","CL",$F$1="LMS5 31 ClPRODUCT4 ms","JZ",$F$1="LMS8 31 ClPRODUCT4 ms","DL",$F$1="LMS6 31 ClPRODUCT4 ms","MD",TRUE, ""),IF(AND($E$1="GENINTEGRATION 22 Attributes",$E3<>""),"22","")),"")} -> CV | H3: context_label | I3: https://purl.demodata7.org/spec/GENINTEGRATION/clPRODUCT4 m/context|label | J3: Yes | K3: Yes | L3: Yes | M3: Yes | N3: Yes | O3: Yes | P3: =IF(AND($H3<>"",Q3<>""),$H3,"") -> context_label | Q3: =IF($J3="yes",$I3,"") -> https://purl.demodata7.org/spec/GENINTEGRATION/clPRODUCT4 m/context|label | R3: =IF(AND($H3<>"",S3<>""),$H3,"") -> context_label | S3: =IF($K3="yes",$I3,"") -> https://purl.demodata7.org/spec/GENINTEGRATION/clPRODUCT4 m/context|label | T3: =IF(AND($H3<>"",U3<>""),$H3,"") -> context_label | U3: =IF($L3="yes",$I3,"") -> https://purl.demodata7.org/spec/GENINTEGRATION/clPRODUCT4 m/context|label | V3: =IF(AND($H3<>"",W3<>""),$H3,"") -> context_label | W3: =IF($M3="yes",$I3,"") -> https://purl.demodata7.org/spec/GENINTEGRATION/clPRODUCT4 m/context|label | X3: =IF(AND($H3<>"",Y3<>""),$H3,"") -> context_label | Y3: =IF($N3="yes",$I3,"") -> https://purl.demodata7.org/spec/GENINTEGRATION/clPRODUCT4 m/context|label | Z3: =IF(AND($H3<>"",AA3<>""),$H3,"") -> context_label | AA3: =IF($L3="yes",$I3,"") -> https://purl.demodata7.org/spec/GENINTEGRATION/clPRODUCT4 m/context|label | AC3: From | AD3: context_title
A4: =IF('Program Config'!$C$14<>"",IF(AND('Program Config'!$C$14<>"LMS3",'Program Config'!$C$14<>"LMS4",'Program Config'!$C$14<>"LMS11",'Program Config'!$C$14<>"LMS10"),"Recommended DemoData3 Build Settings Note",""),"") -> Recommended DemoData3 Build Settings Note | B4: =TRIM(IF('Program Config'!$C$14<>"",IF(AND('Program Config'!$C$14<>"LMS3",'Program Config'!$C$14<>"LMS4",'Program Config'!$C$14<>"LMS11",'Program Config'!$C$14<>"LMS10"),IF(AND('Program Config'!$C$27<>"",'Program Config'!$H$2<>"",'Program Config'!$C$14<>""),_xlfn.CONCAT("")&IF('Program Config'!$F$10<>"",_xlfn.CONCAT(""&('Program Config'!$F$10)&"",_xlfn.CONCAT(" | Program ID "&('Program Config'!$C$27)&" | "&('Program Config'!$H$2)&IF('Program Config'!$C$14<>"",_xlfn.CONCAT(" | "&('Program Config'!$C$14),"")&IF('Program Contacts & Kickoff'!$B$1<>"",_xlfn.CONCAT(" | IM: "&(VLOOKUP('Program Contacts & Kickoff'!$B$1,'Program Contacts & Kickoff'!$O$2:$Q$475,1,TRUE)&""),""))))))&IF('Program Config'!$H$3<>"",_xlfn.CONCAT(" Build Specs View-Only Link: "&('Program Config'!$H$3)),"")&IF('Program Config'!$F$34<>"",_xlfn.CONCAT(" LMS Required Unique DomPRODUCT4 n: "&('Program Config'!$F$34)),"")&IF('Program Config'!$H$4<>"",_xlfn.CONCAT(" JSM Ticket Link: "&('Program Config'!$H$4)),"")&IF('Program Config'!$H$2="GENINTEGRATION 31 Migration",_xlfn.CONCAT(" Team IM Migration Project Link: "&"https://www.linkedin.com/in/jo-ann-balsamo"),""),"Get to Building! 🔨 🛠️ 🔧 This program has not been configured yet."),"This is true for: • LMS3 Integrations • LMS4 Integrations • LMS10 Integrations • LMS11 Programs"),"")) -> DEMO | Program ID 2026 | New Build | LMS1 - GENINTEGRATION 31 Link & Course NAV | IM: Clara Doyle Build Specs View-Only Link: https://www.linkedin.com/in/jo-ann-balsamo/ | E4: {=IFERROR(_xlfn.IFS($E$1="GENINTEGRATION 22 Parameters",(_xlfn.IFS($F$1=$Q$1,INDEX($P$2:$P$100,MATCH(0,INDEX(COUNTIF($E$1:$E3,$P$2:$P$100)+(COUNTIF($P$2:$P$100,$P$2:$P$100)<>1),0,0),0)),$F$1=$S$1,INDEX($R$2:$R$100,MATCH(0,INDEX(COUNTIF($E$1:$E3,$R$2:$R$100)+(COUNTIF($R$2:$R$100,$R$2:$R$100)<>1),0,0),0)),$F$1=$U$1,INDEX($T$2:$T$100,MATCH(0,INDEX(COUNTIF($E$1:$E3,$T$2:$T$100)+(COUNTIF($T$2:$T$100,$T$2:$T$100)<>1),0,0),0)),$F$1=$W$1,INDEX($V$2:$V$100,MATCH(0,INDEX(COUNTIF($E$1:$E3,$V$2:$V$100)+(COUNTIF($V$2:$V$100,$V$2:$V$100)<>1),0,0),0)),$F$1=$Y$1,INDEX($X$2:$X$100,MATCH(0,INDEX(COUNTIF($E$1:$E3,$X$2:$X$100)+(COUNTIF($X$2:$X$100,$X$2:$X$100)<>1),0,0),0)),$F$1=$AA$1,INDEX($Z$2:$Z$100,MATCH(0,INDEX(COUNTIF($E$1:$E3,$Z$2:$Z$100)+(COUNTIF($Z$2:$Z$100,$Z$2:$Z$100)<>1),0,0),0)),TRUE,"")),$E$1="GENINTEGRATION 22 Attributes",INDEX($H$2:$H$100,MATCH(0,INDEX(COUNTIF($E$1:$E3,$H$2:$H$100)+(COUNTIF($H$2:$H$100,$H$2:$H$100)<>1),0,0),0)),TRUE,""),"")} -> context_title | F4: {=IFERROR(_xlfn.IFS($F$1=$Q$1,_xlfn.XLOOKUP($E4,$P$2:$P$100,Q$2:Q$100)&"",$F$1=$S$1,_xlfn.XLOOKUP($E4,$R$2:$R$100,$S$2:$S$100)&"",$F$1=$Y$1,_xlfn.XLOOKUP($E4,$X$2:$X$100,$Y$2:$Y$100)&"",$F$1=$U$1,_xlfn.XLOOKUP($E4,$T$2:$T$100,$U$2:$U$100)&"",$F$1=$W$1,_xlfn.XLOOKUP($E4,$V$2:$V$100,$W$2:$W$100)&"",$F$1=$AA$1,_xlfn.XLOOKUP($E4,$Z$2:$Z$100,$AA$2:$AA$100)&"",TRUE, ""),"")} -> https://purl.demodata7.org/spec/GENINTEGRATION/clPRODUCT4 m/context|title | G4: {=IFERROR(IF($F4<>"",_xlfn.IFS($F$1="LM7 31 ClPRODUCT4 ms","LM7",$F$1="LMS1 31 ClPRODUCT4 ms","CV",$F$1="LMS2 31 ClPRODUCT4 ms","CL",$F$1="LMS5 31 ClPRODUCT4 ms","JZ",$F$1="LMS8 31 ClPRODUCT4 ms","DL",$F$1="LMS6 31 ClPRODUCT4 ms","MD",TRUE, ""),IF(AND($E$1="GENINTEGRATION 22 Attributes",$E4<>""),"22","")),"")} -> CV | H4: context_title | I4: https://purl.demodata7.org/spec/GENINTEGRATION/clPRODUCT4 m/context|title | J4: Yes | K4: Yes | L4: Yes | M4: Yes | N4: Yes | O4: Yes | P4: =IF(AND($H4<>"",Q4<>""),$H4,"") -> context_title | Q4: =IF($J4="yes",$I4,"") -> https://purl.demodata7.org/spec/GENINTEGRATION/clPRODUCT4 m/context|title | R4: =IF(AND($H4<>"",S4<>""),$H4,"") -> context_title | S4: =IF($K4="yes",$I4,"") -> https://purl.demodata7.org/spec/GENINTEGRATION/clPRODUCT4 m/context|title | T4: =IF(AND($H4<>"",U4<>""),$H4,"") -> context_title | U4: =IF($L4="yes",$I4,"") -> https://purl.demodata7.org/spec/GENINTEGRATION/clPRODUCT4 m/context|title | V4: =IF(AND($H4<>"",W4<>""),$H4,"") -> context_title | W4: =IF($M4="yes",$I4,"") -> https://purl.demodata7.org/spec/GENINTEGRATION/clPRODUCT4 m/context|title | X4: =IF(AND($H4<>"",Y4<>""),$H4,"") -> context_title | Y4: =IF($N4="yes",$I4,"") -> https://purl.demodata7.org/spec/GENINTEGRATION/clPRODUCT4 m/context|title | Z4: =IF(AND($H4<>"",AA4<>""),$H4,"") -> context_title | AA4: =IF($L4="yes",$I4,"") -> https://purl.demodata7.org/spec/GENINTEGRATION/clPRODUCT4 m/context|title | AC4: To | AD4: context_id
E5: {=IFERROR(_xlfn.IFS($E$1="GENINTEGRATION 22 Parameters",(_xlfn.IFS($F$1=$Q$1,INDEX($P$2:$P$100,MATCH(0,INDEX(COUNTIF($E$1:$E4,$P$2:$P$100)+(COUNTIF($P$2:$P$100,$P$2:$P$100)<>1),0,0),0)),$F$1=$S$1,INDEX($R$2:$R$100,MATCH(0,INDEX(COUNTIF($E$1:$E4,$R$2:$R$100)+(COUNTIF($R$2:$R$100,$R$2:$R$100)<>1),0,0),0)),$F$1=$U$1,INDEX($T$2:$T$100,MATCH(0,INDEX(COUNTIF($E$1:$E4,$T$2:$T$100)+(COUNTIF($T$2:$T$100,$T$2:$T$100)<>1),0,0),0)),$F$1=$W$1,INDEX($V$2:$V$100,MATCH(0,INDEX(COUNTIF($E$1:$E4,$V$2:$V$100)+(COUNTIF($V$2:$V$100,$V$2:$V$100)<>1),0,0),0)),$F$1=$Y$1,INDEX($X$2:$X$100,MATCH(0,INDEX(COUNTIF($E$1:$E4,$X$2:$X$100)+(COUNTIF($X$2:$X$100,$X$2:$X$100)<>1),0,0),0)),$F$1=$AA$1,INDEX($Z$2:$Z$100,MATCH(0,INDEX(COUNTIF($E$1:$E4,$Z$2:$Z$100)+(COUNTIF($Z$2:$Z$100,$Z$2:$Z$100)<>1),0,0),0)),TRUE,"")),$E$1="GENINTEGRATION 22 Attributes",INDEX($H$2:$H$100,MATCH(0,INDEX(COUNTIF($E$1:$E4,$H$2:$H$100)+(COUNTIF($H$2:$H$100,$H$2:$H$100)<>1),0,0),0)),TRUE,""),"")} -> context_type | F5: {=IFERROR(_xlfn.IFS($F$1=$Q$1,_xlfn.XLOOKUP($E5,$P$2:$P$100,Q$2:Q$100)&"",$F$1=$S$1,_xlfn.XLOOKUP($E5,$R$2:$R$100,$S$2:$S$100)&"",$F$1=$Y$1,_xlfn.XLOOKUP($E5,$X$2:$X$100,$Y$2:$Y$100)&"",$F$1=$U$1,_xlfn.XLOOKUP($E5,$T$2:$T$100,$U$2:$U$100)&"",$F$1=$W$1,_xlfn.XLOOKUP($E5,$V$2:$V$100,$W$2:$W$100)&"",$F$1=$AA$1,_xlfn.XLOOKUP($E5,$Z$2:$Z$100,$AA$2:$AA$100)&"",TRUE, ""),"")} -> https://purl.demodata7.org/spec/GENINTEGRATION/clPRODUCT4 m/context|type | G5: {=IFERROR(IF($F5<>"",_xlfn.IFS($F$1="LM7 31 ClPRODUCT4 ms","LM7",$F$1="LMS1 31 ClPRODUCT4 ms","CV",$F$1="LMS2 31 ClPRODUCT4 ms","CL",$F$1="LMS5 31 ClPRODUCT4 ms","JZ",$F$1="LMS8 31 ClPRODUCT4 ms","DL",$F$1="LMS6 31 ClPRODUCT4 ms","MD",TRUE, ""),IF(AND($E$1="GENINTEGRATION 22 Attributes",$E5<>""),"22","")),"")} -> CV | H5: context_type | I5: https://purl.demodata7.org/spec/GENINTEGRATION/clPRODUCT4 m/context|type | J5: Yes | K5: Yes | L5: Yes | M5: Yes | N5: Yes | O5: Yes | P5: =IF(AND($H5<>"",Q5<>""),$H5,"") -> context_type | Q5: =IF($J5="yes",$I5,"") -> https://purl.demodata7.org/spec/GENINTEGRATION/clPRODUCT4 m/context|type | R5: =IF(AND($H5<>"",S5<>""),$H5,"") -> context_type | S5: =IF($K5="yes",$I5,"") -> https://purl.demodata7.org/spec/GENINTEGRATION/clPRODUCT4 m/context|type | T5: =IF(AND($H5<>"",U5<>""),$H5,"") -> context_type | U5: =IF($L5="yes",$I5,"") -> https://purl.demodata7.org/spec/GENINTEGRATION/clPRODUCT4 m/context|type | V5: =IF(AND($H5<>"",W5<>""),$H5,"") -> context_type | W5: =IF($M5="yes",$I5,"") -> https://purl.demodata7.org/spec/GENINTEGRATION/clPRODUCT4 m/context|type | X5: =IF(AND($H5<>"",Y5<>""),$H5,"") -> context_type | Y5: =IF($N5="yes",$I5,"") -> https://purl.demodata7.org/spec/GENINTEGRATION/clPRODUCT4 m/context|type | Z5: =IF(AND($H5<>"",AA5<>""),$H5,"") -> context_type | AA5: =IF($L5="yes",$I5,"") -> https://purl.demodata7.org/spec/GENINTEGRATION/clPRODUCT4 m/context|type | AC5: Copy PRODCUT4 to user_id
E6: {=IFERROR(_xlfn.IFS($E$1="GENINTEGRATION 22 Parameters",(_xlfn.IFS($F$1=$Q$1,INDEX($P$2:$P$100,MATCH(0,INDEX(COUNTIF($E$1:$E5,$P$2:$P$100)+(COUNTIF($P$2:$P$100,$P$2:$P$100)<>1),0,0),0)),$F$1=$S$1,INDEX($R$2:$R$100,MATCH(0,INDEX(COUNTIF($E$1:$E5,$R$2:$R$100)+(COUNTIF($R$2:$R$100,$R$2:$R$100)<>1),0,0),0)),$F$1=$U$1,INDEX($T$2:$T$100,MATCH(0,INDEX(COUNTIF($E$1:$E5,$T$2:$T$100)+(COUNTIF($T$2:$T$100,$T$2:$T$100)<>1),0,0),0)),$F$1=$W$1,INDEX($V$2:$V$100,MATCH(0,INDEX(COUNTIF($E$1:$E5,$V$2:$V$100)+(COUNTIF($V$2:$V$100,$V$2:$V$100)<>1),0,0),0)),$F$1=$Y$1,INDEX($X$2:$X$100,MATCH(0,INDEX(COUNTIF($E$1:$E5,$X$2:$X$100)+(COUNTIF($X$2:$X$100,$X$2:$X$100)<>1),0,0),0)),$F$1=$AA$1,INDEX($Z$2:$Z$100,MATCH(0,INDEX(COUNTIF($E$1:$E5,$Z$2:$Z$100)+(COUNTIF($Z$2:$Z$100,$Z$2:$Z$100)<>1),0,0),0)),TRUE,"")),$E$1="GENINTEGRATION 22 Attributes",INDEX($H$2:$H$100,MATCH(0,INDEX(COUNTIF($E$1:$E5,$H$2:$H$100)+(COUNTIF($H$2:$H$100,$H$2:$H$100)<>1),0,0),0)),TRUE,""),"")} -> custom_ap (Full ClPRODUCT4 m) | F6: {=IFERROR(_xlfn.IFS($F$1=$Q$1,_xlfn.XLOOKUP($E6,$P$2:$P$100,Q$2:Q$100)&"",$F$1=$S$1,_xlfn.XLOOKUP($E6,$R$2:$R$100,$S$2:$S$100)&"",$F$1=$Y$1,_xlfn.XLOOKUP($E6,$X$2:$X$100,$Y$2:$Y$100)&"",$F$1=$U$1,_xlfn.XLOOKUP($E6,$T$2:$T$100,$U$2:$U$100)&"",$F$1=$W$1,_xlfn.XLOOKUP($E6,$V$2:$V$100,$W$2:$W$100)&"",$F$1=$AA$1,_xlfn.XLOOKUP($E6,$Z$2:$Z$100,$AA$2:$AA$100)&"",TRUE, ""),"")} -> https://purl.demodata7.org/spec/GENINTEGRATION/clPRODUCT4 m/custom|custom_ap | G6: {=IFERROR(IF($F6<>"",_xlfn.IFS($F$1="LM7 31 ClPRODUCT4 ms","LM7",$F$1="LMS1 31 ClPRODUCT4 ms","CV",$F$1="LMS2 31 ClPRODUCT4 ms","CL",$F$1="LMS5 31 ClPRODUCT4 ms","JZ",$F$1="LMS8 31 ClPRODUCT4 ms","DL",$F$1="LMS6 31 ClPRODUCT4 ms","MD",TRUE, ""),IF(AND($E$1="GENINTEGRATION 22 Attributes",$E6<>""),"22","")),"")} -> CV | H6: custom_ap (Full ClPRODUCT4 m) | I6: https://purl.demodata7.org/spec/GENINTEGRATION/clPRODUCT4 m/custom|custom_ap | J6: Yes | K6: Yes | L6: Yes | M6: Yes | N6: Yes | O6: Yes | P6: =IF(AND($H6<>"",Q6<>""),$H6,"") -> custom_ap (Full ClPRODUCT4 m) | Q6: =IF($J6="yes",$I6,"") -> https://purl.demodata7.org/spec/GENINTEGRATION/clPRODUCT4 m/custom|custom_ap | R6: =IF(AND($H6<>"",S6<>""),$H6,"") -> custom_ap (Full ClPRODUCT4 m) | S6: =IF($K6="yes",$I6,"") -> https://purl.demodata7.org/spec/GENINTEGRATION/clPRODUCT4 m/custom|custom_ap | T6: =IF(AND($H6<>"",U6<>""),$H6,"") -> custom_ap (Full ClPRODUCT4 m) | U6: =IF($L6="yes",$I6,"") -> https://purl.demodata7.org/spec/GENINTEGRATION/clPRODUCT4 m/custom|custom_ap | V6: =IF(AND($H6<>"",W6<>""),$H6,"") -> custom_ap (Full ClPRODUCT4 m) | W6: =IF($M6="yes",$I6,"") -> https://purl.demodata7.org/spec/GENINTEGRATION/clPRODUCT4 m/custom|custom_ap | X6: =IF(AND($H6<>"",Y6<>""),$H6,"") -> custom_ap (Full ClPRODUCT4 m) | Y6: =IF($N6="yes",$I6,"") -> https://purl.demodata7.org/spec/GENINTEGRATION/clPRODUCT4 m/custom|custom_ap | Z6: =IF(AND($H6<>"",AA6<>""),$H6,"") -> custom_ap (Full ClPRODUCT4 m) | AA6: =IF($L6="yes",$I6,"") -> https://purl.demodata7.org/spec/GENINTEGRATION/clPRODUCT4 m/custom|custom_ap | AC6: From | AD6: lis_person_contact_PRODCUT4_primary
E7: {=IFERROR(_xlfn.IFS($E$1="GENINTEGRATION 22 Parameters",(_xlfn.IFS($F$1=$Q$1,INDEX($P$2:$P$100,MATCH(0,INDEX(COUNTIF($E$1:$E6,$P$2:$P$100)+(COUNTIF($P$2:$P$100,$P$2:$P$100)<>1),0,0),0)),$F$1=$S$1,INDEX($R$2:$R$100,MATCH(0,INDEX(COUNTIF($E$1:$E6,$R$2:$R$100)+(COUNTIF($R$2:$R$100,$R$2:$R$100)<>1),0,0),0)),$F$1=$U$1,INDEX($T$2:$T$100,MATCH(0,INDEX(COUNTIF($E$1:$E6,$T$2:$T$100)+(COUNTIF($T$2:$T$100,$T$2:$T$100)<>1),0,0),0)),$F$1=$W$1,INDEX($V$2:$V$100,MATCH(0,INDEX(COUNTIF($E$1:$E6,$V$2:$V$100)+(COUNTIF($V$2:$V$100,$V$2:$V$100)<>1),0,0),0)),$F$1=$Y$1,INDEX($X$2:$X$100,MATCH(0,INDEX(COUNTIF($E$1:$E6,$X$2:$X$100)+(COUNTIF($X$2:$X$100,$X$2:$X$100)<>1),0,0),0)),$F$1=$AA$1,INDEX($Z$2:$Z$100,MATCH(0,INDEX(COUNTIF($E$1:$E6,$Z$2:$Z$100)+(COUNTIF($Z$2:$Z$100,$Z$2:$Z$100)<>1),0,0),0)),TRUE,"")),$E$1="GENINTEGRATION 22 Attributes",INDEX($H$2:$H$100,MATCH(0,INDEX(COUNTIF($E$1:$E6,$H$2:$H$100)+(COUNTIF($H$2:$H$100,$H$2:$H$100)<>1),0,0),0)),TRUE,""),"")} -> custom_ap | F7: {=IFERROR(_xlfn.IFS($F$1=$Q$1,_xlfn.XLOOKUP($E7,$P$2:$P$100,Q$2:Q$100)&"",$F$1=$S$1,_xlfn.XLOOKUP($E7,$R$2:$R$100,$S$2:$S$100)&"",$F$1=$Y$1,_xlfn.XLOOKUP($E7,$X$2:$X$100,$Y$2:$Y$100)&"",$F$1=$U$1,_xlfn.XLOOKUP($E7,$T$2:$T$100,$U$2:$U$100)&"",$F$1=$W$1,_xlfn.XLOOKUP($E7,$V$2:$V$100,$W$2:$W$100)&"",$F$1=$AA$1,_xlfn.XLOOKUP($E7,$Z$2:$Z$100,$AA$2:$AA$100)&"",TRUE, ""),"")} -> custom_ap | G7: {=IFERROR(IF($F7<>"",_xlfn.IFS($F$1="LM7 31 ClPRODUCT4 ms","LM7",$F$1="LMS1 31 ClPRODUCT4 ms","CV",$F$1="LMS2 31 ClPRODUCT4 ms","CL",$F$1="LMS5 31 ClPRODUCT4 ms","JZ",$F$1="LMS8 31 ClPRODUCT4 ms","DL",$F$1="LMS6 31 ClPRODUCT4 ms","MD",TRUE, ""),IF(AND($E$1="GENINTEGRATION 22 Attributes",$E7<>""),"22","")),"")} -> CV | H7: custom_ap | I7: custom_ap | J7: Yes | K7: Yes | L7: Yes | M7: Yes | N7: Yes | O7: Yes | P7: =IF(AND($H7<>"",Q7<>""),$H7,"") -> custom_ap | Q7: =IF($J7="yes",$I7,"") -> custom_ap | R7: =IF(AND($H7<>"",S7<>""),$H7,"") -> custom_ap | S7: =IF($K7="yes",$I7,"") -> custom_ap | T7: =IF(AND($H7<>"",U7<>""),$H7,"") -> custom_ap | U7: =IF($L7="yes",$I7,"") -> custom_ap | V7: =IF(AND($H7<>"",W7<>""),$H7,"") -> custom_ap | W7: =IF($M7="yes",$I7,"") -> custom_ap | X7: =IF(AND($H7<>"",Y7<>""),$H7,"") -> custom_ap | Y7: =IF($N7="yes",$I7,"") -> custom_ap | Z7: =IF(AND($H7<>"",AA7<>""),$H7,"") -> custom_ap | AA7: =IF($L7="yes",$I7,"") -> custom_ap | AC7: To | AD7: user_id
E8: {=IFERROR(_xlfn.IFS($E$1="GENINTEGRATION 22 Parameters",(_xlfn.IFS($F$1=$Q$1,INDEX($P$2:$P$100,MATCH(0,INDEX(COUNTIF($E$1:$E7,$P$2:$P$100)+(COUNTIF($P$2:$P$100,$P$2:$P$100)<>1),0,0),0)),$F$1=$S$1,INDEX($R$2:$R$100,MATCH(0,INDEX(COUNTIF($E$1:$E7,$R$2:$R$100)+(COUNTIF($R$2:$R$100,$R$2:$R$100)<>1),0,0),0)),$F$1=$U$1,INDEX($T$2:$T$100,MATCH(0,INDEX(COUNTIF($E$1:$E7,$T$2:$T$100)+(COUNTIF($T$2:$T$100,$T$2:$T$100)<>1),0,0),0)),$F$1=$W$1,INDEX($V$2:$V$100,MATCH(0,INDEX(COUNTIF($E$1:$E7,$V$2:$V$100)+(COUNTIF($V$2:$V$100,$V$2:$V$100)<>1),0,0),0)),$F$1=$Y$1,INDEX($X$2:$X$100,MATCH(0,INDEX(COUNTIF($E$1:$E7,$X$2:$X$100)+(COUNTIF($X$2:$X$100,$X$2:$X$100)<>1),0,0),0)),$F$1=$AA$1,INDEX($Z$2:$Z$100,MATCH(0,INDEX(COUNTIF($E$1:$E7,$Z$2:$Z$100)+(COUNTIF($Z$2:$Z$100,$Z$2:$Z$100)<>1),0,0),0)),TRUE,"")),$E$1="GENINTEGRATION 22 Attributes",INDEX($H$2:$H$100,MATCH(0,INDEX(COUNTIF($E$1:$E7,$H$2:$H$100)+(COUNTIF($H$2:$H$100,$H$2:$H$100)<>1),0,0),0)),TRUE,""),"")} -> custom_LMS1_user_LI_id | F8: {=IFERROR(_xlfn.IFS($F$1=$Q$1,_xlfn.XLOOKUP($E8,$P$2:$P$100,Q$2:Q$100)&"",$F$1=$S$1,_xlfn.XLOOKUP($E8,$R$2:$R$100,$S$2:$S$100)&"",$F$1=$Y$1,_xlfn.XLOOKUP($E8,$X$2:$X$100,$Y$2:$Y$100)&"",$F$1=$U$1,_xlfn.XLOOKUP($E8,$T$2:$T$100,$U$2:$U$100)&"",$F$1=$W$1,_xlfn.XLOOKUP($E8,$V$2:$V$100,$W$2:$W$100)&"",$F$1=$AA$1,_xlfn.XLOOKUP($E8,$Z$2:$Z$100,$AA$2:$AA$100)&"",TRUE, ""),"")} -> https://purl.demodata7.org/spec/GENINTEGRATION/clPRODUCT4 m/lis|person_Type2 | G8: {=IFERROR(IF($F8<>"",_xlfn.IFS($F$1="LM7 31 ClPRODUCT4 ms","LM7",$F$1="LMS1 31 ClPRODUCT4 ms","CV",$F$1="LMS2 31 ClPRODUCT4 ms","CL",$F$1="LMS5 31 ClPRODUCT4 ms","JZ",$F$1="LMS8 31 ClPRODUCT4 ms","DL",$F$1="LMS6 31 ClPRODUCT4 ms","MD",TRUE, ""),IF(AND($E$1="GENINTEGRATION 22 Attributes",$E8<>""),"22","")),"")} -> CV | H8: custom_LMS1_user_LI_id | I8: https://purl.demodata7.org/spec/GENINTEGRATION/clPRODUCT4 m/lis|person_Type2 | J8: No | K8: Yes | L8: No | M8: No | N8: No | O8: No | P8: =IF(AND($H8<>"",Q8<>""),$H8,"") | Q8: =IF($J8="yes",$I8,"") | R8: =IF(AND($H8<>"",S8<>""),$H8,"") -> custom_LMS1_user_LI_id | S8: =IF($K8="yes",$I8,"") -> https://purl.demodata7.org/spec/GENINTEGRATION/clPRODUCT4 m/lis|person_Type2 | T8: =IF(AND($H8<>"",U8<>""),$H8,"") | U8: =IF($L8="yes",$I8,"") | V8: =IF(AND($H8<>"",W8<>""),$H8,"") | W8: =IF($M8="yes",$I8,"") | X8: =IF(AND($H8<>"",Y8<>""),$H8,"") | Y8: =IF($N8="yes",$I8,"") | Z8: =IF(AND($H8<>"",AA8<>""),$H8,"") | AA8: =IF($L8="yes",$I8,"")
E9: {=IFERROR(_xlfn.IFS($E$1="GENINTEGRATION 22 Parameters",(_xlfn.IFS($F$1=$Q$1,INDEX($P$2:$P$100,MATCH(0,INDEX(COUNTIF($E$1:$E8,$P$2:$P$100)+(COUNTIF($P$2:$P$100,$P$2:$P$100)<>1),0,0),0)),$F$1=$S$1,INDEX($R$2:$R$100,MATCH(0,INDEX(COUNTIF($E$1:$E8,$R$2:$R$100)+(COUNTIF($R$2:$R$100,$R$2:$R$100)<>1),0,0),0)),$F$1=$U$1,INDEX($T$2:$T$100,MATCH(0,INDEX(COUNTIF($E$1:$E8,$T$2:$T$100)+(COUNTIF($T$2:$T$100,$T$2:$T$100)<>1),0,0),0)),$F$1=$W$1,INDEX($V$2:$V$100,MATCH(0,INDEX(COUNTIF($E$1:$E8,$V$2:$V$100)+(COUNTIF($V$2:$V$100,$V$2:$V$100)<>1),0,0),0)),$F$1=$Y$1,INDEX($X$2:$X$100,MATCH(0,INDEX(COUNTIF($E$1:$E8,$X$2:$X$100)+(COUNTIF($X$2:$X$100,$X$2:$X$100)<>1),0,0),0)),$F$1=$AA$1,INDEX($Z$2:$Z$100,MATCH(0,INDEX(COUNTIF($E$1:$E8,$Z$2:$Z$100)+(COUNTIF($Z$2:$Z$100,$Z$2:$Z$100)<>1),0,0),0)),TRUE,"")),$E$1="GENINTEGRATION 22 Attributes",INDEX($H$2:$H$100,MATCH(0,INDEX(COUNTIF($E$1:$E8,$H$2:$H$100)+(COUNTIF($H$2:$H$100,$H$2:$H$100)<>1),0,0),0)),TRUE,""),"")} -> custom_DemoData27name (Full ClPRODUCT4 m) | F9: {=IFERROR(_xlfn.IFS($F$1=$Q$1,_xlfn.XLOOKUP($E9,$P$2:$P$100,Q$2:Q$100)&"",$F$1=$S$1,_xlfn.XLOOKUP($E9,$R$2:$R$100,$S$2:$S$100)&"",$F$1=$Y$1,_xlfn.XLOOKUP($E9,$X$2:$X$100,$Y$2:$Y$100)&"",$F$1=$U$1,_xlfn.XLOOKUP($E9,$T$2:$T$100,$U$2:$U$100)&"",$F$1=$W$1,_xlfn.XLOOKUP($E9,$V$2:$V$100,$W$2:$W$100)&"",$F$1=$AA$1,_xlfn.XLOOKUP($E9,$Z$2:$Z$100,$AA$2:$AA$100)&"",TRUE, ""),"")} -> https://purl.demodata7.org/spec/GENINTEGRATION/clPRODUCT4 m/custom|custom_DemoData27name | G9: {=IFERROR(IF($F9<>"",_xlfn.IFS($F$1="LM7 31 ClPRODUCT4 ms","LM7",$F$1="LMS1 31 ClPRODUCT4 ms","CV",$F$1="LMS2 31 ClPRODUCT4 ms","CL",$F$1="LMS5 31 ClPRODUCT4 ms","JZ",$F$1="LMS8 31 ClPRODUCT4 ms","DL",$F$1="LMS6 31 ClPRODUCT4 ms","MD",TRUE, ""),IF(AND($E$1="GENINTEGRATION 22 Attributes",$E9<>""),"22","")),"")} -> CV | H9: custom_DemoData27name (Full ClPRODUCT4 m) | I9: https://purl.demodata7.org/spec/GENINTEGRATION/clPRODUCT4 m/custom|custom_DemoData27name | J9: Yes | K9: Yes | L9: Yes | M9: Yes | N9: Yes | O9: Yes | P9: =IF(AND($H9<>"",Q9<>""),$H9,"") -> custom_DemoData27name (Full ClPRODUCT4 m) | Q9: =IF($J9="yes",$I9,"") -> https://purl.demodata7.org/spec/GENINTEGRATION/clPRODUCT4 m/custom|custom_DemoData27name | R9: =IF(AND($H9<>"",S9<>""),$H9,"") -> custom_DemoData27name (Full ClPRODUCT4 m) | S9: =IF($K9="yes",$I9,"") -> https://purl.demodata7.org/spec/GENINTEGRATION/clPRODUCT4 m/custom|custom_DemoData27name | T9: =IF(AND($H9<>"",U9<>""),$H9,"") -> custom_DemoData27name (Full ClPRODUCT4 m) | U9: =IF($L9="yes",$I9,"") -> https://purl.demodata7.org/spec/GENINTEGRATION/clPRODUCT4 m/custom|custom_DemoData27name | V9: =IF(AND($H9<>"",W9<>""),$H9,"") -> custom_DemoData27name (Full ClPRODUCT4 m) | W9: =IF($M9="yes",$I9,"") -> https://purl.demodata7.org/spec/GENINTEGRATION/clPRODUCT4 m/custom|custom_DemoData27name | X9: =IF(AND($H9<>"",Y9<>""),$H9,"") -> custom_DemoData27name (Full ClPRODUCT4 m) | Y9: =IF($N9="yes",$I9,"") -> https://purl.demodata7.org/spec/GENINTEGRATION/clPRODUCT4 m/custom|custom_DemoData27name | Z9: =IF(AND($H9<>"",AA9<>""),$H9,"") -> custom_DemoData27name (Full ClPRODUCT4 m) | AA9: =IF($L9="yes",$I9,"") -> https://purl.demodata7.org/spec/GENINTEGRATION/clPRODUCT4 m/custom|custom_DemoData27name
E10: {=IFERROR(_xlfn.IFS($E$1="GENINTEGRATION 22 Parameters",(_xlfn.IFS($F$1=$Q$1,INDEX($P$2:$P$100,MATCH(0,INDEX(COUNTIF($E$1:$E9,$P$2:$P$100)+(COUNTIF($P$2:$P$100,$P$2:$P$100)<>1),0,0),0)),$F$1=$S$1,INDEX($R$2:$R$100,MATCH(0,INDEX(COUNTIF($E$1:$E9,$R$2:$R$100)+(COUNTIF($R$2:$R$100,$R$2:$R$100)<>1),0,0),0)),$F$1=$U$1,INDEX($T$2:$T$100,MATCH(0,INDEX(COUNTIF($E$1:$E9,$T$2:$T$100)+(COUNTIF($T$2:$T$100,$T$2:$T$100)<>1),0,0),0)),$F$1=$W$1,INDEX($V$2:$V$100,MATCH(0,INDEX(COUNTIF($E$1:$E9,$V$2:$V$100)+(COUNTIF($V$2:$V$100,$V$2:$V$100)<>1),0,0),0)),$F$1=$Y$1,INDEX($X$2:$X$100,MATCH(0,INDEX(COUNTIF($E$1:$E9,$X$2:$X$100)+(COUNTIF($X$2:$X$100,$X$2:$X$100)<>1),0,0),0)),$F$1=$AA$1,INDEX($Z$2:$Z$100,MATCH(0,INDEX(COUNTIF($E$1:$E9,$Z$2:$Z$100)+(COUNTIF($Z$2:$Z$100,$Z$2:$Z$100)<>1),0,0),0)),TRUE,"")),$E$1="GENINTEGRATION 22 Attributes",INDEX($H$2:$H$100,MATCH(0,INDEX(COUNTIF($E$1:$E9,$H$2:$H$100)+(COUNTIF($H$2:$H$100,$H$2:$H$100)<>1),0,0),0)),TRUE,""),"")} -> custom_DemoData27name | F10: {=IFERROR(_xlfn.IFS($F$1=$Q$1,_xlfn.XLOOKUP($E10,$P$2:$P$100,Q$2:Q$100)&"",$F$1=$S$1,_xlfn.XLOOKUP($E10,$R$2:$R$100,$S$2:$S$100)&"",$F$1=$Y$1,_xlfn.XLOOKUP($E10,$X$2:$X$100,$Y$2:$Y$100)&"",$F$1=$U$1,_xlfn.XLOOKUP($E10,$T$2:$T$100,$U$2:$U$100)&"",$F$1=$W$1,_xlfn.XLOOKUP($E10,$V$2:$V$100,$W$2:$W$100)&"",$F$1=$AA$1,_xlfn.XLOOKUP($E10,$Z$2:$Z$100,$AA$2:$AA$100)&"",TRUE, ""),"")} -> custom_DemoData27name | G10: {=IFERROR(IF($F10<>"",_xlfn.IFS($F$1="LM7 31 ClPRODUCT4 ms","LM7",$F$1="LMS1 31 ClPRODUCT4 ms","CV",$F$1="LMS2 31 ClPRODUCT4 ms","CL",$F$1="LMS5 31 ClPRODUCT4 ms","JZ",$F$1="LMS8 31 ClPRODUCT4 ms","DL",$F$1="LMS6 31 ClPRODUCT4 ms","MD",TRUE, ""),IF(AND($E$1="GENINTEGRATION 22 Attributes",$E10<>""),"22","")),"")} -> CV | H10: custom_DemoData27name | I10: custom_DemoData27name | J10: Yes | K10: Yes | L10: Yes | M10: Yes | N10: Yes | O10: Yes | P10: =IF(AND($H10<>"",Q10<>""),$H10,"") -> custom_DemoData27name | Q10: =IF($J10="yes",$I10,"") -> custom_DemoData27name | R10: =IF(AND($H10<>"",S10<>""),$H10,"") -> custom_DemoData27name | S10: =IF($K10="yes",$I10,"") -> custom_DemoData27name | T10: =IF(AND($H10<>"",U10<>""),$H10,"") -> custom_DemoData27name | U10: =IF($L10="yes",$I10,"") -> custom_DemoData27name | V10: =IF(AND($H10<>"",W10<>""),$H10,"") -> custom_DemoData27name | W10: =IF($M10="yes",$I10,"") -> custom_DemoData27name | X10: =IF(AND($H10<>"",Y10<>""),$H10,"") -> custom_DemoData27name | Y10: =IF($N10="yes",$I10,"") -> custom_DemoData27name | Z10: =IF(AND($H10<>"",AA10<>""),$H10,"") -> custom_DemoData27name | AA10: =IF($L10="yes",$I10,"") -> custom_DemoData27name | AC10: Common Custom Parameters for GENINTEGRATION 31
E11: {=IFERROR(_xlfn.IFS($E$1="GENINTEGRATION 22 Parameters",(_xlfn.IFS($F$1=$Q$1,INDEX($P$2:$P$100,MATCH(0,INDEX(COUNTIF($E$1:$E10,$P$2:$P$100)+(COUNTIF($P$2:$P$100,$P$2:$P$100)<>1),0,0),0)),$F$1=$S$1,INDEX($R$2:$R$100,MATCH(0,INDEX(COUNTIF($E$1:$E10,$R$2:$R$100)+(COUNTIF($R$2:$R$100,$R$2:$R$100)<>1),0,0),0)),$F$1=$U$1,INDEX($T$2:$T$100,MATCH(0,INDEX(COUNTIF($E$1:$E10,$T$2:$T$100)+(COUNTIF($T$2:$T$100,$T$2:$T$100)<>1),0,0),0)),$F$1=$W$1,INDEX($V$2:$V$100,MATCH(0,INDEX(COUNTIF($E$1:$E10,$V$2:$V$100)+(COUNTIF($V$2:$V$100,$V$2:$V$100)<>1),0,0),0)),$F$1=$Y$1,INDEX($X$2:$X$100,MATCH(0,INDEX(COUNTIF($E$1:$E10,$X$2:$X$100)+(COUNTIF($X$2:$X$100,$X$2:$X$100)<>1),0,0),0)),$F$1=$AA$1,INDEX($Z$2:$Z$100,MATCH(0,INDEX(COUNTIF($E$1:$E10,$Z$2:$Z$100)+(COUNTIF($Z$2:$Z$100,$Z$2:$Z$100)<>1),0,0),0)),TRUE,"")),$E$1="GENINTEGRATION 22 Attributes",INDEX($H$2:$H$100,MATCH(0,INDEX(COUNTIF($E$1:$E10,$H$2:$H$100)+(COUNTIF($H$2:$H$100,$H$2:$H$100)<>1),0,0),0)),TRUE,""),"")} -> ext | F11: {=IFERROR(_xlfn.IFS($F$1=$Q$1,_xlfn.XLOOKUP($E11,$P$2:$P$100,Q$2:Q$100)&"",$F$1=$S$1,_xlfn.XLOOKUP($E11,$R$2:$R$100,$S$2:$S$100)&"",$F$1=$Y$1,_xlfn.XLOOKUP($E11,$X$2:$X$100,$Y$2:$Y$100)&"",$F$1=$U$1,_xlfn.XLOOKUP($E11,$T$2:$T$100,$U$2:$U$100)&"",$F$1=$W$1,_xlfn.XLOOKUP($E11,$V$2:$V$100,$W$2:$W$100)&"",$F$1=$AA$1,_xlfn.XLOOKUP($E11,$Z$2:$Z$100,$AA$2:$AA$100)&"",TRUE, ""),"")} -> https://{domPRODUCT4 n}/{clPRODUCT4 mDemoData2h} | G11: {=IFERROR(IF($F11<>"",_xlfn.IFS($F$1="LM7 31 ClPRODUCT4 ms","LM7",$F$1="LMS1 31 ClPRODUCT4 ms","CV",$F$1="LMS2 31 ClPRODUCT4 ms","CL",$F$1="LMS5 31 ClPRODUCT4 ms","JZ",$F$1="LMS8 31 ClPRODUCT4 ms","DL",$F$1="LMS6 31 ClPRODUCT4 ms","MD",TRUE, ""),IF(AND($E$1="GENINTEGRATION 22 Attributes",$E11<>""),"22","")),"")} -> CV | H11: ext | I11: https://{domPRODUCT4 n}/{clPRODUCT4 mDemoData2h} | J11: Yes | K11: Yes | L11: Yes | M11: Yes | N11: Yes | O11: Yes | P11: ext | Q11: =IF($J11="yes",$I11,"") -> https://{domPRODUCT4 n}/{clPRODUCT4 mDemoData2h} | R11: =IF(AND($H11<>"",S11<>""),$H11,"") -> ext | S11: =IF($K11="yes",$I11,"") -> https://{domPRODUCT4 n}/{clPRODUCT4 mDemoData2h} | T11: =IF(AND($H11<>"",U11<>""),$H11,"") -> ext | U11: =IF($L11="yes",$I11,"") -> https://{domPRODUCT4 n}/{clPRODUCT4 mDemoData2h} | V11: =IF(AND($H11<>"",W11<>""),$H11,"") -> ext | W11: =IF($M11="yes",$I11,"") -> https://{domPRODUCT4 n}/{clPRODUCT4 mDemoData2h} | X11: =IF(AND($H11<>"",Y11<>""),$H11,"") -> ext | Y11: =IF($N11="yes",$I11,"") -> https://{domPRODUCT4 n}/{clPRODUCT4 mDemoData2h} | Z11: =IF(AND($H11<>"",AA11<>""),$H11,"") -> ext | AA11: =IF($L11="yes",$I11,"") -> https://{domPRODUCT4 n}/{clPRODUCT4 mDemoData2h} | AC11: Copy Context Title to Context ID
E12: {=IFERROR(_xlfn.IFS($E$1="GENINTEGRATION 22 Parameters",(_xlfn.IFS($F$1=$Q$1,INDEX($P$2:$P$100,MATCH(0,INDEX(COUNTIF($E$1:$E11,$P$2:$P$100)+(COUNTIF($P$2:$P$100,$P$2:$P$100)<>1),0,0),0)),$F$1=$S$1,INDEX($R$2:$R$100,MATCH(0,INDEX(COUNTIF($E$1:$E11,$R$2:$R$100)+(COUNTIF($R$2:$R$100,$R$2:$R$100)<>1),0,0),0)),$F$1=$U$1,INDEX($T$2:$T$100,MATCH(0,INDEX(COUNTIF($E$1:$E11,$T$2:$T$100)+(COUNTIF($T$2:$T$100,$T$2:$T$100)<>1),0,0),0)),$F$1=$W$1,INDEX($V$2:$V$100,MATCH(0,INDEX(COUNTIF($E$1:$E11,$V$2:$V$100)+(COUNTIF($V$2:$V$100,$V$2:$V$100)<>1),0,0),0)),$F$1=$Y$1,INDEX($X$2:$X$100,MATCH(0,INDEX(COUNTIF($E$1:$E11,$X$2:$X$100)+(COUNTIF($X$2:$X$100,$X$2:$X$100)<>1),0,0),0)),$F$1=$AA$1,INDEX($Z$2:$Z$100,MATCH(0,INDEX(COUNTIF($E$1:$E11,$Z$2:$Z$100)+(COUNTIF($Z$2:$Z$100,$Z$2:$Z$100)<>1),0,0),0)),TRUE,"")),$E$1="GENINTEGRATION 22 Attributes",INDEX($H$2:$H$100,MATCH(0,INDEX(COUNTIF($E$1:$E11,$H$2:$H$100)+(COUNTIF($H$2:$H$100,$H$2:$H$100)<>1),0,0),0)),TRUE,""),"")} -> launch_presentation_css_url | F12: {=IFERROR(_xlfn.IFS($F$1=$Q$1,_xlfn.XLOOKUP($E12,$P$2:$P$100,Q$2:Q$100)&"",$F$1=$S$1,_xlfn.XLOOKUP($E12,$R$2:$R$100,$S$2:$S$100)&"",$F$1=$Y$1,_xlfn.XLOOKUP($E12,$X$2:$X$100,$Y$2:$Y$100)&"",$F$1=$U$1,_xlfn.XLOOKUP($E12,$T$2:$T$100,$U$2:$U$100)&"",$F$1=$W$1,_xlfn.XLOOKUP($E12,$V$2:$V$100,$W$2:$W$100)&"",$F$1=$AA$1,_xlfn.XLOOKUP($E12,$Z$2:$Z$100,$AA$2:$AA$100)&"",TRUE, ""),"")} -> Not Supported in GENINTEGRATION 31 | G12: {=IFERROR(IF($F12<>"",_xlfn.IFS($F$1="LM7 31 ClPRODUCT4 ms","LM7",$F$1="LMS1 31 ClPRODUCT4 ms","CV",$F$1="LMS2 31 ClPRODUCT4 ms","CL",$F$1="LMS5 31 ClPRODUCT4 ms","JZ",$F$1="LMS8 31 ClPRODUCT4 ms","DL",$F$1="LMS6 31 ClPRODUCT4 ms","MD",TRUE, ""),IF(AND($E$1="GENINTEGRATION 22 Attributes",$E12<>""),"22","")),"")} -> CV | H12: ext_user_username | I12: https://purl.demodata7.org/spec/GENINTEGRATION/clPRODUCT4 m/lis|person_Type2 | J12: No | K12: No | L12: No | M12: Yes | N12: No | O12: No | P12: =IF(AND($H12<>"",Q12<>""),$H12,"") | Q12: =IF($J12="yes",$I12,"") | R12: =IF(AND($H12<>"",S12<>""),$H12,"") | S12: =IF($K12="yes",$I12,"") | T12: =IF(AND($H12<>"",U12<>""),$H12,"") | U12: =IF($L12="yes",$I12,"") | V12: =IF(AND($H12<>"",W12<>""),$H12,"") -> ext_user_username | W12: =IF($M12="yes",$I12,"") -> https://purl.demodata7.org/spec/GENINTEGRATION/clPRODUCT4 m/lis|person_Type2 | X12: =IF(AND($H12<>"",Y12<>""),$H12,"") | Y12: =IF($N12="yes",$I12,"") | Z12: =IF(AND($H12<>"",AA12<>""),$H12,"") | AA12: =IF($L12="yes",$I12,"") | AC12: From | AD12: https://purl.demodata7.org/spec/GENINTEGRATION/clPRODUCT4 m/context|title
A13: {=IF('Program Config'!$C$14<>"",IF(AND('Program Config'!$C$14<>"LMS3",'Program Config'!$C$14<>"LMS4",'Program Config'!$C$14<>"LMS11",'Program Config'!$C$14<>"LMS10"),_xlfn.IFS('Program Config'!$C$14="LMS1 - GENINTEGRATION 31 - All Types of Placement",$AC$10,'Program Config'!$C$14="LMS1 - GENINTEGRATION 31 Link & Course NAV",$AC$10,'Program Config'!$C$14="LMS8 - GENINTEGRATION 31",$AC$10,'Program Config'!$C$14="LMS5 - GENINTEGRATION 31",$AC$10,'Program Config'!$C$14="LMS2 - GENINTEGRATION 31",$AC$10,'Program Config'!$C$14="LM7 - GENINTEGRATION 31",$AC$10,'Program Config'!$C$14="LMS6 - GENINTEGRATION 31",$AC$10,TRUE,$AC$1),""),"")} -> Common Custom Parameters for GENINTEGRATION 31 | E13: {=IFERROR(_xlfn.IFS($E$1="GENINTEGRATION 22 Parameters",(_xlfn.IFS($F$1=$Q$1,INDEX($P$2:$P$100,MATCH(0,INDEX(COUNTIF($E$1:$E12,$P$2:$P$100)+(COUNTIF($P$2:$P$100,$P$2:$P$100)<>1),0,0),0)),$F$1=$S$1,INDEX($R$2:$R$100,MATCH(0,INDEX(COUNTIF($E$1:$E12,$R$2:$R$100)+(COUNTIF($R$2:$R$100,$R$2:$R$100)<>1),0,0),0)),$F$1=$U$1,INDEX($T$2:$T$100,MATCH(0,INDEX(COUNTIF($E$1:$E12,$T$2:$T$100)+(COUNTIF($T$2:$T$100,$T$2:$T$100)<>1),0,0),0)),$F$1=$W$1,INDEX($V$2:$V$100,MATCH(0,INDEX(COUNTIF($E$1:$E12,$V$2:$V$100)+(COUNTIF($V$2:$V$100,$V$2:$V$100)<>1),0,0),0)),$F$1=$Y$1,INDEX($X$2:$X$100,MATCH(0,INDEX(COUNTIF($E$1:$E12,$X$2:$X$100)+(COUNTIF($X$2:$X$100,$X$2:$X$100)<>1),0,0),0)),$F$1=$AA$1,INDEX($Z$2:$Z$100,MATCH(0,INDEX(COUNTIF($E$1:$E12,$Z$2:$Z$100)+(COUNTIF($Z$2:$Z$100,$Z$2:$Z$100)<>1),0,0),0)),TRUE,"")),$E$1="GENINTEGRATION 22 Attributes",INDEX($H$2:$H$100,MATCH(0,INDEX(COUNTIF($E$1:$E12,$H$2:$H$100)+(COUNTIF($H$2:$H$100,$H$2:$H$100)<>1),0,0),0)),TRUE,""),"")} -> launch_presentation_document_target | F13: {=IFERROR(_xlfn.IFS($F$1=$Q$1,_xlfn.XLOOKUP($E13,$P$2:$P$100,Q$2:Q$100)&"",$F$1=$S$1,_xlfn.XLOOKUP($E13,$R$2:$R$100,$S$2:$S$100)&"",$F$1=$Y$1,_xlfn.XLOOKUP($E13,$X$2:$X$100,$Y$2:$Y$100)&"",$F$1=$U$1,_xlfn.XLOOKUP($E13,$T$2:$T$100,$U$2:$U$100)&"",$F$1=$W$1,_xlfn.XLOOKUP($E13,$V$2:$V$100,$W$2:$W$100)&"",$F$1=$AA$1,_xlfn.XLOOKUP($E13,$Z$2:$Z$100,$AA$2:$AA$100)&"",TRUE, ""),"")} -> https://purl.demodata7.org/spec/GENINTEGRATION/clPRODUCT4 m/launch_presentation|document_target | G13: {=IFERROR(IF($F13<>"",_xlfn.IFS($F$1="LM7 31 ClPRODUCT4 ms","LM7",$F$1="LMS1 31 ClPRODUCT4 ms","CV",$F$1="LMS2 31 ClPRODUCT4 ms","CL",$F$1="LMS5 31 ClPRODUCT4 ms","JZ",$F$1="LMS8 31 ClPRODUCT4 ms","DL",$F$1="LMS6 31 ClPRODUCT4 ms","MD",TRUE, ""),IF(AND($E$1="GENINTEGRATION 22 Attributes",$E13<>""),"22","")),"")} -> CV | H13: launch_presentation_css_url | I13: Not Supported in GENINTEGRATION 31 | J13: Yes | K13: Yes | L13: Yes | M13: Yes | N13: Yes | O13: Yes | P13: =IF(AND($H13<>"",Q13<>""),$H13,"") -> launch_presentation_css_url | Q13: =IF($J13="yes",$I13,"") -> Not Supported in GENINTEGRATION 31 | R13: =IF(AND($H13<>"",S13<>""),$H13,"") -> launch_presentation_css_url | S13: =IF($K13="yes",$I13,"") -> Not Supported in GENINTEGRATION 31 | T13: =IF(AND($H13<>"",U13<>""),$H13,"") -> launch_presentation_css_url | U13: =IF($L13="yes",$I13,"") -> Not Supported in GENINTEGRATION 31 | V13: =IF(AND($H13<>"",W13<>""),$H13,"") -> launch_presentation_css_url | W13: =IF($M13="yes",$I13,"") -> Not Supported in GENINTEGRATION 31 | X13: =IF(AND($H13<>"",Y13<>""),$H13,"") -> launch_presentation_css_url | Y13: =IF($N13="yes",$I13,"") -> Not Supported in GENINTEGRATION 31 | Z13: =IF(AND($H13<>"",AA13<>""),$H13,"") -> launch_presentation_css_url | AA13: =IF($L13="yes",$I13,"") -> Not Supported in GENINTEGRATION 31 | AC13: To | AD13: https://purl.demodata7.org/spec/GENINTEGRATION/clPRODUCT4 m/context|id
A14: {=IFERROR(_xlfn.IFS($A$13=$AC$1,$AC2,$A$13=$AC$10,$AC11,TRUE,""),"")} -> Copy Context Title to Context ID | E14: {=IFERROR(_xlfn.IFS($E$1="GENINTEGRATION 22 Parameters",(_xlfn.IFS($F$1=$Q$1,INDEX($P$2:$P$100,MATCH(0,INDEX(COUNTIF($E$1:$E13,$P$2:$P$100)+(COUNTIF($P$2:$P$100,$P$2:$P$100)<>1),0,0),0)),$F$1=$S$1,INDEX($R$2:$R$100,MATCH(0,INDEX(COUNTIF($E$1:$E13,$R$2:$R$100)+(COUNTIF($R$2:$R$100,$R$2:$R$100)<>1),0,0),0)),$F$1=$U$1,INDEX($T$2:$T$100,MATCH(0,INDEX(COUNTIF($E$1:$E13,$T$2:$T$100)+(COUNTIF($T$2:$T$100,$T$2:$T$100)<>1),0,0),0)),$F$1=$W$1,INDEX($V$2:$V$100,MATCH(0,INDEX(COUNTIF($E$1:$E13,$V$2:$V$100)+(COUNTIF($V$2:$V$100,$V$2:$V$100)<>1),0,0),0)),$F$1=$Y$1,INDEX($X$2:$X$100,MATCH(0,INDEX(COUNTIF($E$1:$E13,$X$2:$X$100)+(COUNTIF($X$2:$X$100,$X$2:$X$100)<>1),0,0),0)),$F$1=$AA$1,INDEX($Z$2:$Z$100,MATCH(0,INDEX(COUNTIF($E$1:$E13,$Z$2:$Z$100)+(COUNTIF($Z$2:$Z$100,$Z$2:$Z$100)<>1),0,0),0)),TRUE,"")),$E$1="GENINTEGRATION 22 Attributes",INDEX($H$2:$H$100,MATCH(0,INDEX(COUNTIF($E$1:$E13,$H$2:$H$100)+(COUNTIF($H$2:$H$100,$H$2:$H$100)<>1),0,0),0)),TRUE,""),"")} -> launch_presentation_height | F14: {=IFERROR(_xlfn.IFS($F$1=$Q$1,_xlfn.XLOOKUP($E14,$P$2:$P$100,Q$2:Q$100)&"",$F$1=$S$1,_xlfn.XLOOKUP($E14,$R$2:$R$100,$S$2:$S$100)&"",$F$1=$Y$1,_xlfn.XLOOKUP($E14,$X$2:$X$100,$Y$2:$Y$100)&"",$F$1=$U$1,_xlfn.XLOOKUP($E14,$T$2:$T$100,$U$2:$U$100)&"",$F$1=$W$1,_xlfn.XLOOKUP($E14,$V$2:$V$100,$W$2:$W$100)&"",$F$1=$AA$1,_xlfn.XLOOKUP($E14,$Z$2:$Z$100,$AA$2:$AA$100)&"",TRUE, ""),"")} -> https://purl.demodata7.org/spec/GENINTEGRATION/clPRODUCT4 m/launch_presentation|height | G14: {=IFERROR(IF($F14<>"",_xlfn.IFS($F$1="LM7 31 ClPRODUCT4 ms","LM7",$F$1="LMS1 31 ClPRODUCT4 ms","CV",$F$1="LMS2 31 ClPRODUCT4 ms","CL",$F$1="LMS5 31 ClPRODUCT4 ms","JZ",$F$1="LMS8 31 ClPRODUCT4 ms","DL",$F$1="LMS6 31 ClPRODUCT4 ms","MD",TRUE, ""),IF(AND($E$1="GENINTEGRATION 22 Attributes",$E14<>""),"22","")),"")} -> CV | H14: launch_presentation_document_target | I14: https://purl.demodata7.org/spec/GENINTEGRATION/clPRODUCT4 m/launch_presentation|document_target | J14: Yes | K14: Yes | L14: Yes | M14: Yes | N14: Yes | O14: Yes | P14: =IF(AND($H14<>"",Q14<>""),$H14,"") -> launch_presentation_document_target | Q14: =IF($J14="yes",$I14,"") -> https://purl.demodata7.org/spec/GENINTEGRATION/clPRODUCT4 m/launch_presentation|document_target | R14: =IF(AND($H14<>"",S14<>""),$H14,"") -> launch_presentation_document_target | S14: =IF($K14="yes",$I14,"") -> https://purl.demodata7.org/spec/GENINTEGRATION/clPRODUCT4 m/launch_presentation|document_target | T14: =IF(AND($H14<>"",U14<>""),$H14,"") -> launch_presentation_document_target | U14: =IF($L14="yes",$I14,"") -> https://purl.demodata7.org/spec/GENINTEGRATION/clPRODUCT4 m/launch_presentation|document_target | V14: =IF(AND($H14<>"",W14<>""),$H14,"") -> launch_presentation_document_target | W14: =IF($M14="yes",$I14,"") -> https://purl.demodata7.org/spec/GENINTEGRATION/clPRODUCT4 m/launch_presentation|document_target | X14: =IF(AND($H14<>"",Y14<>""),$H14,"") -> launch_presentation_document_target | Y14: =IF($N14="yes",$I14,"") -> https://purl.demodata7.org/spec/GENINTEGRATION/clPRODUCT4 m/launch_presentation|document_target | Z14: =IF(AND($H14<>"",AA14<>""),$H14,"") -> launch_presentation_document_target | AA14: =IF($L14="yes",$I14,"") -> https://purl.demodata7.org/spec/GENINTEGRATION/clPRODUCT4 m/launch_presentation|document_target | AC14: Copy PRODCUT4 to Sub
A15: {=IFERROR(_xlfn.IFS($A$13=$AC$1,$AC3,$A$13=$AC$10,$AC12,TRUE,""),"")} -> From | B15: {=IFERROR(_xlfn.IFS($A$13=$AC$1,$AD3,$A$13=$AC$10,$AD12,TRUE,""),"")} -> https://purl.demodata7.org/spec/GENINTEGRATION/clPRODUCT4 m/context|title | E15: {=IFERROR(_xlfn.IFS($E$1="GENINTEGRATION 22 Parameters",(_xlfn.IFS($F$1=$Q$1,INDEX($P$2:$P$100,MATCH(0,INDEX(COUNTIF($E$1:$E14,$P$2:$P$100)+(COUNTIF($P$2:$P$100,$P$2:$P$100)<>1),0,0),0)),$F$1=$S$1,INDEX($R$2:$R$100,MATCH(0,INDEX(COUNTIF($E$1:$E14,$R$2:$R$100)+(COUNTIF($R$2:$R$100,$R$2:$R$100)<>1),0,0),0)),$F$1=$U$1,INDEX($T$2:$T$100,MATCH(0,INDEX(COUNTIF($E$1:$E14,$T$2:$T$100)+(COUNTIF($T$2:$T$100,$T$2:$T$100)<>1),0,0),0)),$F$1=$W$1,INDEX($V$2:$V$100,MATCH(0,INDEX(COUNTIF($E$1:$E14,$V$2:$V$100)+(COUNTIF($V$2:$V$100,$V$2:$V$100)<>1),0,0),0)),$F$1=$Y$1,INDEX($X$2:$X$100,MATCH(0,INDEX(COUNTIF($E$1:$E14,$X$2:$X$100)+(COUNTIF($X$2:$X$100,$X$2:$X$100)<>1),0,0),0)),$F$1=$AA$1,INDEX($Z$2:$Z$100,MATCH(0,INDEX(COUNTIF($E$1:$E14,$Z$2:$Z$100)+(COUNTIF($Z$2:$Z$100,$Z$2:$Z$100)<>1),0,0),0)),TRUE,"")),$E$1="GENINTEGRATION 22 Attributes",INDEX($H$2:$H$100,MATCH(0,INDEX(COUNTIF($E$1:$E14,$H$2:$H$100)+(COUNTIF($H$2:$H$100,$H$2:$H$100)<>1),0,0),0)),TRUE,""),"")} -> launch_presentation_locale | F15: {=IFERROR(_xlfn.IFS($F$1=$Q$1,_xlfn.XLOOKUP($E15,$P$2:$P$100,Q$2:Q$100)&"",$F$1=$S$1,_xlfn.XLOOKUP($E15,$R$2:$R$100,$S$2:$S$100)&"",$F$1=$Y$1,_xlfn.XLOOKUP($E15,$X$2:$X$100,$Y$2:$Y$100)&"",$F$1=$U$1,_xlfn.XLOOKUP($E15,$T$2:$T$100,$U$2:$U$100)&"",$F$1=$W$1,_xlfn.XLOOKUP($E15,$V$2:$V$100,$W$2:$W$100)&"",$F$1=$AA$1,_xlfn.XLOOKUP($E15,$Z$2:$Z$100,$AA$2:$AA$100)&"",TRUE, ""),"")} -> https://purl.demodata7.org/spec/GENINTEGRATION/clPRODUCT4 m/launch_presentation|locale | G15: {=IFERROR(IF($F15<>"",_xlfn.IFS($F$1="LM7 31 ClPRODUCT4 ms","LM7",$F$1="LMS1 31 ClPRODUCT4 ms","CV",$F$1="LMS2 31 ClPRODUCT4 ms","CL",$F$1="LMS5 31 ClPRODUCT4 ms","JZ",$F$1="LMS8 31 ClPRODUCT4 ms","DL",$F$1="LMS6 31 ClPRODUCT4 ms","MD",TRUE, ""),IF(AND($E$1="GENINTEGRATION 22 Attributes",$E15<>""),"22","")),"")} -> CV | H15: launch_presentation_height | I15: https://purl.demodata7.org/spec/GENINTEGRATION/clPRODUCT4 m/launch_presentation|height | J15: Yes | K15: Yes | L15: Yes | M15: Yes | N15: Yes | O15: Yes | P15: =IF(AND($H15<>"",Q15<>""),$H15,"") -> launch_presentation_height | Q15: =IF($J15="yes",$I15,"") -> https://purl.demodata7.org/spec/GENINTEGRATION/clPRODUCT4 m/launch_presentation|height | R15: =IF(AND($H15<>"",S15<>""),$H15,"") -> launch_presentation_height | S15: =IF($K15="yes",$I15,"") -> https://purl.demodata7.org/spec/GENINTEGRATION/clPRODUCT4 m/launch_presentation|height | T15: =IF(AND($H15<>"",U15<>""),$H15,"") -> launch_presentation_height | U15: =IF($L15="yes",$I15,"") -> https://purl.demodata7.org/spec/GENINTEGRATION/clPRODUCT4 m/launch_presentation|height | V15: =IF(AND($H15<>"",W15<>""),$H15,"") -> launch_presentation_height | W15: =IF($M15="yes",$I15,"") -> https://purl.demodata7.org/spec/GENINTEGRATION/clPRODUCT4 m/launch_presentation|height | X15: =IF(AND($H15<>"",Y15<>""),$H15,"") -> launch_presentation_height | Y15: =IF($N15="yes",$I15,"") -> https://purl.demodata7.org/spec/GENINTEGRATION/clPRODUCT4 m/launch_presentation|height | Z15: =IF(AND($H15<>"",AA15<>""),$H15,"") -> launch_presentation_height | AA15: =IF($L15="yes",$I15,"") -> https://purl.demodata7.org/spec/GENINTEGRATION/clPRODUCT4 m/launch_presentation|height | AC15: From | AD15: PRODCUT4
A16: {=IFERROR(_xlfn.IFS($A$13=$AC$1,$AC4,$A$13=$AC$10,$AC13,TRUE,""),"")} -> To | B16: {=IFERROR(_xlfn.IFS($A$13=$AC$1,$AD4,$A$13=$AC$10,$AD13,TRUE,""),"")} -> https://purl.demodata7.org/spec/GENINTEGRATION/clPRODUCT4 m/context|id | E16: {=IFERROR(_xlfn.IFS($E$1="GENINTEGRATION 22 Parameters",(_xlfn.IFS($F$1=$Q$1,INDEX($P$2:$P$100,MATCH(0,INDEX(COUNTIF($E$1:$E15,$P$2:$P$100)+(COUNTIF($P$2:$P$100,$P$2:$P$100)<>1),0,0),0)),$F$1=$S$1,INDEX($R$2:$R$100,MATCH(0,INDEX(COUNTIF($E$1:$E15,$R$2:$R$100)+(COUNTIF($R$2:$R$100,$R$2:$R$100)<>1),0,0),0)),$F$1=$U$1,INDEX($T$2:$T$100,MATCH(0,INDEX(COUNTIF($E$1:$E15,$T$2:$T$100)+(COUNTIF($T$2:$T$100,$T$2:$T$100)<>1),0,0),0)),$F$1=$W$1,INDEX($V$2:$V$100,MATCH(0,INDEX(COUNTIF($E$1:$E15,$V$2:$V$100)+(COUNTIF($V$2:$V$100,$V$2:$V$100)<>1),0,0),0)),$F$1=$Y$1,INDEX($X$2:$X$100,MATCH(0,INDEX(COUNTIF($E$1:$E15,$X$2:$X$100)+(COUNTIF($X$2:$X$100,$X$2:$X$100)<>1),0,0),0)),$F$1=$AA$1,INDEX($Z$2:$Z$100,MATCH(0,INDEX(COUNTIF($E$1:$E15,$Z$2:$Z$100)+(COUNTIF($Z$2:$Z$100,$Z$2:$Z$100)<>1),0,0),0)),TRUE,"")),$E$1="GENINTEGRATION 22 Attributes",INDEX($H$2:$H$100,MATCH(0,INDEX(COUNTIF($E$1:$E15,$H$2:$H$100)+(COUNTIF($H$2:$H$100,$H$2:$H$100)<>1),0,0),0)),TRUE,""),"")} -> launch_presentation_return_url | F16: {=IFERROR(_xlfn.IFS($F$1=$Q$1,_xlfn.XLOOKUP($E16,$P$2:$P$100,Q$2:Q$100)&"",$F$1=$S$1,_xlfn.XLOOKUP($E16,$R$2:$R$100,$S$2:$S$100)&"",$F$1=$Y$1,_xlfn.XLOOKUP($E16,$X$2:$X$100,$Y$2:$Y$100)&"",$F$1=$U$1,_xlfn.XLOOKUP($E16,$T$2:$T$100,$U$2:$U$100)&"",$F$1=$W$1,_xlfn.XLOOKUP($E16,$V$2:$V$100,$W$2:$W$100)&"",$F$1=$AA$1,_xlfn.XLOOKUP($E16,$Z$2:$Z$100,$AA$2:$AA$100)&"",TRUE, ""),"")} -> https://purl.demodata7.org/spec/GENINTEGRATION/clPRODUCT4 m/launch_presentation|return_url | G16: {=IFERROR(IF($F16<>"",_xlfn.IFS($F$1="LM7 31 ClPRODUCT4 ms","LM7",$F$1="LMS1 31 ClPRODUCT4 ms","CV",$F$1="LMS2 31 ClPRODUCT4 ms","CL",$F$1="LMS5 31 ClPRODUCT4 ms","JZ",$F$1="LMS8 31 ClPRODUCT4 ms","DL",$F$1="LMS6 31 ClPRODUCT4 ms","MD",TRUE, ""),IF(AND($E$1="GENINTEGRATION 22 Attributes",$E16<>""),"22","")),"")} -> CV | H16: launch_presentation_locale | I16: https://purl.demodata7.org/spec/GENINTEGRATION/clPRODUCT4 m/launch_presentation|locale | J16: Yes | K16: Yes | L16: Yes | M16: Yes | N16: Yes | O16: Yes | P16: =IF(AND($H16<>"",Q16<>""),$H16,"") -> launch_presentation_locale | Q16: =IF($J16="yes",$I16,"") -> https://purl.demodata7.org/spec/GENINTEGRATION/clPRODUCT4 m/launch_presentation|locale | R16: =IF(AND($H16<>"",S16<>""),$H16,"") -> launch_presentation_locale | S16: =IF($K16="yes",$I16,"") -> https://purl.demodata7.org/spec/GENINTEGRATION/clPRODUCT4 m/launch_presentation|locale | T16: =IF(AND($H16<>"",U16<>""),$H16,"") -> launch_presentation_locale | U16: =IF($L16="yes",$I16,"") -> https://purl.demodata7.org/spec/GENINTEGRATION/clPRODUCT4 m/launch_presentation|locale | V16: =IF(AND($H16<>"",W16<>""),$H16,"") -> launch_presentation_locale | W16: =IF($M16="yes",$I16,"") -> https://purl.demodata7.org/spec/GENINTEGRATION/clPRODUCT4 m/launch_presentation|locale | X16: =IF(AND($H16<>"",Y16<>""),$H16,"") -> launch_presentation_locale | Y16: =IF($N16="yes",$I16,"") -> https://purl.demodata7.org/spec/GENINTEGRATION/clPRODUCT4 m/launch_presentation|locale | Z16: =IF(AND($H16<>"",AA16<>""),$H16,"") -> launch_presentation_locale | AA16: =IF($L16="yes",$I16,"") -> https://purl.demodata7.org/spec/GENINTEGRATION/clPRODUCT4 m/launch_presentation|locale | AC16: To | AD16: sub
A17: {=IFERROR(_xlfn.IFS($A$13=$AC$1,$AC5,$A$13=$AC$10,$AC14,TRUE,""),"")} -> Copy PRODCUT4 to Sub | E17: {=IFERROR(_xlfn.IFS($E$1="GENINTEGRATION 22 Parameters",(_xlfn.IFS($F$1=$Q$1,INDEX($P$2:$P$100,MATCH(0,INDEX(COUNTIF($E$1:$E16,$P$2:$P$100)+(COUNTIF($P$2:$P$100,$P$2:$P$100)<>1),0,0),0)),$F$1=$S$1,INDEX($R$2:$R$100,MATCH(0,INDEX(COUNTIF($E$1:$E16,$R$2:$R$100)+(COUNTIF($R$2:$R$100,$R$2:$R$100)<>1),0,0),0)),$F$1=$U$1,INDEX($T$2:$T$100,MATCH(0,INDEX(COUNTIF($E$1:$E16,$T$2:$T$100)+(COUNTIF($T$2:$T$100,$T$2:$T$100)<>1),0,0),0)),$F$1=$W$1,INDEX($V$2:$V$100,MATCH(0,INDEX(COUNTIF($E$1:$E16,$V$2:$V$100)+(COUNTIF($V$2:$V$100,$V$2:$V$100)<>1),0,0),0)),$F$1=$Y$1,INDEX($X$2:$X$100,MATCH(0,INDEX(COUNTIF($E$1:$E16,$X$2:$X$100)+(COUNTIF($X$2:$X$100,$X$2:$X$100)<>1),0,0),0)),$F$1=$AA$1,INDEX($Z$2:$Z$100,MATCH(0,INDEX(COUNTIF($E$1:$E16,$Z$2:$Z$100)+(COUNTIF($Z$2:$Z$100,$Z$2:$Z$100)<>1),0,0),0)),TRUE,"")),$E$1="GENINTEGRATION 22 Attributes",INDEX($H$2:$H$100,MATCH(0,INDEX(COUNTIF($E$1:$E16,$H$2:$H$100)+(COUNTIF($H$2:$H$100,$H$2:$H$100)<>1),0,0),0)),TRUE,""),"")} -> launch_presentation_width | F17: {=IFERROR(_xlfn.IFS($F$1=$Q$1,_xlfn.XLOOKUP($E17,$P$2:$P$100,Q$2:Q$100)&"",$F$1=$S$1,_xlfn.XLOOKUP($E17,$R$2:$R$100,$S$2:$S$100)&"",$F$1=$Y$1,_xlfn.XLOOKUP($E17,$X$2:$X$100,$Y$2:$Y$100)&"",$F$1=$U$1,_xlfn.XLOOKUP($E17,$T$2:$T$100,$U$2:$U$100)&"",$F$1=$W$1,_xlfn.XLOOKUP($E17,$V$2:$V$100,$W$2:$W$100)&"",$F$1=$AA$1,_xlfn.XLOOKUP($E17,$Z$2:$Z$100,$AA$2:$AA$100)&"",TRUE, ""),"")} -> https://purl.demodata7.org/spec/GENINTEGRATION/clPRODUCT4 m/launch_presentation|width | G17: {=IFERROR(IF($F17<>"",_xlfn.IFS($F$1="LM7 31 ClPRODUCT4 ms","LM7",$F$1="LMS1 31 ClPRODUCT4 ms","CV",$F$1="LMS2 31 ClPRODUCT4 ms","CL",$F$1="LMS5 31 ClPRODUCT4 ms","JZ",$F$1="LMS8 31 ClPRODUCT4 ms","DL",$F$1="LMS6 31 ClPRODUCT4 ms","MD",TRUE, ""),IF(AND($E$1="GENINTEGRATION 22 Attributes",$E17<>""),"22","")),"")} -> CV | H17: launch_presentation_return_url | I17: https://purl.demodata7.org/spec/GENINTEGRATION/clPRODUCT4 m/launch_presentation|return_url | J17: Yes | K17: Yes | L17: Yes | M17: Yes | N17: Yes | O17: Yes | P17: =IF(AND($H17<>"",Q17<>""),$H17,"") -> launch_presentation_return_url | Q17: =IF($J17="yes",$I17,"") -> https://purl.demodata7.org/spec/GENINTEGRATION/clPRODUCT4 m/launch_presentation|return_url | R17: =IF(AND($H17<>"",S17<>""),$H17,"") -> launch_presentation_return_url | S17: =IF($K17="yes",$I17,"") -> https://purl.demodata7.org/spec/GENINTEGRATION/clPRODUCT4 m/launch_presentation|return_url | T17: =IF(AND($H17<>"",U17<>""),$H17,"") -> launch_presentation_return_url | U17: =IF($L17="yes",$I17,"") -> https://purl.demodata7.org/spec/GENINTEGRATION/clPRODUCT4 m/launch_presentation|return_url | V17: =IF(AND($H17<>"",W17<>""),$H17,"") -> launch_presentation_return_url | W17: =IF($M17="yes",$I17,"") -> https://purl.demodata7.org/spec/GENINTEGRATION/clPRODUCT4 m/launch_presentation|return_url | X17: =IF(AND($H17<>"",Y17<>""),$H17,"") -> launch_presentation_return_url | Y17: =IF($N17="yes",$I17,"") -> https://purl.demodata7.org/spec/GENINTEGRATION/clPRODUCT4 m/launch_presentation|return_url | Z17: =IF(AND($H17<>"",AA17<>""),$H17,"") -> launch_presentation_return_url | AA17: =IF($L17="yes",$I17,"") -> https://purl.demodata7.org/spec/GENINTEGRATION/clPRODUCT4 m/launch_presentation|return_url | AC17: Copy student ID to sub
A18: {=IFERROR(_xlfn.IFS($A$13=$AC$1,$AC6,$A$13=$AC$10,$AC15,TRUE,""),"")} -> From | B18: {=IFERROR(_xlfn.IFS($A$13=$AC$1,$AD6,$A$13=$AC$10,$AD15,TRUE,""),"")} -> PRODCUT4 | E18: {=IFERROR(_xlfn.IFS($E$1="GENINTEGRATION 22 Parameters",(_xlfn.IFS($F$1=$Q$1,INDEX($P$2:$P$100,MATCH(0,INDEX(COUNTIF($E$1:$E17,$P$2:$P$100)+(COUNTIF($P$2:$P$100,$P$2:$P$100)<>1),0,0),0)),$F$1=$S$1,INDEX($R$2:$R$100,MATCH(0,INDEX(COUNTIF($E$1:$E17,$R$2:$R$100)+(COUNTIF($R$2:$R$100,$R$2:$R$100)<>1),0,0),0)),$F$1=$U$1,INDEX($T$2:$T$100,MATCH(0,INDEX(COUNTIF($E$1:$E17,$T$2:$T$100)+(COUNTIF($T$2:$T$100,$T$2:$T$100)<>1),0,0),0)),$F$1=$W$1,INDEX($V$2:$V$100,MATCH(0,INDEX(COUNTIF($E$1:$E17,$V$2:$V$100)+(COUNTIF($V$2:$V$100,$V$2:$V$100)<>1),0,0),0)),$F$1=$Y$1,INDEX($X$2:$X$100,MATCH(0,INDEX(COUNTIF($E$1:$E17,$X$2:$X$100)+(COUNTIF($X$2:$X$100,$X$2:$X$100)<>1),0,0),0)),$F$1=$AA$1,INDEX($Z$2:$Z$100,MATCH(0,INDEX(COUNTIF($E$1:$E17,$Z$2:$Z$100)+(COUNTIF($Z$2:$Z$100,$Z$2:$Z$100)<>1),0,0),0)),TRUE,"")),$E$1="GENINTEGRATION 22 Attributes",INDEX($H$2:$H$100,MATCH(0,INDEX(COUNTIF($E$1:$E17,$H$2:$H$100)+(COUNTIF($H$2:$H$100,$H$2:$H$100)<>1),0,0),0)),TRUE,""),"")} -> lis_course_offering_Type2 | F18: {=IFERROR(_xlfn.IFS($F$1=$Q$1,_xlfn.XLOOKUP($E18,$P$2:$P$100,Q$2:Q$100)&"",$F$1=$S$1,_xlfn.XLOOKUP($E18,$R$2:$R$100,$S$2:$S$100)&"",$F$1=$Y$1,_xlfn.XLOOKUP($E18,$X$2:$X$100,$Y$2:$Y$100)&"",$F$1=$U$1,_xlfn.XLOOKUP($E18,$T$2:$T$100,$U$2:$U$100)&"",$F$1=$W$1,_xlfn.XLOOKUP($E18,$V$2:$V$100,$W$2:$W$100)&"",$F$1=$AA$1,_xlfn.XLOOKUP($E18,$Z$2:$Z$100,$AA$2:$AA$100)&"",TRUE, ""),"")} -> https://purl.demodata7.org/spec/GENINTEGRATION/clPRODUCT4 m/lis|course_offering_Type2 | G18: {=IFERROR(IF($F18<>"",_xlfn.IFS($F$1="LM7 31 ClPRODUCT4 ms","LM7",$F$1="LMS1 31 ClPRODUCT4 ms","CV",$F$1="LMS2 31 ClPRODUCT4 ms","CL",$F$1="LMS5 31 ClPRODUCT4 ms","JZ",$F$1="LMS8 31 ClPRODUCT4 ms","DL",$F$1="LMS6 31 ClPRODUCT4 ms","MD",TRUE, ""),IF(AND($E$1="GENINTEGRATION 22 Attributes",$E18<>""),"22","")),"")} -> CV | H18: launch_presentation_width | I18: https://purl.demodata7.org/spec/GENINTEGRATION/clPRODUCT4 m/launch_presentation|width | J18: Yes | K18: Yes | L18: Yes | M18: Yes | N18: Yes | O18: Yes | P18: =IF(AND($H18<>"",Q18<>""),$H18,"") -> launch_presentation_width | Q18: =IF($J18="yes",$I18,"") -> https://purl.demodata7.org/spec/GENINTEGRATION/clPRODUCT4 m/launch_presentation|width | R18: =IF(AND($H18<>"",S18<>""),$H18,"") -> launch_presentation_width | S18: =IF($K18="yes",$I18,"") -> https://purl.demodata7.org/spec/GENINTEGRATION/clPRODUCT4 m/launch_presentation|width | T18: =IF(AND($H18<>"",U18<>""),$H18,"") -> launch_presentation_width | U18: =IF($L18="yes",$I18,"") -> https://purl.demodata7.org/spec/GENINTEGRATION/clPRODUCT4 m/launch_presentation|width | V18: =IF(AND($H18<>"",W18<>""),$H18,"") -> launch_presentation_width | W18: =IF($M18="yes",$I18,"") -> https://purl.demodata7.org/spec/GENINTEGRATION/clPRODUCT4 m/launch_presentation|width | X18: =IF(AND($H18<>"",Y18<>""),$H18,"") -> launch_presentation_width | Y18: =IF($N18="yes",$I18,"") -> https://purl.demodata7.org/spec/GENINTEGRATION/clPRODUCT4 m/launch_presentation|width | Z18: =IF(AND($H18<>"",AA18<>""),$H18,"") -> launch_presentation_width | AA18: =IF($L18="yes",$I18,"") -> https://purl.demodata7.org/spec/GENINTEGRATION/clPRODUCT4 m/launch_presentation|width | AC18: From | AD18: https://purl.demodata7.org/spec/GENINTEGRATION/clPRODUCT4 m/lis|person_Type2
A19: {=IFERROR(_xlfn.IFS($A$13=$AC$1,$AC7,$A$13=$AC$10,$AC16,TRUE,""),"")} -> To | B19: {=IFERROR(_xlfn.IFS($A$13=$AC$1,$AD7,$A$13=$AC$10,$AD16,TRUE,""),"")} -> sub | E19: {=IFERROR(_xlfn.IFS($E$1="GENINTEGRATION 22 Parameters",(_xlfn.IFS($F$1=$Q$1,INDEX($P$2:$P$100,MATCH(0,INDEX(COUNTIF($E$1:$E18,$P$2:$P$100)+(COUNTIF($P$2:$P$100,$P$2:$P$100)<>1),0,0),0)),$F$1=$S$1,INDEX($R$2:$R$100,MATCH(0,INDEX(COUNTIF($E$1:$E18,$R$2:$R$100)+(COUNTIF($R$2:$R$100,$R$2:$R$100)<>1),0,0),0)),$F$1=$U$1,INDEX($T$2:$T$100,MATCH(0,INDEX(COUNTIF($E$1:$E18,$T$2:$T$100)+(COUNTIF($T$2:$T$100,$T$2:$T$100)<>1),0,0),0)),$F$1=$W$1,INDEX($V$2:$V$100,MATCH(0,INDEX(COUNTIF($E$1:$E18,$V$2:$V$100)+(COUNTIF($V$2:$V$100,$V$2:$V$100)<>1),0,0),0)),$F$1=$Y$1,INDEX($X$2:$X$100,MATCH(0,INDEX(COUNTIF($E$1:$E18,$X$2:$X$100)+(COUNTIF($X$2:$X$100,$X$2:$X$100)<>1),0,0),0)),$F$1=$AA$1,INDEX($Z$2:$Z$100,MATCH(0,INDEX(COUNTIF($E$1:$E18,$Z$2:$Z$100)+(COUNTIF($Z$2:$Z$100,$Z$2:$Z$100)<>1),0,0),0)),TRUE,"")),$E$1="GENINTEGRATION 22 Attributes",INDEX($H$2:$H$100,MATCH(0,INDEX(COUNTIF($E$1:$E18,$H$2:$H$100)+(COUNTIF($H$2:$H$100,$H$2:$H$100)<>1),0,0),0)),TRUE,""),"")} -> lis_course_section_Type2 | F19: {=IFERROR(_xlfn.IFS($F$1=$Q$1,_xlfn.XLOOKUP($E19,$P$2:$P$100,Q$2:Q$100)&"",$F$1=$S$1,_xlfn.XLOOKUP($E19,$R$2:$R$100,$S$2:$S$100)&"",$F$1=$Y$1,_xlfn.XLOOKUP($E19,$X$2:$X$100,$Y$2:$Y$100)&"",$F$1=$U$1,_xlfn.XLOOKUP($E19,$T$2:$T$100,$U$2:$U$100)&"",$F$1=$W$1,_xlfn.XLOOKUP($E19,$V$2:$V$100,$W$2:$W$100)&"",$F$1=$AA$1,_xlfn.XLOOKUP($E19,$Z$2:$Z$100,$AA$2:$AA$100)&"",TRUE, ""),"")} -> https://purl.demodata7.org/spec/GENINTEGRATION/clPRODUCT4 m/lis|course_section_Type2 | G19: {=IFERROR(IF($F19<>"",_xlfn.IFS($F$1="LM7 31 ClPRODUCT4 ms","LM7",$F$1="LMS1 31 ClPRODUCT4 ms","CV",$F$1="LMS2 31 ClPRODUCT4 ms","CL",$F$1="LMS5 31 ClPRODUCT4 ms","JZ",$F$1="LMS8 31 ClPRODUCT4 ms","DL",$F$1="LMS6 31 ClPRODUCT4 ms","MD",TRUE, ""),IF(AND($E$1="GENINTEGRATION 22 Attributes",$E19<>""),"22","")),"")} -> CV | H19: lis_course_offering_Type2 | I19: https://purl.demodata7.org/spec/GENINTEGRATION/clPRODUCT4 m/lis|course_offering_Type2 | J19: Yes | K19: Yes | L19: Yes | M19: Yes | N19: Yes | O19: Yes | P19: =IF(AND($H19<>"",Q19<>""),$H19,"") -> lis_course_offering_Type2 | Q19: =IF($J19="yes",$I19,"") -> https://purl.demodata7.org/spec/GENINTEGRATION/clPRODUCT4 m/lis|course_offering_Type2 | R19: =IF(AND($H19<>"",S19<>""),$H19,"") -> lis_course_offering_Type2 | S19: =IF($K19="yes",$I19,"") -> https://purl.demodata7.org/spec/GENINTEGRATION/clPRODUCT4 m/lis|course_offering_Type2 | T19: =IF(AND($H19<>"",U19<>""),$H19,"") -> lis_course_offering_Type2 | U19: =IF($L19="yes",$I19,"") -> https://purl.demodata7.org/spec/GENINTEGRATION/clPRODUCT4 m/lis|course_offering_Type2 | V19: =IF(AND($H19<>"",W19<>""),$H19,"") -> lis_course_offering_Type2 | W19: =IF($M19="yes",$I19,"") -> https://purl.demodata7.org/spec/GENINTEGRATION/clPRODUCT4 m/lis|course_offering_Type2 | X19: =IF(AND($H19<>"",Y19<>""),$H19,"") -> lis_course_offering_Type2 | Y19: =IF($N19="yes",$I19,"") -> https://purl.demodata7.org/spec/GENINTEGRATION/clPRODUCT4 m/lis|course_offering_Type2 | Z19: =IF(AND($H19<>"",AA19<>""),$H19,"") -> lis_course_offering_Type2 | AA19: =IF($L19="yes",$I19,"") -> https://purl.demodata7.org/spec/GENINTEGRATION/clPRODUCT4 m/lis|course_offering_Type2 | AC19: To | AD19: sub
A20: {=IFERROR(_xlfn.IFS($A$13=$AC$1,"",$A$13=$AC$10,$AC17,TRUE,""),"")} -> Copy student ID to sub | E20: {=IFERROR(_xlfn.IFS($E$1="GENINTEGRATION 22 Parameters",(_xlfn.IFS($F$1=$Q$1,INDEX($P$2:$P$100,MATCH(0,INDEX(COUNTIF($E$1:$E19,$P$2:$P$100)+(COUNTIF($P$2:$P$100,$P$2:$P$100)<>1),0,0),0)),$F$1=$S$1,INDEX($R$2:$R$100,MATCH(0,INDEX(COUNTIF($E$1:$E19,$R$2:$R$100)+(COUNTIF($R$2:$R$100,$R$2:$R$100)<>1),0,0),0)),$F$1=$U$1,INDEX($T$2:$T$100,MATCH(0,INDEX(COUNTIF($E$1:$E19,$T$2:$T$100)+(COUNTIF($T$2:$T$100,$T$2:$T$100)<>1),0,0),0)),$F$1=$W$1,INDEX($V$2:$V$100,MATCH(0,INDEX(COUNTIF($E$1:$E19,$V$2:$V$100)+(COUNTIF($V$2:$V$100,$V$2:$V$100)<>1),0,0),0)),$F$1=$Y$1,INDEX($X$2:$X$100,MATCH(0,INDEX(COUNTIF($E$1:$E19,$X$2:$X$100)+(COUNTIF($X$2:$X$100,$X$2:$X$100)<>1),0,0),0)),$F$1=$AA$1,INDEX($Z$2:$Z$100,MATCH(0,INDEX(COUNTIF($E$1:$E19,$Z$2:$Z$100)+(COUNTIF($Z$2:$Z$100,$Z$2:$Z$100)<>1),0,0),0)),TRUE,"")),$E$1="GENINTEGRATION 22 Attributes",INDEX($H$2:$H$100,MATCH(0,INDEX(COUNTIF($E$1:$E19,$H$2:$H$100)+(COUNTIF($H$2:$H$100,$H$2:$H$100)<>1),0,0),0)),TRUE,""),"")} -> lis_person_contact_PRODCUT4_primary | F20: {=IFERROR(_xlfn.IFS($F$1=$Q$1,_xlfn.XLOOKUP($E20,$P$2:$P$100,Q$2:Q$100)&"",$F$1=$S$1,_xlfn.XLOOKUP($E20,$R$2:$R$100,$S$2:$S$100)&"",$F$1=$Y$1,_xlfn.XLOOKUP($E20,$X$2:$X$100,$Y$2:$Y$100)&"",$F$1=$U$1,_xlfn.XLOOKUP($E20,$T$2:$T$100,$U$2:$U$100)&"",$F$1=$W$1,_xlfn.XLOOKUP($E20,$V$2:$V$100,$W$2:$W$100)&"",$F$1=$AA$1,_xlfn.XLOOKUP($E20,$Z$2:$Z$100,$AA$2:$AA$100)&"",TRUE, ""),"")} -> PRODCUT4 | G20: {=IFERROR(IF($F20<>"",_xlfn.IFS($F$1="LM7 31 ClPRODUCT4 ms","LM7",$F$1="LMS1 31 ClPRODUCT4 ms","CV",$F$1="LMS2 31 ClPRODUCT4 ms","CL",$F$1="LMS5 31 ClPRODUCT4 ms","JZ",$F$1="LMS8 31 ClPRODUCT4 ms","DL",$F$1="LMS6 31 ClPRODUCT4 ms","MD",TRUE, ""),IF(AND($E$1="GENINTEGRATION 22 Attributes",$E20<>""),"22","")),"")} -> CV | H20: lis_course_section_Type2 | I20: https://purl.demodata7.org/spec/GENINTEGRATION/clPRODUCT4 m/lis|course_section_Type2 | J20: Yes | K20: Yes | L20: Yes | M20: Yes | N20: Yes | O20: Yes | P20: =IF(AND($H20<>"",Q20<>""),$H20,"") -> lis_course_section_Type2 | Q20: =IF($J20="yes",$I20,"") -> https://purl.demodata7.org/spec/GENINTEGRATION/clPRODUCT4 m/lis|course_section_Type2 | R20: =IF(AND($H20<>"",S20<>""),$H20,"") -> lis_course_section_Type2 | S20: =IF($K20="yes",$I20,"") -> https://purl.demodata7.org/spec/GENINTEGRATION/clPRODUCT4 m/lis|course_section_Type2 | T20: =IF(AND($H20<>"",U20<>""),$H20,"") -> lis_course_section_Type2 | U20: =IF($L20="yes",$I20,"") -> https://purl.demodata7.org/spec/GENINTEGRATION/clPRODUCT4 m/lis|course_section_Type2 | V20: =IF(AND($H20<>"",W20<>""),$H20,"") -> lis_course_section_Type2 | W20: =IF($M20="yes",$I20,"") -> https://purl.demodata7.org/spec/GENINTEGRATION/clPRODUCT4 m/lis|course_section_Type2 | X20: =IF(AND($H20<>"",Y20<>""),$H20,"") -> lis_course_section_Type2 | Y20: =IF($N20="yes",$I20,"") -> https://purl.demodata7.org/spec/GENINTEGRATION/clPRODUCT4 m/lis|course_section_Type2 | Z20: =IF(AND($H20<>"",AA20<>""),$H20,"") -> lis_course_section_Type2 | AA20: =IF($L20="yes",$I20,"") -> https://purl.demodata7.org/spec/GENINTEGRATION/clPRODUCT4 m/lis|course_section_Type2 | AC20: Set custom_ap to Program Name
A21: {=IFERROR(_xlfn.IFS($A$13=$AC$1,"",$A$13=$AC$10,$AC18,TRUE,""),"")} -> From | B21: {=IFERROR(_xlfn.IFS($A$13=$AC$1,"",$A$13=$AC$10,$AD18,TRUE,""),"")} -> https://purl.demodata7.org/spec/GENINTEGRATION/clPRODUCT4 m/lis|person_Type2 | E21: {=IFERROR(_xlfn.IFS($E$1="GENINTEGRATION 22 Parameters",(_xlfn.IFS($F$1=$Q$1,INDEX($P$2:$P$100,MATCH(0,INDEX(COUNTIF($E$1:$E20,$P$2:$P$100)+(COUNTIF($P$2:$P$100,$P$2:$P$100)<>1),0,0),0)),$F$1=$S$1,INDEX($R$2:$R$100,MATCH(0,INDEX(COUNTIF($E$1:$E20,$R$2:$R$100)+(COUNTIF($R$2:$R$100,$R$2:$R$100)<>1),0,0),0)),$F$1=$U$1,INDEX($T$2:$T$100,MATCH(0,INDEX(COUNTIF($E$1:$E20,$T$2:$T$100)+(COUNTIF($T$2:$T$100,$T$2:$T$100)<>1),0,0),0)),$F$1=$W$1,INDEX($V$2:$V$100,MATCH(0,INDEX(COUNTIF($E$1:$E20,$V$2:$V$100)+(COUNTIF($V$2:$V$100,$V$2:$V$100)<>1),0,0),0)),$F$1=$Y$1,INDEX($X$2:$X$100,MATCH(0,INDEX(COUNTIF($E$1:$E20,$X$2:$X$100)+(COUNTIF($X$2:$X$100,$X$2:$X$100)<>1),0,0),0)),$F$1=$AA$1,INDEX($Z$2:$Z$100,MATCH(0,INDEX(COUNTIF($E$1:$E20,$Z$2:$Z$100)+(COUNTIF($Z$2:$Z$100,$Z$2:$Z$100)<>1),0,0),0)),TRUE,"")),$E$1="GENINTEGRATION 22 Attributes",INDEX($H$2:$H$100,MATCH(0,INDEX(COUNTIF($E$1:$E20,$H$2:$H$100)+(COUNTIF($H$2:$H$100,$H$2:$H$100)<>1),0,0),0)),TRUE,""),"")} -> lis_person_name_family | F21: {=IFERROR(_xlfn.IFS($F$1=$Q$1,_xlfn.XLOOKUP($E21,$P$2:$P$100,Q$2:Q$100)&"",$F$1=$S$1,_xlfn.XLOOKUP($E21,$R$2:$R$100,$S$2:$S$100)&"",$F$1=$Y$1,_xlfn.XLOOKUP($E21,$X$2:$X$100,$Y$2:$Y$100)&"",$F$1=$U$1,_xlfn.XLOOKUP($E21,$T$2:$T$100,$U$2:$U$100)&"",$F$1=$W$1,_xlfn.XLOOKUP($E21,$V$2:$V$100,$W$2:$W$100)&"",$F$1=$AA$1,_xlfn.XLOOKUP($E21,$Z$2:$Z$100,$AA$2:$AA$100)&"",TRUE, ""),"")} -> family_name | G21: {=IFERROR(IF($F21<>"",_xlfn.IFS($F$1="LM7 31 ClPRODUCT4 ms","LM7",$F$1="LMS1 31 ClPRODUCT4 ms","CV",$F$1="LMS2 31 ClPRODUCT4 ms","CL",$F$1="LMS5 31 ClPRODUCT4 ms","JZ",$F$1="LMS8 31 ClPRODUCT4 ms","DL",$F$1="LMS6 31 ClPRODUCT4 ms","MD",TRUE, ""),IF(AND($E$1="GENINTEGRATION 22 Attributes",$E21<>""),"22","")),"")} -> CV | H21: lis_person_contact_PRODCUT4_primary | I21: PRODCUT4 | J21: Yes | K21: Yes | L21: Yes | M21: Yes | N21: Yes | O21: Yes | P21: =IF(AND($H21<>"",Q21<>""),$H21,"") -> lis_person_contact_PRODCUT4_primary | Q21: =IF($J21="yes",$I21,"") -> PRODCUT4 | R21: =IF(AND($H21<>"",S21<>""),$H21,"") -> lis_person_contact_PRODCUT4_primary | S21: =IF($K21="yes",$I21,"") -> PRODCUT4 | T21: =IF(AND($H21<>"",U21<>""),$H21,"") -> lis_person_contact_PRODCUT4_primary | U21: =IF($L21="yes",$I21,"") -> PRODCUT4 | V21: =IF(AND($H21<>"",W21<>""),$H21,"") -> lis_person_contact_PRODCUT4_primary | W21: =IF($M21="yes",$I21,"") -> PRODCUT4 | X21: =IF(AND($H21<>"",Y21<>""),$H21,"") -> lis_person_contact_PRODCUT4_primary | Y21: =IF($N21="yes",$I21,"") -> PRODCUT4 | Z21: =IF(AND($H21<>"",AA21<>""),$H21,"") -> lis_person_contact_PRODCUT4_primary | AA21: =IF($L21="yes",$I21,"") -> PRODCUT4 | AC21: Parameter | AD21: https://purl.demodata7.org/spec/GENINTEGRATION/clPRODUCT4 m/custom|custom_ap
A22: {=IFERROR(_xlfn.IFS($A$13=$AC$1,"",$A$13=$AC$10,$AC19,TRUE,""),"")} -> To | B22: {=IFERROR(_xlfn.IFS($A$13=$AC$1,"",$A$13=$AC$10,$AD19,TRUE,""),"")} -> sub | E22: {=IFERROR(_xlfn.IFS($E$1="GENINTEGRATION 22 Parameters",(_xlfn.IFS($F$1=$Q$1,INDEX($P$2:$P$100,MATCH(0,INDEX(COUNTIF($E$1:$E21,$P$2:$P$100)+(COUNTIF($P$2:$P$100,$P$2:$P$100)<>1),0,0),0)),$F$1=$S$1,INDEX($R$2:$R$100,MATCH(0,INDEX(COUNTIF($E$1:$E21,$R$2:$R$100)+(COUNTIF($R$2:$R$100,$R$2:$R$100)<>1),0,0),0)),$F$1=$U$1,INDEX($T$2:$T$100,MATCH(0,INDEX(COUNTIF($E$1:$E21,$T$2:$T$100)+(COUNTIF($T$2:$T$100,$T$2:$T$100)<>1),0,0),0)),$F$1=$W$1,INDEX($V$2:$V$100,MATCH(0,INDEX(COUNTIF($E$1:$E21,$V$2:$V$100)+(COUNTIF($V$2:$V$100,$V$2:$V$100)<>1),0,0),0)),$F$1=$Y$1,INDEX($X$2:$X$100,MATCH(0,INDEX(COUNTIF($E$1:$E21,$X$2:$X$100)+(COUNTIF($X$2:$X$100,$X$2:$X$100)<>1),0,0),0)),$F$1=$AA$1,INDEX($Z$2:$Z$100,MATCH(0,INDEX(COUNTIF($E$1:$E21,$Z$2:$Z$100)+(COUNTIF($Z$2:$Z$100,$Z$2:$Z$100)<>1),0,0),0)),TRUE,"")),$E$1="GENINTEGRATION 22 Attributes",INDEX($H$2:$H$100,MATCH(0,INDEX(COUNTIF($E$1:$E21,$H$2:$H$100)+(COUNTIF($H$2:$H$100,$H$2:$H$100)<>1),0,0),0)),TRUE,""),"")} -> lis_person_name_full | F22: {=IFERROR(_xlfn.IFS($F$1=$Q$1,_xlfn.XLOOKUP($E22,$P$2:$P$100,Q$2:Q$100)&"",$F$1=$S$1,_xlfn.XLOOKUP($E22,$R$2:$R$100,$S$2:$S$100)&"",$F$1=$Y$1,_xlfn.XLOOKUP($E22,$X$2:$X$100,$Y$2:$Y$100)&"",$F$1=$U$1,_xlfn.XLOOKUP($E22,$T$2:$T$100,$U$2:$U$100)&"",$F$1=$W$1,_xlfn.XLOOKUP($E22,$V$2:$V$100,$W$2:$W$100)&"",$F$1=$AA$1,_xlfn.XLOOKUP($E22,$Z$2:$Z$100,$AA$2:$AA$100)&"",TRUE, ""),"")} -> name | G22: {=IFERROR(IF($F22<>"",_xlfn.IFS($F$1="LM7 31 ClPRODUCT4 ms","LM7",$F$1="LMS1 31 ClPRODUCT4 ms","CV",$F$1="LMS2 31 ClPRODUCT4 ms","CL",$F$1="LMS5 31 ClPRODUCT4 ms","JZ",$F$1="LMS8 31 ClPRODUCT4 ms","DL",$F$1="LMS6 31 ClPRODUCT4 ms","MD",TRUE, ""),IF(AND($E$1="GENINTEGRATION 22 Attributes",$E22<>""),"22","")),"")} -> CV | H22: lis_person_name_family | I22: family_name | J22: Yes | K22: Yes | L22: Yes | M22: Yes | N22: Yes | O22: Yes | P22: =IF(AND($H22<>"",Q22<>""),$H22,"") -> lis_person_name_family | Q22: =IF($J22="yes",$I22,"") -> family_name | R22: =IF(AND($H22<>"",S22<>""),$H22,"") -> lis_person_name_family | S22: =IF($K22="yes",$I22,"") -> family_name | T22: =IF(AND($H22<>"",U22<>""),$H22,"") -> lis_person_name_family | U22: =IF($L22="yes",$I22,"") -> family_name | V22: =IF(AND($H22<>"",W22<>""),$H22,"") -> lis_person_name_family | W22: =IF($M22="yes",$I22,"") -> family_name | X22: =IF(AND($H22<>"",Y22<>""),$H22,"") -> lis_person_name_family | Y22: =IF($N22="yes",$I22,"") -> family_name | Z22: =IF(AND($H22<>"",AA22<>""),$H22,"") -> lis_person_name_family | AA22: =IF($L22="yes",$I22,"") -> family_name | AC22: Value | AD22: =IF('Program Config'!$F$10<>"",'Program Config'!$F$10,"") -> DEMO
A23: {=IFERROR(_xlfn.IFS($A$13=$AC$1,"",$A$13=$AC$10,$AC20,TRUE,""),"")} -> Set custom_ap to Program Name | E23: {=IFERROR(_xlfn.IFS($E$1="GENINTEGRATION 22 Parameters",(_xlfn.IFS($F$1=$Q$1,INDEX($P$2:$P$100,MATCH(0,INDEX(COUNTIF($E$1:$E22,$P$2:$P$100)+(COUNTIF($P$2:$P$100,$P$2:$P$100)<>1),0,0),0)),$F$1=$S$1,INDEX($R$2:$R$100,MATCH(0,INDEX(COUNTIF($E$1:$E22,$R$2:$R$100)+(COUNTIF($R$2:$R$100,$R$2:$R$100)<>1),0,0),0)),$F$1=$U$1,INDEX($T$2:$T$100,MATCH(0,INDEX(COUNTIF($E$1:$E22,$T$2:$T$100)+(COUNTIF($T$2:$T$100,$T$2:$T$100)<>1),0,0),0)),$F$1=$W$1,INDEX($V$2:$V$100,MATCH(0,INDEX(COUNTIF($E$1:$E22,$V$2:$V$100)+(COUNTIF($V$2:$V$100,$V$2:$V$100)<>1),0,0),0)),$F$1=$Y$1,INDEX($X$2:$X$100,MATCH(0,INDEX(COUNTIF($E$1:$E22,$X$2:$X$100)+(COUNTIF($X$2:$X$100,$X$2:$X$100)<>1),0,0),0)),$F$1=$AA$1,INDEX($Z$2:$Z$100,MATCH(0,INDEX(COUNTIF($E$1:$E22,$Z$2:$Z$100)+(COUNTIF($Z$2:$Z$100,$Z$2:$Z$100)<>1),0,0),0)),TRUE,"")),$E$1="GENINTEGRATION 22 Attributes",INDEX($H$2:$H$100,MATCH(0,INDEX(COUNTIF($E$1:$E22,$H$2:$H$100)+(COUNTIF($H$2:$H$100,$H$2:$H$100)<>1),0,0),0)),TRUE,""),"")} -> lis_person_name_given | F23: {=IFERROR(_xlfn.IFS($F$1=$Q$1,_xlfn.XLOOKUP($E23,$P$2:$P$100,Q$2:Q$100)&"",$F$1=$S$1,_xlfn.XLOOKUP($E23,$R$2:$R$100,$S$2:$S$100)&"",$F$1=$Y$1,_xlfn.XLOOKUP($E23,$X$2:$X$100,$Y$2:$Y$100)&"",$F$1=$U$1,_xlfn.XLOOKUP($E23,$T$2:$T$100,$U$2:$U$100)&"",$F$1=$W$1,_xlfn.XLOOKUP($E23,$V$2:$V$100,$W$2:$W$100)&"",$F$1=$AA$1,_xlfn.XLOOKUP($E23,$Z$2:$Z$100,$AA$2:$AA$100)&"",TRUE, ""),"")} -> given_name | G23: {=IFERROR(IF($F23<>"",_xlfn.IFS($F$1="LM7 31 ClPRODUCT4 ms","LM7",$F$1="LMS1 31 ClPRODUCT4 ms","CV",$F$1="LMS2 31 ClPRODUCT4 ms","CL",$F$1="LMS5 31 ClPRODUCT4 ms","JZ",$F$1="LMS8 31 ClPRODUCT4 ms","DL",$F$1="LMS6 31 ClPRODUCT4 ms","MD",TRUE, ""),IF(AND($E$1="GENINTEGRATION 22 Attributes",$E23<>""),"22","")),"")} -> CV | H23: lis_person_name_full | I23: name | J23: Yes | K23: Yes | L23: Yes | M23: Yes | N23: Yes | O23: Yes | P23: =IF(AND($H23<>"",Q23<>""),$H23,"") -> lis_person_name_full | Q23: =IF($J23="yes",$I23,"") -> name | R23: =IF(AND($H23<>"",S23<>""),$H23,"") -> lis_person_name_full | S23: =IF($K23="yes",$I23,"") -> name | T23: =IF(AND($H23<>"",U23<>""),$H23,"") -> lis_person_name_full | U23: =IF($L23="yes",$I23,"") -> name | V23: =IF(AND($H23<>"",W23<>""),$H23,"") -> lis_person_name_full | W23: =IF($M23="yes",$I23,"") -> name | X23: =IF(AND($H23<>"",Y23<>""),$H23,"") -> lis_person_name_full | Y23: =IF($N23="yes",$I23,"") -> name | Z23: =IF(AND($H23<>"",AA23<>""),$H23,"") -> lis_person_name_full | AA23: =IF($L23="yes",$I23,"") -> name | AC23: Set a Generic custom_ap using the LMS Name
A24: {=IFERROR(_xlfn.IFS($A$13=$AC$1,"",$A$13=$AC$10,$AC21,TRUE,""),"")} -> Parameter | B24: {=IFERROR(_xlfn.IFS($A$13=$AC$1,"",$A$13=$AC$10,$AD21,TRUE,""),"")} -> https://purl.demodata7.org/spec/GENINTEGRATION/clPRODUCT4 m/custom|custom_ap | E24: {=IFERROR(_xlfn.IFS($E$1="GENINTEGRATION 22 Parameters",(_xlfn.IFS($F$1=$Q$1,INDEX($P$2:$P$100,MATCH(0,INDEX(COUNTIF($E$1:$E23,$P$2:$P$100)+(COUNTIF($P$2:$P$100,$P$2:$P$100)<>1),0,0),0)),$F$1=$S$1,INDEX($R$2:$R$100,MATCH(0,INDEX(COUNTIF($E$1:$E23,$R$2:$R$100)+(COUNTIF($R$2:$R$100,$R$2:$R$100)<>1),0,0),0)),$F$1=$U$1,INDEX($T$2:$T$100,MATCH(0,INDEX(COUNTIF($E$1:$E23,$T$2:$T$100)+(COUNTIF($T$2:$T$100,$T$2:$T$100)<>1),0,0),0)),$F$1=$W$1,INDEX($V$2:$V$100,MATCH(0,INDEX(COUNTIF($E$1:$E23,$V$2:$V$100)+(COUNTIF($V$2:$V$100,$V$2:$V$100)<>1),0,0),0)),$F$1=$Y$1,INDEX($X$2:$X$100,MATCH(0,INDEX(COUNTIF($E$1:$E23,$X$2:$X$100)+(COUNTIF($X$2:$X$100,$X$2:$X$100)<>1),0,0),0)),$F$1=$AA$1,INDEX($Z$2:$Z$100,MATCH(0,INDEX(COUNTIF($E$1:$E23,$Z$2:$Z$100)+(COUNTIF($Z$2:$Z$100,$Z$2:$Z$100)<>1),0,0),0)),TRUE,"")),$E$1="GENINTEGRATION 22 Attributes",INDEX($H$2:$H$100,MATCH(0,INDEX(COUNTIF($E$1:$E23,$H$2:$H$100)+(COUNTIF($H$2:$H$100,$H$2:$H$100)<>1),0,0),0)),TRUE,""),"")} -> lis_person_Type2 | F24: {=IFERROR(_xlfn.IFS($F$1=$Q$1,_xlfn.XLOOKUP($E24,$P$2:$P$100,Q$2:Q$100)&"",$F$1=$S$1,_xlfn.XLOOKUP($E24,$R$2:$R$100,$S$2:$S$100)&"",$F$1=$Y$1,_xlfn.XLOOKUP($E24,$X$2:$X$100,$Y$2:$Y$100)&"",$F$1=$U$1,_xlfn.XLOOKUP($E24,$T$2:$T$100,$U$2:$U$100)&"",$F$1=$W$1,_xlfn.XLOOKUP($E24,$V$2:$V$100,$W$2:$W$100)&"",$F$1=$AA$1,_xlfn.XLOOKUP($E24,$Z$2:$Z$100,$AA$2:$AA$100)&"",TRUE, ""),"")} -> https://purl.demodata7.org/spec/GENINTEGRATION/clPRODUCT4 m/lis|person_Type2 | G24: {=IFERROR(IF($F24<>"",_xlfn.IFS($F$1="LM7 31 ClPRODUCT4 ms","LM7",$F$1="LMS1 31 ClPRODUCT4 ms","CV",$F$1="LMS2 31 ClPRODUCT4 ms","CL",$F$1="LMS5 31 ClPRODUCT4 ms","JZ",$F$1="LMS8 31 ClPRODUCT4 ms","DL",$F$1="LMS6 31 ClPRODUCT4 ms","MD",TRUE, ""),IF(AND($E$1="GENINTEGRATION 22 Attributes",$E24<>""),"22","")),"")} -> CV | H24: lis_person_name_given | I24: given_name | J24: Yes | K24: Yes | L24: Yes | M24: Yes | N24: Yes | O24: Yes | P24: =IF(AND($H24<>"",Q24<>""),$H24,"") -> lis_person_name_given | Q24: =IF($J24="yes",$I24,"") -> given_name | R24: =IF(AND($H24<>"",S24<>""),$H24,"") -> lis_person_name_given | S24: =IF($K24="yes",$I24,"") -> given_name | T24: =IF(AND($H24<>"",U24<>""),$H24,"") -> lis_person_name_given | U24: =IF($L24="yes",$I24,"") -> given_name | V24: =IF(AND($H24<>"",W24<>""),$H24,"") -> lis_person_name_given | W24: =IF($M24="yes",$I24,"") -> given_name | X24: =IF(AND($H24<>"",Y24<>""),$H24,"") -> lis_person_name_given | Y24: =IF($N24="yes",$I24,"") -> given_name | Z24: =IF(AND($H24<>"",AA24<>""),$H24,"") -> lis_person_name_given | AA24: =IF($L24="yes",$I24,"") -> given_name | AC24: From | AD24: https://purl.demodata7.org/spec/GENINTEGRATION/clPRODUCT4 m/tool_platform|product_family_code
A25: {=IFERROR(_xlfn.IFS($A$13=$AC$1,"",$A$13=$AC$10,$AC22,TRUE,""),"")} -> Value | B25: {=IFERROR(_xlfn.IFS($A$13=$AC$1,"",$A$13=$AC$10,$AD22,TRUE,""),"")} -> DEMO | E25: {=IFERROR(_xlfn.IFS($E$1="GENINTEGRATION 22 Parameters",(_xlfn.IFS($F$1=$Q$1,INDEX($P$2:$P$100,MATCH(0,INDEX(COUNTIF($E$1:$E24,$P$2:$P$100)+(COUNTIF($P$2:$P$100,$P$2:$P$100)<>1),0,0),0)),$F$1=$S$1,INDEX($R$2:$R$100,MATCH(0,INDEX(COUNTIF($E$1:$E24,$R$2:$R$100)+(COUNTIF($R$2:$R$100,$R$2:$R$100)<>1),0,0),0)),$F$1=$U$1,INDEX($T$2:$T$100,MATCH(0,INDEX(COUNTIF($E$1:$E24,$T$2:$T$100)+(COUNTIF($T$2:$T$100,$T$2:$T$100)<>1),0,0),0)),$F$1=$W$1,INDEX($V$2:$V$100,MATCH(0,INDEX(COUNTIF($E$1:$E24,$V$2:$V$100)+(COUNTIF($V$2:$V$100,$V$2:$V$100)<>1),0,0),0)),$F$1=$Y$1,INDEX($X$2:$X$100,MATCH(0,INDEX(COUNTIF($E$1:$E24,$X$2:$X$100)+(COUNTIF($X$2:$X$100,$X$2:$X$100)<>1),0,0),0)),$F$1=$AA$1,INDEX($Z$2:$Z$100,MATCH(0,INDEX(COUNTIF($E$1:$E24,$Z$2:$Z$100)+(COUNTIF($Z$2:$Z$100,$Z$2:$Z$100)<>1),0,0),0)),TRUE,"")),$E$1="GENINTEGRATION 22 Attributes",INDEX($H$2:$H$100,MATCH(0,INDEX(COUNTIF($E$1:$E24,$H$2:$H$100)+(COUNTIF($H$2:$H$100,$H$2:$H$100)<>1),0,0),0)),TRUE,""),"")} -> GENINTEGRATION_message_type | F25: {=IFERROR(_xlfn.IFS($F$1=$Q$1,_xlfn.XLOOKUP($E25,$P$2:$P$100,Q$2:Q$100)&"",$F$1=$S$1,_xlfn.XLOOKUP($E25,$R$2:$R$100,$S$2:$S$100)&"",$F$1=$Y$1,_xlfn.XLOOKUP($E25,$X$2:$X$100,$Y$2:$Y$100)&"",$F$1=$U$1,_xlfn.XLOOKUP($E25,$T$2:$T$100,$U$2:$U$100)&"",$F$1=$W$1,_xlfn.XLOOKUP($E25,$V$2:$V$100,$W$2:$W$100)&"",$F$1=$AA$1,_xlfn.XLOOKUP($E25,$Z$2:$Z$100,$AA$2:$AA$100)&"",TRUE, ""),"")} -> https://purl.demodata7.org/spec/GENINTEGRATION/clPRODUCT4 m/message_type | G25: {=IFERROR(IF($F25<>"",_xlfn.IFS($F$1="LM7 31 ClPRODUCT4 ms","LM7",$F$1="LMS1 31 ClPRODUCT4 ms","CV",$F$1="LMS2 31 ClPRODUCT4 ms","CL",$F$1="LMS5 31 ClPRODUCT4 ms","JZ",$F$1="LMS8 31 ClPRODUCT4 ms","DL",$F$1="LMS6 31 ClPRODUCT4 ms","MD",TRUE, ""),IF(AND($E$1="GENINTEGRATION 22 Attributes",$E25<>""),"22","")),"")} -> CV | H25: lis_person_Type2 | I25: https://purl.demodata7.org/spec/GENINTEGRATION/clPRODUCT4 m/lis|person_Type2 | J25: Yes | K25: Yes | L25: Yes | M25: Yes | N25: Yes | O25: Yes | P25: =IF(AND($H25<>"",Q25<>""),$H25,"") -> lis_person_Type2 | Q25: =IF($J25="yes",$I25,"") -> https://purl.demodata7.org/spec/GENINTEGRATION/clPRODUCT4 m/lis|person_Type2 | R25: =IF(AND($H25<>"",S25<>""),$H25,"") -> lis_person_Type2 | S25: =IF($K25="yes",$I25,"") -> https://purl.demodata7.org/spec/GENINTEGRATION/clPRODUCT4 m/lis|person_Type2 | T25: =IF(AND($H25<>"",U25<>""),$H25,"") -> lis_person_Type2 | U25: =IF($L25="yes",$I25,"") -> https://purl.demodata7.org/spec/GENINTEGRATION/clPRODUCT4 m/lis|person_Type2 | V25: =IF(AND($H25<>"",W25<>""),$H25,"") -> lis_person_Type2 | W25: =IF($M25="yes",$I25,"") -> https://purl.demodata7.org/spec/GENINTEGRATION/clPRODUCT4 m/lis|person_Type2 | X25: =IF(AND($H25<>"",Y25<>""),$H25,"") -> lis_person_Type2 | Y25: =IF($N25="yes",$I25,"") -> https://purl.demodata7.org/spec/GENINTEGRATION/clPRODUCT4 m/lis|person_Type2 | Z25: =IF(AND($H25<>"",AA25<>""),$H25,"") -> lis_person_Type2 | AA25: =IF($L25="yes",$I25,"") -> https://purl.demodata7.org/spec/GENINTEGRATION/clPRODUCT4 m/lis|person_Type2 | AC25: To | AD25: https://purl.demodata7.org/spec/GENINTEGRATION/clPRODUCT4 m/custom|custom_ap
A26: {=IFERROR(_xlfn.IFS($A$13=$AC$1,"",$A$13=$AC$10,$AC23,TRUE,""),"")} -> Set a Generic custom_ap using the LMS Name | E26: {=IFERROR(_xlfn.IFS($E$1="GENINTEGRATION 22 Parameters",(_xlfn.IFS($F$1=$Q$1,INDEX($P$2:$P$100,MATCH(0,INDEX(COUNTIF($E$1:$E25,$P$2:$P$100)+(COUNTIF($P$2:$P$100,$P$2:$P$100)<>1),0,0),0)),$F$1=$S$1,INDEX($R$2:$R$100,MATCH(0,INDEX(COUNTIF($E$1:$E25,$R$2:$R$100)+(COUNTIF($R$2:$R$100,$R$2:$R$100)<>1),0,0),0)),$F$1=$U$1,INDEX($T$2:$T$100,MATCH(0,INDEX(COUNTIF($E$1:$E25,$T$2:$T$100)+(COUNTIF($T$2:$T$100,$T$2:$T$100)<>1),0,0),0)),$F$1=$W$1,INDEX($V$2:$V$100,MATCH(0,INDEX(COUNTIF($E$1:$E25,$V$2:$V$100)+(COUNTIF($V$2:$V$100,$V$2:$V$100)<>1),0,0),0)),$F$1=$Y$1,INDEX($X$2:$X$100,MATCH(0,INDEX(COUNTIF($E$1:$E25,$X$2:$X$100)+(COUNTIF($X$2:$X$100,$X$2:$X$100)<>1),0,0),0)),$F$1=$AA$1,INDEX($Z$2:$Z$100,MATCH(0,INDEX(COUNTIF($E$1:$E25,$Z$2:$Z$100)+(COUNTIF($Z$2:$Z$100,$Z$2:$Z$100)<>1),0,0),0)),TRUE,"")),$E$1="GENINTEGRATION 22 Attributes",INDEX($H$2:$H$100,MATCH(0,INDEX(COUNTIF($E$1:$E25,$H$2:$H$100)+(COUNTIF($H$2:$H$100,$H$2:$H$100)<>1),0,0),0)),TRUE,""),"")} -> GENINTEGRATION_version | F26: {=IFERROR(_xlfn.IFS($F$1=$Q$1,_xlfn.XLOOKUP($E26,$P$2:$P$100,Q$2:Q$100)&"",$F$1=$S$1,_xlfn.XLOOKUP($E26,$R$2:$R$100,$S$2:$S$100)&"",$F$1=$Y$1,_xlfn.XLOOKUP($E26,$X$2:$X$100,$Y$2:$Y$100)&"",$F$1=$U$1,_xlfn.XLOOKUP($E26,$T$2:$T$100,$U$2:$U$100)&"",$F$1=$W$1,_xlfn.XLOOKUP($E26,$V$2:$V$100,$W$2:$W$100)&"",$F$1=$AA$1,_xlfn.XLOOKUP($E26,$Z$2:$Z$100,$AA$2:$AA$100)&"",TRUE, ""),"")} -> https://purl.demodata7.org/spec/GENINTEGRATION/clPRODUCT4 m/version | G26: {=IFERROR(IF($F26<>"",_xlfn.IFS($F$1="LM7 31 ClPRODUCT4 ms","LM7",$F$1="LMS1 31 ClPRODUCT4 ms","CV",$F$1="LMS2 31 ClPRODUCT4 ms","CL",$F$1="LMS5 31 ClPRODUCT4 ms","JZ",$F$1="LMS8 31 ClPRODUCT4 ms","DL",$F$1="LMS6 31 ClPRODUCT4 ms","MD",TRUE, ""),IF(AND($E$1="GENINTEGRATION 22 Attributes",$E26<>""),"22","")),"")} -> CV | H26: GENINTEGRATION_message_type | I26: https://purl.demodata7.org/spec/GENINTEGRATION/clPRODUCT4 m/message_type | J26: Yes | K26: Yes | L26: Yes | M26: Yes | N26: Yes | O26: Yes | P26: =IF(AND($H26<>"",Q26<>""),$H26,"") -> GENINTEGRATION_message_type | Q26: =IF($J26="yes",$I26,"") -> https://purl.demodata7.org/spec/GENINTEGRATION/clPRODUCT4 m/message_type | R26: =IF(AND($H26<>"",S26<>""),$H26,"") -> GENINTEGRATION_message_type | S26: =IF($K26="yes",$I26,"") -> https://purl.demodata7.org/spec/GENINTEGRATION/clPRODUCT4 m/message_type | T26: =IF(AND($H26<>"",U26<>""),$H26,"") -> GENINTEGRATION_message_type | U26: =IF($L26="yes",$I26,"") -> https://purl.demodata7.org/spec/GENINTEGRATION/clPRODUCT4 m/message_type | V26: =IF(AND($H26<>"",W26<>""),$H26,"") -> GENINTEGRATION_message_type | W26: =IF($M26="yes",$I26,"") -> https://purl.demodata7.org/spec/GENINTEGRATION/clPRODUCT4 m/message_type | X26: =IF(AND($H26<>"",Y26<>""),$H26,"") -> GENINTEGRATION_message_type | Y26: =IF($N26="yes",$I26,"") -> https://purl.demodata7.org/spec/GENINTEGRATION/clPRODUCT4 m/message_type | Z26: =IF(AND($H26<>"",AA26<>""),$H26,"") -> GENINTEGRATION_message_type | AA26: =IF($L26="yes",$I26,"") -> https://purl.demodata7.org/spec/GENINTEGRATION/clPRODUCT4 m/message_type
A27: {=IFERROR(_xlfn.IFS($A$13=$AC$1,"",$A$13=$AC$10,$AC24,TRUE,""),"")} -> From | B27: {=IFERROR(_xlfn.IFS($A$13=$AC$1,"",$A$13=$AC$10,$AD24,TRUE,""),"")} -> https://purl.demodata7.org/spec/GENINTEGRATION/clPRODUCT4 m/tool_platform|product_family_code | E27: {=IFERROR(_xlfn.IFS($E$1="GENINTEGRATION 22 Parameters",(_xlfn.IFS($F$1=$Q$1,INDEX($P$2:$P$100,MATCH(0,INDEX(COUNTIF($E$1:$E26,$P$2:$P$100)+(COUNTIF($P$2:$P$100,$P$2:$P$100)<>1),0,0),0)),$F$1=$S$1,INDEX($R$2:$R$100,MATCH(0,INDEX(COUNTIF($E$1:$E26,$R$2:$R$100)+(COUNTIF($R$2:$R$100,$R$2:$R$100)<>1),0,0),0)),$F$1=$U$1,INDEX($T$2:$T$100,MATCH(0,INDEX(COUNTIF($E$1:$E26,$T$2:$T$100)+(COUNTIF($T$2:$T$100,$T$2:$T$100)<>1),0,0),0)),$F$1=$W$1,INDEX($V$2:$V$100,MATCH(0,INDEX(COUNTIF($E$1:$E26,$V$2:$V$100)+(COUNTIF($V$2:$V$100,$V$2:$V$100)<>1),0,0),0)),$F$1=$Y$1,INDEX($X$2:$X$100,MATCH(0,INDEX(COUNTIF($E$1:$E26,$X$2:$X$100)+(COUNTIF($X$2:$X$100,$X$2:$X$100)<>1),0,0),0)),$F$1=$AA$1,INDEX($Z$2:$Z$100,MATCH(0,INDEX(COUNTIF($E$1:$E26,$Z$2:$Z$100)+(COUNTIF($Z$2:$Z$100,$Z$2:$Z$100)<>1),0,0),0)),TRUE,"")),$E$1="GENINTEGRATION 22 Attributes",INDEX($H$2:$H$100,MATCH(0,INDEX(COUNTIF($E$1:$E26,$H$2:$H$100)+(COUNTIF($H$2:$H$100,$H$2:$H$100)<>1),0,0),0)),TRUE,""),"")} -> resource_link_description | F27: {=IFERROR(_xlfn.IFS($F$1=$Q$1,_xlfn.XLOOKUP($E27,$P$2:$P$100,Q$2:Q$100)&"",$F$1=$S$1,_xlfn.XLOOKUP($E27,$R$2:$R$100,$S$2:$S$100)&"",$F$1=$Y$1,_xlfn.XLOOKUP($E27,$X$2:$X$100,$Y$2:$Y$100)&"",$F$1=$U$1,_xlfn.XLOOKUP($E27,$T$2:$T$100,$U$2:$U$100)&"",$F$1=$W$1,_xlfn.XLOOKUP($E27,$V$2:$V$100,$W$2:$W$100)&"",$F$1=$AA$1,_xlfn.XLOOKUP($E27,$Z$2:$Z$100,$AA$2:$AA$100)&"",TRUE, ""),"")} -> https://purl.demodata7.org/spec/GENINTEGRATION/clPRODUCT4 m/resource_link|description | G27: {=IFERROR(IF($F27<>"",_xlfn.IFS($F$1="LM7 31 ClPRODUCT4 ms","LM7",$F$1="LMS1 31 ClPRODUCT4 ms","CV",$F$1="LMS2 31 ClPRODUCT4 ms","CL",$F$1="LMS5 31 ClPRODUCT4 ms","JZ",$F$1="LMS8 31 ClPRODUCT4 ms","DL",$F$1="LMS6 31 ClPRODUCT4 ms","MD",TRUE, ""),IF(AND($E$1="GENINTEGRATION 22 Attributes",$E27<>""),"22","")),"")} -> CV | H27: GENINTEGRATION_version | I27: https://purl.demodata7.org/spec/GENINTEGRATION/clPRODUCT4 m/version | J27: Yes | K27: Yes | L27: Yes | M27: Yes | N27: Yes | O27: Yes | P27: =IF(AND($H27<>"",Q27<>""),$H27,"") -> GENINTEGRATION_version | Q27: =IF($J27="yes",$I27,"") -> https://purl.demodata7.org/spec/GENINTEGRATION/clPRODUCT4 m/version | R27: =IF(AND($H27<>"",S27<>""),$H27,"") -> GENINTEGRATION_version | S27: =IF($K27="yes",$I27,"") -> https://purl.demodata7.org/spec/GENINTEGRATION/clPRODUCT4 m/version | T27: =IF(AND($H27<>"",U27<>""),$H27,"") -> GENINTEGRATION_version | U27: =IF($L27="yes",$I27,"") -> https://purl.demodata7.org/spec/GENINTEGRATION/clPRODUCT4 m/version | V27: =IF(AND($H27<>"",W27<>""),$H27,"") -> GENINTEGRATION_version | W27: =IF($M27="yes",$I27,"") -> https://purl.demodata7.org/spec/GENINTEGRATION/clPRODUCT4 m/version | X27: =IF(AND($H27<>"",Y27<>""),$H27,"") -> GENINTEGRATION_version | Y27: =IF($N27="yes",$I27,"") -> https://purl.demodata7.org/spec/GENINTEGRATION/clPRODUCT4 m/version | Z27: =IF(AND($H27<>"",AA27<>""),$H27,"") -> GENINTEGRATION_version | AA27: =IF($L27="yes",$I27,"") -> https://purl.demodata7.org/spec/GENINTEGRATION/clPRODUCT4 m/version
A28: {=IFERROR(_xlfn.IFS($A$13=$AC$1,"",$A$13=$AC$10,$AC25,TRUE,""),"")} -> To | B28: {=IFERROR(_xlfn.IFS($A$13=$AC$1,"",$A$13=$AC$10,$AD25,TRUE,""),"")} -> https://purl.demodata7.org/spec/GENINTEGRATION/clPRODUCT4 m/custom|custom_ap | E28: {=IFERROR(_xlfn.IFS($E$1="GENINTEGRATION 22 Parameters",(_xlfn.IFS($F$1=$Q$1,INDEX($P$2:$P$100,MATCH(0,INDEX(COUNTIF($E$1:$E27,$P$2:$P$100)+(COUNTIF($P$2:$P$100,$P$2:$P$100)<>1),0,0),0)),$F$1=$S$1,INDEX($R$2:$R$100,MATCH(0,INDEX(COUNTIF($E$1:$E27,$R$2:$R$100)+(COUNTIF($R$2:$R$100,$R$2:$R$100)<>1),0,0),0)),$F$1=$U$1,INDEX($T$2:$T$100,MATCH(0,INDEX(COUNTIF($E$1:$E27,$T$2:$T$100)+(COUNTIF($T$2:$T$100,$T$2:$T$100)<>1),0,0),0)),$F$1=$W$1,INDEX($V$2:$V$100,MATCH(0,INDEX(COUNTIF($E$1:$E27,$V$2:$V$100)+(COUNTIF($V$2:$V$100,$V$2:$V$100)<>1),0,0),0)),$F$1=$Y$1,INDEX($X$2:$X$100,MATCH(0,INDEX(COUNTIF($E$1:$E27,$X$2:$X$100)+(COUNTIF($X$2:$X$100,$X$2:$X$100)<>1),0,0),0)),$F$1=$AA$1,INDEX($Z$2:$Z$100,MATCH(0,INDEX(COUNTIF($E$1:$E27,$Z$2:$Z$100)+(COUNTIF($Z$2:$Z$100,$Z$2:$Z$100)<>1),0,0),0)),TRUE,"")),$E$1="GENINTEGRATION 22 Attributes",INDEX($H$2:$H$100,MATCH(0,INDEX(COUNTIF($E$1:$E27,$H$2:$H$100)+(COUNTIF($H$2:$H$100,$H$2:$H$100)<>1),0,0),0)),TRUE,""),"")} -> resource_link_id | F28: {=IFERROR(_xlfn.IFS($F$1=$Q$1,_xlfn.XLOOKUP($E28,$P$2:$P$100,Q$2:Q$100)&"",$F$1=$S$1,_xlfn.XLOOKUP($E28,$R$2:$R$100,$S$2:$S$100)&"",$F$1=$Y$1,_xlfn.XLOOKUP($E28,$X$2:$X$100,$Y$2:$Y$100)&"",$F$1=$U$1,_xlfn.XLOOKUP($E28,$T$2:$T$100,$U$2:$U$100)&"",$F$1=$W$1,_xlfn.XLOOKUP($E28,$V$2:$V$100,$W$2:$W$100)&"",$F$1=$AA$1,_xlfn.XLOOKUP($E28,$Z$2:$Z$100,$AA$2:$AA$100)&"",TRUE, ""),"")} -> https://purl.demodata7.org/spec/GENINTEGRATION/clPRODUCT4 m/resource_link|id | G28: {=IFERROR(IF($F28<>"",_xlfn.IFS($F$1="LM7 31 ClPRODUCT4 ms","LM7",$F$1="LMS1 31 ClPRODUCT4 ms","CV",$F$1="LMS2 31 ClPRODUCT4 ms","CL",$F$1="LMS5 31 ClPRODUCT4 ms","JZ",$F$1="LMS8 31 ClPRODUCT4 ms","DL",$F$1="LMS6 31 ClPRODUCT4 ms","MD",TRUE, ""),IF(AND($E$1="GENINTEGRATION 22 Attributes",$E28<>""),"22","")),"")} -> CV | H28: resource_link_description | I28: https://purl.demodata7.org/spec/GENINTEGRATION/clPRODUCT4 m/resource_link|description | J28: Yes | K28: Yes | L28: Yes | M28: Yes | N28: Yes | O28: Yes | P28: =IF(AND($H28<>"",Q28<>""),$H28,"") -> resource_link_description | Q28: =IF($J28="yes",$I28,"") -> https://purl.demodata7.org/spec/GENINTEGRATION/clPRODUCT4 m/resource_link|description | R28: =IF(AND($H28<>"",S28<>""),$H28,"") -> resource_link_description | S28: =IF($K28="yes",$I28,"") -> https://purl.demodata7.org/spec/GENINTEGRATION/clPRODUCT4 m/resource_link|description | T28: =IF(AND($H28<>"",U28<>""),$H28,"") -> resource_link_description | U28: =IF($L28="yes",$I28,"") -> https://purl.demodata7.org/spec/GENINTEGRATION/clPRODUCT4 m/resource_link|description | V28: =IF(AND($H28<>"",W28<>""),$H28,"") -> resource_link_description | W28: =IF($M28="yes",$I28,"") -> https://purl.demodata7.org/spec/GENINTEGRATION/clPRODUCT4 m/resource_link|description | X28: =IF(AND($H28<>"",Y28<>""),$H28,"") -> resource_link_description | Y28: =IF($N28="yes",$I28,"") -> https://purl.demodata7.org/spec/GENINTEGRATION/clPRODUCT4 m/resource_link|description | Z28: =IF(AND($H28<>"",AA28<>""),$H28,"") -> resource_link_description | AA28: =IF($L28="yes",$I28,"") -> https://purl.demodata7.org/spec/GENINTEGRATION/clPRODUCT4 m/resource_link|description
E29: {=IFERROR(_xlfn.IFS($E$1="GENINTEGRATION 22 Parameters",(_xlfn.IFS($F$1=$Q$1,INDEX($P$2:$P$100,MATCH(0,INDEX(COUNTIF($E$1:$E28,$P$2:$P$100)+(COUNTIF($P$2:$P$100,$P$2:$P$100)<>1),0,0),0)),$F$1=$S$1,INDEX($R$2:$R$100,MATCH(0,INDEX(COUNTIF($E$1:$E28,$R$2:$R$100)+(COUNTIF($R$2:$R$100,$R$2:$R$100)<>1),0,0),0)),$F$1=$U$1,INDEX($T$2:$T$100,MATCH(0,INDEX(COUNTIF($E$1:$E28,$T$2:$T$100)+(COUNTIF($T$2:$T$100,$T$2:$T$100)<>1),0,0),0)),$F$1=$W$1,INDEX($V$2:$V$100,MATCH(0,INDEX(COUNTIF($E$1:$E28,$V$2:$V$100)+(COUNTIF($V$2:$V$100,$V$2:$V$100)<>1),0,0),0)),$F$1=$Y$1,INDEX($X$2:$X$100,MATCH(0,INDEX(COUNTIF($E$1:$E28,$X$2:$X$100)+(COUNTIF($X$2:$X$100,$X$2:$X$100)<>1),0,0),0)),$F$1=$AA$1,INDEX($Z$2:$Z$100,MATCH(0,INDEX(COUNTIF($E$1:$E28,$Z$2:$Z$100)+(COUNTIF($Z$2:$Z$100,$Z$2:$Z$100)<>1),0,0),0)),TRUE,"")),$E$1="GENINTEGRATION 22 Attributes",INDEX($H$2:$H$100,MATCH(0,INDEX(COUNTIF($E$1:$E28,$H$2:$H$100)+(COUNTIF($H$2:$H$100,$H$2:$H$100)<>1),0,0),0)),TRUE,""),"")} -> resource_link_title | F29: {=IFERROR(_xlfn.IFS($F$1=$Q$1,_xlfn.XLOOKUP($E29,$P$2:$P$100,Q$2:Q$100)&"",$F$1=$S$1,_xlfn.XLOOKUP($E29,$R$2:$R$100,$S$2:$S$100)&"",$F$1=$Y$1,_xlfn.XLOOKUP($E29,$X$2:$X$100,$Y$2:$Y$100)&"",$F$1=$U$1,_xlfn.XLOOKUP($E29,$T$2:$T$100,$U$2:$U$100)&"",$F$1=$W$1,_xlfn.XLOOKUP($E29,$V$2:$V$100,$W$2:$W$100)&"",$F$1=$AA$1,_xlfn.XLOOKUP($E29,$Z$2:$Z$100,$AA$2:$AA$100)&"",TRUE, ""),"")} -> https://purl.demodata7.org/spec/GENINTEGRATION/clPRODUCT4 m/resource_link|title | G29: {=IFERROR(IF($F29<>"",_xlfn.IFS($F$1="LM7 31 ClPRODUCT4 ms","LM7",$F$1="LMS1 31 ClPRODUCT4 ms","CV",$F$1="LMS2 31 ClPRODUCT4 ms","CL",$F$1="LMS5 31 ClPRODUCT4 ms","JZ",$F$1="LMS8 31 ClPRODUCT4 ms","DL",$F$1="LMS6 31 ClPRODUCT4 ms","MD",TRUE, ""),IF(AND($E$1="GENINTEGRATION 22 Attributes",$E29<>""),"22","")),"")} -> CV | H29: resource_link_id | I29: https://purl.demodata7.org/spec/GENINTEGRATION/clPRODUCT4 m/resource_link|id | J29: Yes | K29: Yes | L29: Yes | M29: Yes | N29: Yes | O29: Yes | P29: =IF(AND($H29<>"",Q29<>""),$H29,"") -> resource_link_id | Q29: =IF($J29="yes",$I29,"") -> https://purl.demodata7.org/spec/GENINTEGRATION/clPRODUCT4 m/resource_link|id | R29: =IF(AND($H29<>"",S29<>""),$H29,"") -> resource_link_id | S29: =IF($K29="yes",$I29,"") -> https://purl.demodata7.org/spec/GENINTEGRATION/clPRODUCT4 m/resource_link|id | T29: =IF(AND($H29<>"",U29<>""),$H29,"") -> resource_link_id | U29: =IF($L29="yes",$I29,"") -> https://purl.demodata7.org/spec/GENINTEGRATION/clPRODUCT4 m/resource_link|id | V29: =IF(AND($H29<>"",W29<>""),$H29,"") -> resource_link_id | W29: =IF($M29="yes",$I29,"") -> https://purl.demodata7.org/spec/GENINTEGRATION/clPRODUCT4 m/resource_link|id | X29: =IF(AND($H29<>"",Y29<>""),$H29,"") -> resource_link_id | Y29: =IF($N29="yes",$I29,"") -> https://purl.demodata7.org/spec/GENINTEGRATION/clPRODUCT4 m/resource_link|id | Z29: =IF(AND($H29<>"",AA29<>""),$H29,"") -> resource_link_id | AA29: =IF($L29="yes",$I29,"") -> https://purl.demodata7.org/spec/GENINTEGRATION/clPRODUCT4 m/resource_link|id
E30: {=IFERROR(_xlfn.IFS($E$1="GENINTEGRATION 22 Parameters",(_xlfn.IFS($F$1=$Q$1,INDEX($P$2:$P$100,MATCH(0,INDEX(COUNTIF($E$1:$E29,$P$2:$P$100)+(COUNTIF($P$2:$P$100,$P$2:$P$100)<>1),0,0),0)),$F$1=$S$1,INDEX($R$2:$R$100,MATCH(0,INDEX(COUNTIF($E$1:$E29,$R$2:$R$100)+(COUNTIF($R$2:$R$100,$R$2:$R$100)<>1),0,0),0)),$F$1=$U$1,INDEX($T$2:$T$100,MATCH(0,INDEX(COUNTIF($E$1:$E29,$T$2:$T$100)+(COUNTIF($T$2:$T$100,$T$2:$T$100)<>1),0,0),0)),$F$1=$W$1,INDEX($V$2:$V$100,MATCH(0,INDEX(COUNTIF($E$1:$E29,$V$2:$V$100)+(COUNTIF($V$2:$V$100,$V$2:$V$100)<>1),0,0),0)),$F$1=$Y$1,INDEX($X$2:$X$100,MATCH(0,INDEX(COUNTIF($E$1:$E29,$X$2:$X$100)+(COUNTIF($X$2:$X$100,$X$2:$X$100)<>1),0,0),0)),$F$1=$AA$1,INDEX($Z$2:$Z$100,MATCH(0,INDEX(COUNTIF($E$1:$E29,$Z$2:$Z$100)+(COUNTIF($Z$2:$Z$100,$Z$2:$Z$100)<>1),0,0),0)),TRUE,"")),$E$1="GENINTEGRATION 22 Attributes",INDEX($H$2:$H$100,MATCH(0,INDEX(COUNTIF($E$1:$E29,$H$2:$H$100)+(COUNTIF($H$2:$H$100,$H$2:$H$100)<>1),0,0),0)),TRUE,""),"")} -> role_scope_mentor | F30: {=IFERROR(_xlfn.IFS($F$1=$Q$1,_xlfn.XLOOKUP($E30,$P$2:$P$100,Q$2:Q$100)&"",$F$1=$S$1,_xlfn.XLOOKUP($E30,$R$2:$R$100,$S$2:$S$100)&"",$F$1=$Y$1,_xlfn.XLOOKUP($E30,$X$2:$X$100,$Y$2:$Y$100)&"",$F$1=$U$1,_xlfn.XLOOKUP($E30,$T$2:$T$100,$U$2:$U$100)&"",$F$1=$W$1,_xlfn.XLOOKUP($E30,$V$2:$V$100,$W$2:$W$100)&"",$F$1=$AA$1,_xlfn.XLOOKUP($E30,$Z$2:$Z$100,$AA$2:$AA$100)&"",TRUE, ""),"")} -> https://purldemodata7.org/spec/GENINTEGRATION/clPRODUCT4 m/role_scope_mentor | G30: {=IFERROR(IF($F30<>"",_xlfn.IFS($F$1="LM7 31 ClPRODUCT4 ms","LM7",$F$1="LMS1 31 ClPRODUCT4 ms","CV",$F$1="LMS2 31 ClPRODUCT4 ms","CL",$F$1="LMS5 31 ClPRODUCT4 ms","JZ",$F$1="LMS8 31 ClPRODUCT4 ms","DL",$F$1="LMS6 31 ClPRODUCT4 ms","MD",TRUE, ""),IF(AND($E$1="GENINTEGRATION 22 Attributes",$E30<>""),"22","")),"")} -> CV | H30: resource_link_title | I30: https://purl.demodata7.org/spec/GENINTEGRATION/clPRODUCT4 m/resource_link|title | J30: Yes | K30: Yes | L30: Yes | M30: Yes | N30: Yes | O30: Yes | P30: =IF(AND($H30<>"",Q30<>""),$H30,"") -> resource_link_title | Q30: =IF($J30="yes",$I30,"") -> https://purl.demodata7.org/spec/GENINTEGRATION/clPRODUCT4 m/resource_link|title | R30: =IF(AND($H30<>"",S30<>""),$H30,"") -> resource_link_title | S30: =IF($K30="yes",$I30,"") -> https://purl.demodata7.org/spec/GENINTEGRATION/clPRODUCT4 m/resource_link|title | T30: =IF(AND($H30<>"",U30<>""),$H30,"") -> resource_link_title | U30: =IF($L30="yes",$I30,"") -> https://purl.demodata7.org/spec/GENINTEGRATION/clPRODUCT4 m/resource_link|title | V30: =IF(AND($H30<>"",W30<>""),$H30,"") -> resource_link_title | W30: =IF($M30="yes",$I30,"") -> https://purl.demodata7.org/spec/GENINTEGRATION/clPRODUCT4 m/resource_link|title | X30: =IF(AND($H30<>"",Y30<>""),$H30,"") -> resource_link_title | Y30: =IF($N30="yes",$I30,"") -> https://purl.demodata7.org/spec/GENINTEGRATION/clPRODUCT4 m/resource_link|title | Z30: =IF(AND($H30<>"",AA30<>""),$H30,"") -> resource_link_title | AA30: =IF($L30="yes",$I30,"") -> https://purl.demodata7.org/spec/GENINTEGRATION/clPRODUCT4 m/resource_link|title
E31: {=IFERROR(_xlfn.IFS($E$1="GENINTEGRATION 22 Parameters",(_xlfn.IFS($F$1=$Q$1,INDEX($P$2:$P$100,MATCH(0,INDEX(COUNTIF($E$1:$E30,$P$2:$P$100)+(COUNTIF($P$2:$P$100,$P$2:$P$100)<>1),0,0),0)),$F$1=$S$1,INDEX($R$2:$R$100,MATCH(0,INDEX(COUNTIF($E$1:$E30,$R$2:$R$100)+(COUNTIF($R$2:$R$100,$R$2:$R$100)<>1),0,0),0)),$F$1=$U$1,INDEX($T$2:$T$100,MATCH(0,INDEX(COUNTIF($E$1:$E30,$T$2:$T$100)+(COUNTIF($T$2:$T$100,$T$2:$T$100)<>1),0,0),0)),$F$1=$W$1,INDEX($V$2:$V$100,MATCH(0,INDEX(COUNTIF($E$1:$E30,$V$2:$V$100)+(COUNTIF($V$2:$V$100,$V$2:$V$100)<>1),0,0),0)),$F$1=$Y$1,INDEX($X$2:$X$100,MATCH(0,INDEX(COUNTIF($E$1:$E30,$X$2:$X$100)+(COUNTIF($X$2:$X$100,$X$2:$X$100)<>1),0,0),0)),$F$1=$AA$1,INDEX($Z$2:$Z$100,MATCH(0,INDEX(COUNTIF($E$1:$E30,$Z$2:$Z$100)+(COUNTIF($Z$2:$Z$100,$Z$2:$Z$100)<>1),0,0),0)),TRUE,"")),$E$1="GENINTEGRATION 22 Attributes",INDEX($H$2:$H$100,MATCH(0,INDEX(COUNTIF($E$1:$E30,$H$2:$H$100)+(COUNTIF($H$2:$H$100,$H$2:$H$100)<>1),0,0),0)),TRUE,""),"")} -> roles (student) | F31: {=IFERROR(_xlfn.IFS($F$1=$Q$1,_xlfn.XLOOKUP($E31,$P$2:$P$100,Q$2:Q$100)&"",$F$1=$S$1,_xlfn.XLOOKUP($E31,$R$2:$R$100,$S$2:$S$100)&"",$F$1=$Y$1,_xlfn.XLOOKUP($E31,$X$2:$X$100,$Y$2:$Y$100)&"",$F$1=$U$1,_xlfn.XLOOKUP($E31,$T$2:$T$100,$U$2:$U$100)&"",$F$1=$W$1,_xlfn.XLOOKUP($E31,$V$2:$V$100,$W$2:$W$100)&"",$F$1=$AA$1,_xlfn.XLOOKUP($E31,$Z$2:$Z$100,$AA$2:$AA$100)&"",TRUE, ""),"")} -> http://purl.demodata7.org/vocab/lis/v2/institution/person#Student | G31: {=IFERROR(IF($F31<>"",_xlfn.IFS($F$1="LM7 31 ClPRODUCT4 ms","LM7",$F$1="LMS1 31 ClPRODUCT4 ms","CV",$F$1="LMS2 31 ClPRODUCT4 ms","CL",$F$1="LMS5 31 ClPRODUCT4 ms","JZ",$F$1="LMS8 31 ClPRODUCT4 ms","DL",$F$1="LMS6 31 ClPRODUCT4 ms","MD",TRUE, ""),IF(AND($E$1="GENINTEGRATION 22 Attributes",$E31<>""),"22","")),"")} -> CV | H31: role_scope_mentor | I31: https://purldemodata7.org/spec/GENINTEGRATION/clPRODUCT4 m/role_scope_mentor | J31: Yes | K31: Yes | L31: Yes | M31: Yes | N31: Yes | O31: Yes | P31: =IF(AND($H31<>"",Q31<>""),$H31,"") -> role_scope_mentor | Q31: =IF($J31="yes",$I31,"") -> https://purldemodata7.org/spec/GENINTEGRATION/clPRODUCT4 m/role_scope_mentor | R31: =IF(AND($H31<>"",S31<>""),$H31,"") -> role_scope_mentor | S31: =IF($K31="yes",$I31,"") -> https://purldemodata7.org/spec/GENINTEGRATION/clPRODUCT4 m/role_scope_mentor | T31: =IF(AND($H31<>"",U31<>""),$H31,"") -> role_scope_mentor | U31: =IF($L31="yes",$I31,"") -> https://purldemodata7.org/spec/GENINTEGRATION/clPRODUCT4 m/role_scope_mentor | V31: =IF(AND($H31<>"",W31<>""),$H31,"") -> role_scope_mentor | W31: =IF($M31="yes",$I31,"") -> https://purldemodata7.org/spec/GENINTEGRATION/clPRODUCT4 m/role_scope_mentor | X31: =IF(AND($H31<>"",Y31<>""),$H31,"") -> role_scope_mentor | Y31: =IF($N31="yes",$I31,"") -> https://purldemodata7.org/spec/GENINTEGRATION/clPRODUCT4 m/role_scope_mentor | Z31: =IF(AND($H31<>"",AA31<>""),$H31,"") -> role_scope_mentor | AA31: =IF($L31="yes",$I31,"") -> https://purldemodata7.org/spec/GENINTEGRATION/clPRODUCT4 m/role_scope_mentor
E32: {=IFERROR(_xlfn.IFS($E$1="GENINTEGRATION 22 Parameters",(_xlfn.IFS($F$1=$Q$1,INDEX($P$2:$P$100,MATCH(0,INDEX(COUNTIF($E$1:$E31,$P$2:$P$100)+(COUNTIF($P$2:$P$100,$P$2:$P$100)<>1),0,0),0)),$F$1=$S$1,INDEX($R$2:$R$100,MATCH(0,INDEX(COUNTIF($E$1:$E31,$R$2:$R$100)+(COUNTIF($R$2:$R$100,$R$2:$R$100)<>1),0,0),0)),$F$1=$U$1,INDEX($T$2:$T$100,MATCH(0,INDEX(COUNTIF($E$1:$E31,$T$2:$T$100)+(COUNTIF($T$2:$T$100,$T$2:$T$100)<>1),0,0),0)),$F$1=$W$1,INDEX($V$2:$V$100,MATCH(0,INDEX(COUNTIF($E$1:$E31,$V$2:$V$100)+(COUNTIF($V$2:$V$100,$V$2:$V$100)<>1),0,0),0)),$F$1=$Y$1,INDEX($X$2:$X$100,MATCH(0,INDEX(COUNTIF($E$1:$E31,$X$2:$X$100)+(COUNTIF($X$2:$X$100,$X$2:$X$100)<>1),0,0),0)),$F$1=$AA$1,INDEX($Z$2:$Z$100,MATCH(0,INDEX(COUNTIF($E$1:$E31,$Z$2:$Z$100)+(COUNTIF($Z$2:$Z$100,$Z$2:$Z$100)<>1),0,0),0)),TRUE,"")),$E$1="GENINTEGRATION 22 Attributes",INDEX($H$2:$H$100,MATCH(0,INDEX(COUNTIF($E$1:$E31,$H$2:$H$100)+(COUNTIF($H$2:$H$100,$H$2:$H$100)<>1),0,0),0)),TRUE,""),"")} -> roles {1-First} | F32: {=IFERROR(_xlfn.IFS($F$1=$Q$1,_xlfn.XLOOKUP($E32,$P$2:$P$100,Q$2:Q$100)&"",$F$1=$S$1,_xlfn.XLOOKUP($E32,$R$2:$R$100,$S$2:$S$100)&"",$F$1=$Y$1,_xlfn.XLOOKUP($E32,$X$2:$X$100,$Y$2:$Y$100)&"",$F$1=$U$1,_xlfn.XLOOKUP($E32,$T$2:$T$100,$U$2:$U$100)&"",$F$1=$W$1,_xlfn.XLOOKUP($E32,$V$2:$V$100,$W$2:$W$100)&"",$F$1=$AA$1,_xlfn.XLOOKUP($E32,$Z$2:$Z$100,$AA$2:$AA$100)&"",TRUE, ""),"")} -> https://purl.demodata7.org/spec/GENINTEGRATION/clPRODUCT4 m/roles|0 | G32: {=IFERROR(IF($F32<>"",_xlfn.IFS($F$1="LM7 31 ClPRODUCT4 ms","LM7",$F$1="LMS1 31 ClPRODUCT4 ms","CV",$F$1="LMS2 31 ClPRODUCT4 ms","CL",$F$1="LMS5 31 ClPRODUCT4 ms","JZ",$F$1="LMS8 31 ClPRODUCT4 ms","DL",$F$1="LMS6 31 ClPRODUCT4 ms","MD",TRUE, ""),IF(AND($E$1="GENINTEGRATION 22 Attributes",$E32<>""),"22","")),"")} -> CV | H32: roles (member) | I32: http://purl.demodata7.org/vocab/lis/v2/institution/membership#Member | J32: No | K32: No | L32: Yes | M32: No | N32: Yes | O32: Yes | P32: =IF(AND($H32<>"",Q32<>""),$H32,"") | Q32: =IF($J32="yes",$I32,"") | R32: =IF(AND($H32<>"",S32<>""),$H32,"") | S32: =IF($K32="yes",$I32,"") | T32: =IF(AND($H32<>"",U32<>""),$H32,"") -> roles (member) | U32: =IF($L32="yes",$I32,"") -> http://purl.demodata7.org/vocab/lis/v2/institution/membership#Member | V32: =IF(AND($H32<>"",W32<>""),$H32,"") | W32: =IF($M32="yes",$I32,"") | X32: =IF(AND($H32<>"",Y32<>""),$H32,"") -> roles (member) | Y32: =IF($N32="yes",$I32,"") -> http://purl.demodata7.org/vocab/lis/v2/institution/membership#Member | Z32: =IF(AND($H32<>"",AA32<>""),$H32,"") -> roles (member) | AA32: =IF($L32="yes",$I32,"") -> http://purl.demodata7.org/vocab/lis/v2/institution/membership#Member
E33: {=IFERROR(_xlfn.IFS($E$1="GENINTEGRATION 22 Parameters",(_xlfn.IFS($F$1=$Q$1,INDEX($P$2:$P$100,MATCH(0,INDEX(COUNTIF($E$1:$E32,$P$2:$P$100)+(COUNTIF($P$2:$P$100,$P$2:$P$100)<>1),0,0),0)),$F$1=$S$1,INDEX($R$2:$R$100,MATCH(0,INDEX(COUNTIF($E$1:$E32,$R$2:$R$100)+(COUNTIF($R$2:$R$100,$R$2:$R$100)<>1),0,0),0)),$F$1=$U$1,INDEX($T$2:$T$100,MATCH(0,INDEX(COUNTIF($E$1:$E32,$T$2:$T$100)+(COUNTIF($T$2:$T$100,$T$2:$T$100)<>1),0,0),0)),$F$1=$W$1,INDEX($V$2:$V$100,MATCH(0,INDEX(COUNTIF($E$1:$E32,$V$2:$V$100)+(COUNTIF($V$2:$V$100,$V$2:$V$100)<>1),0,0),0)),$F$1=$Y$1,INDEX($X$2:$X$100,MATCH(0,INDEX(COUNTIF($E$1:$E32,$X$2:$X$100)+(COUNTIF($X$2:$X$100,$X$2:$X$100)<>1),0,0),0)),$F$1=$AA$1,INDEX($Z$2:$Z$100,MATCH(0,INDEX(COUNTIF($E$1:$E32,$Z$2:$Z$100)+(COUNTIF($Z$2:$Z$100,$Z$2:$Z$100)<>1),0,0),0)),TRUE,"")),$E$1="GENINTEGRATION 22 Attributes",INDEX($H$2:$H$100,MATCH(0,INDEX(COUNTIF($E$1:$E32,$H$2:$H$100)+(COUNTIF($H$2:$H$100,$H$2:$H$100)<>1),0,0),0)),TRUE,""),"")} -> roles {2-Second} | F33: {=IFERROR(_xlfn.IFS($F$1=$Q$1,_xlfn.XLOOKUP($E33,$P$2:$P$100,Q$2:Q$100)&"",$F$1=$S$1,_xlfn.XLOOKUP($E33,$R$2:$R$100,$S$2:$S$100)&"",$F$1=$Y$1,_xlfn.XLOOKUP($E33,$X$2:$X$100,$Y$2:$Y$100)&"",$F$1=$U$1,_xlfn.XLOOKUP($E33,$T$2:$T$100,$U$2:$U$100)&"",$F$1=$W$1,_xlfn.XLOOKUP($E33,$V$2:$V$100,$W$2:$W$100)&"",$F$1=$AA$1,_xlfn.XLOOKUP($E33,$Z$2:$Z$100,$AA$2:$AA$100)&"",TRUE, ""),"")} -> https://purl.demodata7.org/spec/GENINTEGRATION/clPRODUCT4 m/roles|1 | G33: {=IFERROR(IF($F33<>"",_xlfn.IFS($F$1="LM7 31 ClPRODUCT4 ms","LM7",$F$1="LMS1 31 ClPRODUCT4 ms","CV",$F$1="LMS2 31 ClPRODUCT4 ms","CL",$F$1="LMS5 31 ClPRODUCT4 ms","JZ",$F$1="LMS8 31 ClPRODUCT4 ms","DL",$F$1="LMS6 31 ClPRODUCT4 ms","MD",TRUE, ""),IF(AND($E$1="GENINTEGRATION 22 Attributes",$E33<>""),"22","")),"")} -> CV | H33: roles (student) | I33: http://purl.demodata7.org/vocab/lis/v2/institution/person#Student | J33: No | K33: Yes | L33: Yes | M33: No | N33: No | O33: Yes | P33: =IF(AND($H33<>"",Q33<>""),$H33,"") | Q33: =IF($J33="yes",$I33,"") | R33: =IF(AND($H33<>"",S33<>""),$H33,"") -> roles (student) | S33: =IF($K33="yes",$I33,"") -> http://purl.demodata7.org/vocab/lis/v2/institution/person#Student | T33: =IF(AND($H33<>"",U33<>""),$H33,"") -> roles (student) | U33: =IF($L33="yes",$I33,"") -> http://purl.demodata7.org/vocab/lis/v2/institution/person#Student | V33: =IF(AND($H33<>"",W33<>""),$H33,"") | W33: =IF($M33="yes",$I33,"") | X33: =IF(AND($H33<>"",Y33<>""),$H33,"") | Y33: =IF($N33="yes",$I33,"") | Z33: =IF(AND($H33<>"",AA33<>""),$H33,"") -> roles (student) | AA33: =IF($L33="yes",$I33,"") -> http://purl.demodata7.org/vocab/lis/v2/institution/person#Student
E34: {=IFERROR(_xlfn.IFS($E$1="GENINTEGRATION 22 Parameters",(_xlfn.IFS($F$1=$Q$1,INDEX($P$2:$P$100,MATCH(0,INDEX(COUNTIF($E$1:$E33,$P$2:$P$100)+(COUNTIF($P$2:$P$100,$P$2:$P$100)<>1),0,0),0)),$F$1=$S$1,INDEX($R$2:$R$100,MATCH(0,INDEX(COUNTIF($E$1:$E33,$R$2:$R$100)+(COUNTIF($R$2:$R$100,$R$2:$R$100)<>1),0,0),0)),$F$1=$U$1,INDEX($T$2:$T$100,MATCH(0,INDEX(COUNTIF($E$1:$E33,$T$2:$T$100)+(COUNTIF($T$2:$T$100,$T$2:$T$100)<>1),0,0),0)),$F$1=$W$1,INDEX($V$2:$V$100,MATCH(0,INDEX(COUNTIF($E$1:$E33,$V$2:$V$100)+(COUNTIF($V$2:$V$100,$V$2:$V$100)<>1),0,0),0)),$F$1=$Y$1,INDEX($X$2:$X$100,MATCH(0,INDEX(COUNTIF($E$1:$E33,$X$2:$X$100)+(COUNTIF($X$2:$X$100,$X$2:$X$100)<>1),0,0),0)),$F$1=$AA$1,INDEX($Z$2:$Z$100,MATCH(0,INDEX(COUNTIF($E$1:$E33,$Z$2:$Z$100)+(COUNTIF($Z$2:$Z$100,$Z$2:$Z$100)<>1),0,0),0)),TRUE,"")),$E$1="GENINTEGRATION 22 Attributes",INDEX($H$2:$H$100,MATCH(0,INDEX(COUNTIF($E$1:$E33,$H$2:$H$100)+(COUNTIF($H$2:$H$100,$H$2:$H$100)<>1),0,0),0)),TRUE,""),"")} -> roles {3-Third} | F34: {=IFERROR(_xlfn.IFS($F$1=$Q$1,_xlfn.XLOOKUP($E34,$P$2:$P$100,Q$2:Q$100)&"",$F$1=$S$1,_xlfn.XLOOKUP($E34,$R$2:$R$100,$S$2:$S$100)&"",$F$1=$Y$1,_xlfn.XLOOKUP($E34,$X$2:$X$100,$Y$2:$Y$100)&"",$F$1=$U$1,_xlfn.XLOOKUP($E34,$T$2:$T$100,$U$2:$U$100)&"",$F$1=$W$1,_xlfn.XLOOKUP($E34,$V$2:$V$100,$W$2:$W$100)&"",$F$1=$AA$1,_xlfn.XLOOKUP($E34,$Z$2:$Z$100,$AA$2:$AA$100)&"",TRUE, ""),"")} -> https://purl.demodata7.org/spec/GENINTEGRATION/clPRODUCT4 m/roles|2 | G34: {=IFERROR(IF($F34<>"",_xlfn.IFS($F$1="LM7 31 ClPRODUCT4 ms","LM7",$F$1="LMS1 31 ClPRODUCT4 ms","CV",$F$1="LMS2 31 ClPRODUCT4 ms","CL",$F$1="LMS5 31 ClPRODUCT4 ms","JZ",$F$1="LMS8 31 ClPRODUCT4 ms","DL",$F$1="LMS6 31 ClPRODUCT4 ms","MD",TRUE, ""),IF(AND($E$1="GENINTEGRATION 22 Attributes",$E34<>""),"22","")),"")} -> CV | H34: roles {1-First} | I34: https://purl.demodata7.org/spec/GENINTEGRATION/clPRODUCT4 m/roles|0 | J34: No | K34: Yes | L34: Yes | M34: No | N34: Yes | O34: Yes | P34: =IF(AND($H34<>"",Q34<>""),$H34,"") | Q34: =IF($J34="yes",$I34,"") | R34: =IF(AND($H34<>"",S34<>""),$H34,"") -> roles {1-First} | S34: =IF($K34="yes",$I34,"") -> https://purl.demodata7.org/spec/GENINTEGRATION/clPRODUCT4 m/roles|0 | T34: =IF(AND($H34<>"",U34<>""),$H34,"") -> roles {1-First} | U34: =IF($L34="yes",$I34,"") -> https://purl.demodata7.org/spec/GENINTEGRATION/clPRODUCT4 m/roles|0 | V34: =IF(AND($H34<>"",W34<>""),$H34,"") | W34: =IF($M34="yes",$I34,"") | X34: =IF(AND($H34<>"",Y34<>""),$H34,"") -> roles {1-First} | Y34: =IF($N34="yes",$I34,"") -> https://purl.demodata7.org/spec/GENINTEGRATION/clPRODUCT4 m/roles|0 | Z34: =IF(AND($H34<>"",AA34<>""),$H34,"") -> roles {1-First} | AA34: =IF($L34="yes",$I34,"") -> https://purl.demodata7.org/spec/GENINTEGRATION/clPRODUCT4 m/roles|0
E35: {=IFERROR(_xlfn.IFS($E$1="GENINTEGRATION 22 Parameters",(_xlfn.IFS($F$1=$Q$1,INDEX($P$2:$P$100,MATCH(0,INDEX(COUNTIF($E$1:$E34,$P$2:$P$100)+(COUNTIF($P$2:$P$100,$P$2:$P$100)<>1),0,0),0)),$F$1=$S$1,INDEX($R$2:$R$100,MATCH(0,INDEX(COUNTIF($E$1:$E34,$R$2:$R$100)+(COUNTIF($R$2:$R$100,$R$2:$R$100)<>1),0,0),0)),$F$1=$U$1,INDEX($T$2:$T$100,MATCH(0,INDEX(COUNTIF($E$1:$E34,$T$2:$T$100)+(COUNTIF($T$2:$T$100,$T$2:$T$100)<>1),0,0),0)),$F$1=$W$1,INDEX($V$2:$V$100,MATCH(0,INDEX(COUNTIF($E$1:$E34,$V$2:$V$100)+(COUNTIF($V$2:$V$100,$V$2:$V$100)<>1),0,0),0)),$F$1=$Y$1,INDEX($X$2:$X$100,MATCH(0,INDEX(COUNTIF($E$1:$E34,$X$2:$X$100)+(COUNTIF($X$2:$X$100,$X$2:$X$100)<>1),0,0),0)),$F$1=$AA$1,INDEX($Z$2:$Z$100,MATCH(0,INDEX(COUNTIF($E$1:$E34,$Z$2:$Z$100)+(COUNTIF($Z$2:$Z$100,$Z$2:$Z$100)<>1),0,0),0)),TRUE,"")),$E$1="GENINTEGRATION 22 Attributes",INDEX($H$2:$H$100,MATCH(0,INDEX(COUNTIF($E$1:$E34,$H$2:$H$100)+(COUNTIF($H$2:$H$100,$H$2:$H$100)<>1),0,0),0)),TRUE,""),"")} -> roles {4-Fourth} | F35: {=IFERROR(_xlfn.IFS($F$1=$Q$1,_xlfn.XLOOKUP($E35,$P$2:$P$100,Q$2:Q$100)&"",$F$1=$S$1,_xlfn.XLOOKUP($E35,$R$2:$R$100,$S$2:$S$100)&"",$F$1=$Y$1,_xlfn.XLOOKUP($E35,$X$2:$X$100,$Y$2:$Y$100)&"",$F$1=$U$1,_xlfn.XLOOKUP($E35,$T$2:$T$100,$U$2:$U$100)&"",$F$1=$W$1,_xlfn.XLOOKUP($E35,$V$2:$V$100,$W$2:$W$100)&"",$F$1=$AA$1,_xlfn.XLOOKUP($E35,$Z$2:$Z$100,$AA$2:$AA$100)&"",TRUE, ""),"")} -> https://purl.demodata7.org/spec/GENINTEGRATION/clPRODUCT4 m/roles|3 | G35: {=IFERROR(IF($F35<>"",_xlfn.IFS($F$1="LM7 31 ClPRODUCT4 ms","LM7",$F$1="LMS1 31 ClPRODUCT4 ms","CV",$F$1="LMS2 31 ClPRODUCT4 ms","CL",$F$1="LMS5 31 ClPRODUCT4 ms","JZ",$F$1="LMS8 31 ClPRODUCT4 ms","DL",$F$1="LMS6 31 ClPRODUCT4 ms","MD",TRUE, ""),IF(AND($E$1="GENINTEGRATION 22 Attributes",$E35<>""),"22","")),"")} -> CV | H35: roles {2-Second} | I35: https://purl.demodata7.org/spec/GENINTEGRATION/clPRODUCT4 m/roles|1 | J35: No | K35: Yes | L35: Yes | M35: No | N35: Yes | O35: Yes | P35: =IF(AND($H35<>"",Q35<>""),$H35,"") | Q35: =IF($J35="yes",$I35,"") | R35: =IF(AND($H35<>"",S35<>""),$H35,"") -> roles {2-Second} | S35: =IF($K35="yes",$I35,"") -> https://purl.demodata7.org/spec/GENINTEGRATION/clPRODUCT4 m/roles|1 | T35: =IF(AND($H35<>"",U35<>""),$H35,"") -> roles {2-Second} | U35: =IF($L35="yes",$I35,"") -> https://purl.demodata7.org/spec/GENINTEGRATION/clPRODUCT4 m/roles|1 | V35: =IF(AND($H35<>"",W35<>""),$H35,"") | W35: =IF($M35="yes",$I35,"") | X35: =IF(AND($H35<>"",Y35<>""),$H35,"") -> roles {2-Second} | Y35: =IF($N35="yes",$I35,"") -> https://purl.demodata7.org/spec/GENINTEGRATION/clPRODUCT4 m/roles|1 | Z35: =IF(AND($H35<>"",AA35<>""),$H35,"") -> roles {2-Second} | AA35: =IF($L35="yes",$I35,"") -> https://purl.demodata7.org/spec/GENINTEGRATION/clPRODUCT4 m/roles|1
E36: {=IFERROR(_xlfn.IFS($E$1="GENINTEGRATION 22 Parameters",(_xlfn.IFS($F$1=$Q$1,INDEX($P$2:$P$100,MATCH(0,INDEX(COUNTIF($E$1:$E35,$P$2:$P$100)+(COUNTIF($P$2:$P$100,$P$2:$P$100)<>1),0,0),0)),$F$1=$S$1,INDEX($R$2:$R$100,MATCH(0,INDEX(COUNTIF($E$1:$E35,$R$2:$R$100)+(COUNTIF($R$2:$R$100,$R$2:$R$100)<>1),0,0),0)),$F$1=$U$1,INDEX($T$2:$T$100,MATCH(0,INDEX(COUNTIF($E$1:$E35,$T$2:$T$100)+(COUNTIF($T$2:$T$100,$T$2:$T$100)<>1),0,0),0)),$F$1=$W$1,INDEX($V$2:$V$100,MATCH(0,INDEX(COUNTIF($E$1:$E35,$V$2:$V$100)+(COUNTIF($V$2:$V$100,$V$2:$V$100)<>1),0,0),0)),$F$1=$Y$1,INDEX($X$2:$X$100,MATCH(0,INDEX(COUNTIF($E$1:$E35,$X$2:$X$100)+(COUNTIF($X$2:$X$100,$X$2:$X$100)<>1),0,0),0)),$F$1=$AA$1,INDEX($Z$2:$Z$100,MATCH(0,INDEX(COUNTIF($E$1:$E35,$Z$2:$Z$100)+(COUNTIF($Z$2:$Z$100,$Z$2:$Z$100)<>1),0,0),0)),TRUE,"")),$E$1="GENINTEGRATION 22 Attributes",INDEX($H$2:$H$100,MATCH(0,INDEX(COUNTIF($E$1:$E35,$H$2:$H$100)+(COUNTIF($H$2:$H$100,$H$2:$H$100)<>1),0,0),0)),TRUE,""),"")} -> tool_consumer_info_product_family | F36: {=IFERROR(_xlfn.IFS($F$1=$Q$1,_xlfn.XLOOKUP($E36,$P$2:$P$100,Q$2:Q$100)&"",$F$1=$S$1,_xlfn.XLOOKUP($E36,$R$2:$R$100,$S$2:$S$100)&"",$F$1=$Y$1,_xlfn.XLOOKUP($E36,$X$2:$X$100,$Y$2:$Y$100)&"",$F$1=$U$1,_xlfn.XLOOKUP($E36,$T$2:$T$100,$U$2:$U$100)&"",$F$1=$W$1,_xlfn.XLOOKUP($E36,$V$2:$V$100,$W$2:$W$100)&"",$F$1=$AA$1,_xlfn.XLOOKUP($E36,$Z$2:$Z$100,$AA$2:$AA$100)&"",TRUE, ""),"")} -> https://purl.demodata7.org/spec/GENINTEGRATION/clPRODUCT4 m/tool_platform|product_family_code | G36: {=IFERROR(IF($F36<>"",_xlfn.IFS($F$1="LM7 31 ClPRODUCT4 ms","LM7",$F$1="LMS1 31 ClPRODUCT4 ms","CV",$F$1="LMS2 31 ClPRODUCT4 ms","CL",$F$1="LMS5 31 ClPRODUCT4 ms","JZ",$F$1="LMS8 31 ClPRODUCT4 ms","DL",$F$1="LMS6 31 ClPRODUCT4 ms","MD",TRUE, ""),IF(AND($E$1="GENINTEGRATION 22 Attributes",$E36<>""),"22","")),"")} -> CV | H36: roles {3-Third} | I36: https://purl.demodata7.org/spec/GENINTEGRATION/clPRODUCT4 m/roles|2 | J36: No | K36: Yes | L36: Yes | M36: No | N36: Yes | O36: Yes | P36: =IF(AND($H36<>"",Q36<>""),$H36,"") | Q36: =IF($J36="yes",$I36,"") | R36: =IF(AND($H36<>"",S36<>""),$H36,"") -> roles {3-Third} | S36: =IF($K36="yes",$I36,"") -> https://purl.demodata7.org/spec/GENINTEGRATION/clPRODUCT4 m/roles|2 | T36: =IF(AND($H36<>"",U36<>""),$H36,"") -> roles {3-Third} | U36: =IF($L36="yes",$I36,"") -> https://purl.demodata7.org/spec/GENINTEGRATION/clPRODUCT4 m/roles|2 | V36: =IF(AND($H36<>"",W36<>""),$H36,"") | W36: =IF($M36="yes",$I36,"") | X36: =IF(AND($H36<>"",Y36<>""),$H36,"") -> roles {3-Third} | Y36: =IF($N36="yes",$I36,"") -> https://purl.demodata7.org/spec/GENINTEGRATION/clPRODUCT4 m/roles|2 | Z36: =IF(AND($H36<>"",AA36<>""),$H36,"") -> roles {3-Third} | AA36: =IF($L36="yes",$I36,"") -> https://purl.demodata7.org/spec/GENINTEGRATION/clPRODUCT4 m/roles|2
E37: {=IFERROR(_xlfn.IFS($E$1="GENINTEGRATION 22 Parameters",(_xlfn.IFS($F$1=$Q$1,INDEX($P$2:$P$100,MATCH(0,INDEX(COUNTIF($E$1:$E36,$P$2:$P$100)+(COUNTIF($P$2:$P$100,$P$2:$P$100)<>1),0,0),0)),$F$1=$S$1,INDEX($R$2:$R$100,MATCH(0,INDEX(COUNTIF($E$1:$E36,$R$2:$R$100)+(COUNTIF($R$2:$R$100,$R$2:$R$100)<>1),0,0),0)),$F$1=$U$1,INDEX($T$2:$T$100,MATCH(0,INDEX(COUNTIF($E$1:$E36,$T$2:$T$100)+(COUNTIF($T$2:$T$100,$T$2:$T$100)<>1),0,0),0)),$F$1=$W$1,INDEX($V$2:$V$100,MATCH(0,INDEX(COUNTIF($E$1:$E36,$V$2:$V$100)+(COUNTIF($V$2:$V$100,$V$2:$V$100)<>1),0,0),0)),$F$1=$Y$1,INDEX($X$2:$X$100,MATCH(0,INDEX(COUNTIF($E$1:$E36,$X$2:$X$100)+(COUNTIF($X$2:$X$100,$X$2:$X$100)<>1),0,0),0)),$F$1=$AA$1,INDEX($Z$2:$Z$100,MATCH(0,INDEX(COUNTIF($E$1:$E36,$Z$2:$Z$100)+(COUNTIF($Z$2:$Z$100,$Z$2:$Z$100)<>1),0,0),0)),TRUE,"")),$E$1="GENINTEGRATION 22 Attributes",INDEX($H$2:$H$100,MATCH(0,INDEX(COUNTIF($E$1:$E36,$H$2:$H$100)+(COUNTIF($H$2:$H$100,$H$2:$H$100)<>1),0,0),0)),TRUE,""),"")} -> tool_consumer_info_version | F37: {=IFERROR(_xlfn.IFS($F$1=$Q$1,_xlfn.XLOOKUP($E37,$P$2:$P$100,Q$2:Q$100)&"",$F$1=$S$1,_xlfn.XLOOKUP($E37,$R$2:$R$100,$S$2:$S$100)&"",$F$1=$Y$1,_xlfn.XLOOKUP($E37,$X$2:$X$100,$Y$2:$Y$100)&"",$F$1=$U$1,_xlfn.XLOOKUP($E37,$T$2:$T$100,$U$2:$U$100)&"",$F$1=$W$1,_xlfn.XLOOKUP($E37,$V$2:$V$100,$W$2:$W$100)&"",$F$1=$AA$1,_xlfn.XLOOKUP($E37,$Z$2:$Z$100,$AA$2:$AA$100)&"",TRUE, ""),"")} -> https://purl.demodata7.org/spec/GENINTEGRATION/clPRODUCT4 m/tool_platform|version | G37: {=IFERROR(IF($F37<>"",_xlfn.IFS($F$1="LM7 31 ClPRODUCT4 ms","LM7",$F$1="LMS1 31 ClPRODUCT4 ms","CV",$F$1="LMS2 31 ClPRODUCT4 ms","CL",$F$1="LMS5 31 ClPRODUCT4 ms","JZ",$F$1="LMS8 31 ClPRODUCT4 ms","DL",$F$1="LMS6 31 ClPRODUCT4 ms","MD",TRUE, ""),IF(AND($E$1="GENINTEGRATION 22 Attributes",$E37<>""),"22","")),"")} -> CV | H37: roles {4-Fourth} | I37: https://purl.demodata7.org/spec/GENINTEGRATION/clPRODUCT4 m/roles|3 | J37: No | K37: Yes | L37: Yes | M37: No | N37: Yes | O37: Yes | P37: =IF(AND($H37<>"",Q37<>""),$H37,"") | Q37: =IF($J37="yes",$I37,"") | R37: =IF(AND($H37<>"",S37<>""),$H37,"") -> roles {4-Fourth} | S37: =IF($K37="yes",$I37,"") -> https://purl.demodata7.org/spec/GENINTEGRATION/clPRODUCT4 m/roles|3 | T37: =IF(AND($H37<>"",U37<>""),$H37,"") -> roles {4-Fourth} | U37: =IF($L37="yes",$I37,"") -> https://purl.demodata7.org/spec/GENINTEGRATION/clPRODUCT4 m/roles|3 | V37: =IF(AND($H37<>"",W37<>""),$H37,"") | W37: =IF($M37="yes",$I37,"") | X37: =IF(AND($H37<>"",Y37<>""),$H37,"") -> roles {4-Fourth} | Y37: =IF($N37="yes",$I37,"") -> https://purl.demodata7.org/spec/GENINTEGRATION/clPRODUCT4 m/roles|3 | Z37: =IF(AND($H37<>"",AA37<>""),$H37,"") -> roles {4-Fourth} | AA37: =IF($L37="yes",$I37,"") -> https://purl.demodata7.org/spec/GENINTEGRATION/clPRODUCT4 m/roles|3
E38: {=IFERROR(_xlfn.IFS($E$1="GENINTEGRATION 22 Parameters",(_xlfn.IFS($F$1=$Q$1,INDEX($P$2:$P$100,MATCH(0,INDEX(COUNTIF($E$1:$E37,$P$2:$P$100)+(COUNTIF($P$2:$P$100,$P$2:$P$100)<>1),0,0),0)),$F$1=$S$1,INDEX($R$2:$R$100,MATCH(0,INDEX(COUNTIF($E$1:$E37,$R$2:$R$100)+(COUNTIF($R$2:$R$100,$R$2:$R$100)<>1),0,0),0)),$F$1=$U$1,INDEX($T$2:$T$100,MATCH(0,INDEX(COUNTIF($E$1:$E37,$T$2:$T$100)+(COUNTIF($T$2:$T$100,$T$2:$T$100)<>1),0,0),0)),$F$1=$W$1,INDEX($V$2:$V$100,MATCH(0,INDEX(COUNTIF($E$1:$E37,$V$2:$V$100)+(COUNTIF($V$2:$V$100,$V$2:$V$100)<>1),0,0),0)),$F$1=$Y$1,INDEX($X$2:$X$100,MATCH(0,INDEX(COUNTIF($E$1:$E37,$X$2:$X$100)+(COUNTIF($X$2:$X$100,$X$2:$X$100)<>1),0,0),0)),$F$1=$AA$1,INDEX($Z$2:$Z$100,MATCH(0,INDEX(COUNTIF($E$1:$E37,$Z$2:$Z$100)+(COUNTIF($Z$2:$Z$100,$Z$2:$Z$100)<>1),0,0),0)),TRUE,"")),$E$1="GENINTEGRATION 22 Attributes",INDEX($H$2:$H$100,MATCH(0,INDEX(COUNTIF($E$1:$E37,$H$2:$H$100)+(COUNTIF($H$2:$H$100,$H$2:$H$100)<>1),0,0),0)),TRUE,""),"")} -> tool_consumer_instance_contact_PRODCUT4 | F38: {=IFERROR(_xlfn.IFS($F$1=$Q$1,_xlfn.XLOOKUP($E38,$P$2:$P$100,Q$2:Q$100)&"",$F$1=$S$1,_xlfn.XLOOKUP($E38,$R$2:$R$100,$S$2:$S$100)&"",$F$1=$Y$1,_xlfn.XLOOKUP($E38,$X$2:$X$100,$Y$2:$Y$100)&"",$F$1=$U$1,_xlfn.XLOOKUP($E38,$T$2:$T$100,$U$2:$U$100)&"",$F$1=$W$1,_xlfn.XLOOKUP($E38,$V$2:$V$100,$W$2:$W$100)&"",$F$1=$AA$1,_xlfn.XLOOKUP($E38,$Z$2:$Z$100,$AA$2:$AA$100)&"",TRUE, ""),"")} -> https://purl.demodata7.org/spec/GENINTEGRATION/clPRODUCT4 m/tool_platform|PRODCUT4 | G38: {=IFERROR(IF($F38<>"",_xlfn.IFS($F$1="LM7 31 ClPRODUCT4 ms","LM7",$F$1="LMS1 31 ClPRODUCT4 ms","CV",$F$1="LMS2 31 ClPRODUCT4 ms","CL",$F$1="LMS5 31 ClPRODUCT4 ms","JZ",$F$1="LMS8 31 ClPRODUCT4 ms","DL",$F$1="LMS6 31 ClPRODUCT4 ms","MD",TRUE, ""),IF(AND($E$1="GENINTEGRATION 22 Attributes",$E38<>""),"22","")),"")} -> CV | H38: tool_consumer_info_product_family | I38: https://purl.demodata7.org/spec/GENINTEGRATION/clPRODUCT4 m/tool_platform|product_family_code | J38: Yes | K38: Yes | L38: Yes | M38: Yes | N38: Yes | O38: Yes | P38: =IF(AND($H38<>"",Q38<>""),$H38,"") -> tool_consumer_info_product_family | Q38: =IF($J38="yes",$I38,"") -> https://purl.demodata7.org/spec/GENINTEGRATION/clPRODUCT4 m/tool_platform|product_family_code | R38: =IF(AND($H38<>"",S38<>""),$H38,"") -> tool_consumer_info_product_family | S38: =IF($K38="yes",$I38,"") -> https://purl.demodata7.org/spec/GENINTEGRATION/clPRODUCT4 m/tool_platform|product_family_code | T38: =IF(AND($H38<>"",U38<>""),$H38,"") -> tool_consumer_info_product_family | U38: =IF($L38="yes",$I38,"") -> https://purl.demodata7.org/spec/GENINTEGRATION/clPRODUCT4 m/tool_platform|product_family_code | V38: =IF(AND($H38<>"",W38<>""),$H38,"") -> tool_consumer_info_product_family | W38: =IF($M38="yes",$I38,"") -> https://purl.demodata7.org/spec/GENINTEGRATION/clPRODUCT4 m/tool_platform|product_family_code | X38: =IF(AND($H38<>"",Y38<>""),$H38,"") -> tool_consumer_info_product_family | Y38: =IF($N38="yes",$I38,"") -> https://purl.demodata7.org/spec/GENINTEGRATION/clPRODUCT4 m/tool_platform|product_family_code | Z38: =IF(AND($H38<>"",AA38<>""),$H38,"") -> tool_consumer_info_product_family | AA38: =IF($L38="yes",$I38,"") -> https://purl.demodata7.org/spec/GENINTEGRATION/clPRODUCT4 m/tool_platform|product_family_code
E39: {=IFERROR(_xlfn.IFS($E$1="GENINTEGRATION 22 Parameters",(_xlfn.IFS($F$1=$Q$1,INDEX($P$2:$P$100,MATCH(0,INDEX(COUNTIF($E$1:$E38,$P$2:$P$100)+(COUNTIF($P$2:$P$100,$P$2:$P$100)<>1),0,0),0)),$F$1=$S$1,INDEX($R$2:$R$100,MATCH(0,INDEX(COUNTIF($E$1:$E38,$R$2:$R$100)+(COUNTIF($R$2:$R$100,$R$2:$R$100)<>1),0,0),0)),$F$1=$U$1,INDEX($T$2:$T$100,MATCH(0,INDEX(COUNTIF($E$1:$E38,$T$2:$T$100)+(COUNTIF($T$2:$T$100,$T$2:$T$100)<>1),0,0),0)),$F$1=$W$1,INDEX($V$2:$V$100,MATCH(0,INDEX(COUNTIF($E$1:$E38,$V$2:$V$100)+(COUNTIF($V$2:$V$100,$V$2:$V$100)<>1),0,0),0)),$F$1=$Y$1,INDEX($X$2:$X$100,MATCH(0,INDEX(COUNTIF($E$1:$E38,$X$2:$X$100)+(COUNTIF($X$2:$X$100,$X$2:$X$100)<>1),0,0),0)),$F$1=$AA$1,INDEX($Z$2:$Z$100,MATCH(0,INDEX(COUNTIF($E$1:$E38,$Z$2:$Z$100)+(COUNTIF($Z$2:$Z$100,$Z$2:$Z$100)<>1),0,0),0)),TRUE,"")),$E$1="GENINTEGRATION 22 Attributes",INDEX($H$2:$H$100,MATCH(0,INDEX(COUNTIF($E$1:$E38,$H$2:$H$100)+(COUNTIF($H$2:$H$100,$H$2:$H$100)<>1),0,0),0)),TRUE,""),"")} -> tool_consumer_instance_description | F39: {=IFERROR(_xlfn.IFS($F$1=$Q$1,_xlfn.XLOOKUP($E39,$P$2:$P$100,Q$2:Q$100)&"",$F$1=$S$1,_xlfn.XLOOKUP($E39,$R$2:$R$100,$S$2:$S$100)&"",$F$1=$Y$1,_xlfn.XLOOKUP($E39,$X$2:$X$100,$Y$2:$Y$100)&"",$F$1=$U$1,_xlfn.XLOOKUP($E39,$T$2:$T$100,$U$2:$U$100)&"",$F$1=$W$1,_xlfn.XLOOKUP($E39,$V$2:$V$100,$W$2:$W$100)&"",$F$1=$AA$1,_xlfn.XLOOKUP($E39,$Z$2:$Z$100,$AA$2:$AA$100)&"",TRUE, ""),"")} -> https://purl.demodata7.org/spec/GENINTEGRATION/clPRODUCT4 m/tool_platform|description | G39: {=IFERROR(IF($F39<>"",_xlfn.IFS($F$1="LM7 31 ClPRODUCT4 ms","LM7",$F$1="LMS1 31 ClPRODUCT4 ms","CV",$F$1="LMS2 31 ClPRODUCT4 ms","CL",$F$1="LMS5 31 ClPRODUCT4 ms","JZ",$F$1="LMS8 31 ClPRODUCT4 ms","DL",$F$1="LMS6 31 ClPRODUCT4 ms","MD",TRUE, ""),IF(AND($E$1="GENINTEGRATION 22 Attributes",$E39<>""),"22","")),"")} -> CV | H39: tool_consumer_info_version | I39: https://purl.demodata7.org/spec/GENINTEGRATION/clPRODUCT4 m/tool_platform|version | J39: Yes | K39: Yes | L39: Yes | M39: Yes | N39: Yes | O39: Yes | P39: =IF(AND($H39<>"",Q39<>""),$H39,"") -> tool_consumer_info_version | Q39: =IF($J39="yes",$I39,"") -> https://purl.demodata7.org/spec/GENINTEGRATION/clPRODUCT4 m/tool_platform|version | R39: =IF(AND($H39<>"",S39<>""),$H39,"") -> tool_consumer_info_version | S39: =IF($K39="yes",$I39,"") -> https://purl.demodata7.org/spec/GENINTEGRATION/clPRODUCT4 m/tool_platform|version | T39: =IF(AND($H39<>"",U39<>""),$H39,"") -> tool_consumer_info_version | U39: =IF($L39="yes",$I39,"") -> https://purl.demodata7.org/spec/GENINTEGRATION/clPRODUCT4 m/tool_platform|version | V39: =IF(AND($H39<>"",W39<>""),$H39,"") -> tool_consumer_info_version | W39: =IF($M39="yes",$I39,"") -> https://purl.demodata7.org/spec/GENINTEGRATION/clPRODUCT4 m/tool_platform|version | X39: =IF(AND($H39<>"",Y39<>""),$H39,"") -> tool_consumer_info_version | Y39: =IF($N39="yes",$I39,"") -> https://purl.demodata7.org/spec/GENINTEGRATION/clPRODUCT4 m/tool_platform|version | Z39: =IF(AND($H39<>"",AA39<>""),$H39,"") -> tool_consumer_info_version | AA39: =IF($L39="yes",$I39,"") -> https://purl.demodata7.org/spec/GENINTEGRATION/clPRODUCT4 m/tool_platform|version
E40: {=IFERROR(_xlfn.IFS($E$1="GENINTEGRATION 22 Parameters",(_xlfn.IFS($F$1=$Q$1,INDEX($P$2:$P$100,MATCH(0,INDEX(COUNTIF($E$1:$E39,$P$2:$P$100)+(COUNTIF($P$2:$P$100,$P$2:$P$100)<>1),0,0),0)),$F$1=$S$1,INDEX($R$2:$R$100,MATCH(0,INDEX(COUNTIF($E$1:$E39,$R$2:$R$100)+(COUNTIF($R$2:$R$100,$R$2:$R$100)<>1),0,0),0)),$F$1=$U$1,INDEX($T$2:$T$100,MATCH(0,INDEX(COUNTIF($E$1:$E39,$T$2:$T$100)+(COUNTIF($T$2:$T$100,$T$2:$T$100)<>1),0,0),0)),$F$1=$W$1,INDEX($V$2:$V$100,MATCH(0,INDEX(COUNTIF($E$1:$E39,$V$2:$V$100)+(COUNTIF($V$2:$V$100,$V$2:$V$100)<>1),0,0),0)),$F$1=$Y$1,INDEX($X$2:$X$100,MATCH(0,INDEX(COUNTIF($E$1:$E39,$X$2:$X$100)+(COUNTIF($X$2:$X$100,$X$2:$X$100)<>1),0,0),0)),$F$1=$AA$1,INDEX($Z$2:$Z$100,MATCH(0,INDEX(COUNTIF($E$1:$E39,$Z$2:$Z$100)+(COUNTIF($Z$2:$Z$100,$Z$2:$Z$100)<>1),0,0),0)),TRUE,"")),$E$1="GENINTEGRATION 22 Attributes",INDEX($H$2:$H$100,MATCH(0,INDEX(COUNTIF($E$1:$E39,$H$2:$H$100)+(COUNTIF($H$2:$H$100,$H$2:$H$100)<>1),0,0),0)),TRUE,""),"")} -> tool_consumer_instance_DemoData727 | F40: {=IFERROR(_xlfn.IFS($F$1=$Q$1,_xlfn.XLOOKUP($E40,$P$2:$P$100,Q$2:Q$100)&"",$F$1=$S$1,_xlfn.XLOOKUP($E40,$R$2:$R$100,$S$2:$S$100)&"",$F$1=$Y$1,_xlfn.XLOOKUP($E40,$X$2:$X$100,$Y$2:$Y$100)&"",$F$1=$U$1,_xlfn.XLOOKUP($E40,$T$2:$T$100,$U$2:$U$100)&"",$F$1=$W$1,_xlfn.XLOOKUP($E40,$V$2:$V$100,$W$2:$W$100)&"",$F$1=$AA$1,_xlfn.XLOOKUP($E40,$Z$2:$Z$100,$AA$2:$AA$100)&"",TRUE, ""),"")} -> https://purl.demodata7.org/spec/GENINTEGRATION/clPRODUCT4 m/tool_platform|DemoData727 | G40: {=IFERROR(IF($F40<>"",_xlfn.IFS($F$1="LM7 31 ClPRODUCT4 ms","LM7",$F$1="LMS1 31 ClPRODUCT4 ms","CV",$F$1="LMS2 31 ClPRODUCT4 ms","CL",$F$1="LMS5 31 ClPRODUCT4 ms","JZ",$F$1="LMS8 31 ClPRODUCT4 ms","DL",$F$1="LMS6 31 ClPRODUCT4 ms","MD",TRUE, ""),IF(AND($E$1="GENINTEGRATION 22 Attributes",$E40<>""),"22","")),"")} -> CV | H40: tool_consumer_instance_contact_PRODCUT4 | I40: https://purl.demodata7.org/spec/GENINTEGRATION/clPRODUCT4 m/tool_platform|PRODCUT4 | J40: Yes | K40: Yes | L40: Yes | M40: Yes | N40: Yes | O40: Yes | P40: =IF(AND($H40<>"",Q40<>""),$H40,"") -> tool_consumer_instance_contact_PRODCUT4 | Q40: =IF($J40="yes",$I40,"") -> https://purl.demodata7.org/spec/GENINTEGRATION/clPRODUCT4 m/tool_platform|PRODCUT4 | R40: =IF(AND($H40<>"",S40<>""),$H40,"") -> tool_consumer_instance_contact_PRODCUT4 | S40: =IF($K40="yes",$I40,"") -> https://purl.demodata7.org/spec/GENINTEGRATION/clPRODUCT4 m/tool_platform|PRODCUT4 | T40: =IF(AND($H40<>"",U40<>""),$H40,"") -> tool_consumer_instance_contact_PRODCUT4 | U40: =IF($L40="yes",$I40,"") -> https://purl.demodata7.org/spec/GENINTEGRATION/clPRODUCT4 m/tool_platform|PRODCUT4 | V40: =IF(AND($H40<>"",W40<>""),$H40,"") -> tool_consumer_instance_contact_PRODCUT4 | W40: =IF($M40="yes",$I40,"") -> https://purl.demodata7.org/spec/GENINTEGRATION/clPRODUCT4 m/tool_platform|PRODCUT4 | X40: =IF(AND($H40<>"",Y40<>""),$H40,"") -> tool_consumer_instance_contact_PRODCUT4 | Y40: =IF($N40="yes",$I40,"") -> https://purl.demodata7.org/spec/GENINTEGRATION/clPRODUCT4 m/tool_platform|PRODCUT4 | Z40: =IF(AND($H40<>"",AA40<>""),$H40,"") -> tool_consumer_instance_contact_PRODCUT4 | AA40: =IF($L40="yes",$I40,"") -> https://purl.demodata7.org/spec/GENINTEGRATION/clPRODUCT4 m/tool_platform|PRODCUT4
... E46: {=IFERROR(_xlfn.IFS($E$1="GENINTEGRATION 22 Parameters",(_xlfn.IFS($F$1=$Q$1,INDEX($P$2:$P$100,MATCH(0,INDEX(COUNTIF($E$1:$E45,$P$2:$P$100)+(COUNTIF($P$2:$P$100,$P$2:$P$100)<>1),0,0),0)),$F$1=$S$1,INDEX($R$2:$R$100,MATCH(0,INDEX(COUNTIF($E$1:$E45,$R$2:$R$100)+(COUNTIF($R$2:$R$100,$R$2:$R$100)<>1),0,0),0)),$F$1=$U$1,INDEX($T$2:$T$100,MATCH(0,INDEX(COUNTIF($E$1:$E45,$T$2:$T$100)+(COUNTIF($T$2:$T$100,$T$2:$T$100)<>1),0,0),0)),$F$1=$W$1,INDEX($V$2:$V$100,MATCH(0,INDEX(COUNTIF($E$1:$E45,$V$2:$V$100)+(COUNTIF($V$2:$V$100,$V$2:$V$100)<>1),0,0),0)),$F$1=$Y$1,INDEX($X$2:$X$100,MATCH(0,INDEX(COUNTIF($E$1:$E45,$X$2:$X$100)+(COUNTIF($X$2:$X$100,$X$2:$X$100)<>1),0,0),0)),$F$1=$AA$1,INDEX($Z$2:$Z$100,MATCH(0,INDEX(COUNTIF($E$1:$E45,$Z$2:$Z$100)+(COUNTIF($Z$2:$Z$100,$Z$2:$Z$100)<>1),0,0),0)),TRUE,"")),$E$1="GENINTEGRATION 22 Attributes",INDEX($H$2:$H$100,MATCH(0,INDEX(COUNTIF($E$1:$E45,$H$2:$H$100)+(COUNTIF($H$2:$H$100,$H$2:$H$100)<>1),0,0),0)),TRUE,""),"")} | F46: {=IFERROR(_xlfn.IFS($F$1=$Q$1,_xlfn.XLOOKUP($E46,$P$2:$P$100,Q$2:Q$100)&"",$F$1=$S$1,_xlfn.XLOOKUP($E46,$R$2:$R$100,$S$2:$S$100)&"",$F$1=$Y$1,_xlfn.XLOOKUP($E46,$X$2:$X$100,$Y$2:$Y$100)&"",$F$1=$U$1,_xlfn.XLOOKUP($E46,$T$2:$T$100,$U$2:$U$100)&"",$F$1=$W$1,_xlfn.XLOOKUP($E46,$V$2:$V$100,$W$2:$W$100)&"",$F$1=$AA$1,_xlfn.XLOOKUP($E46,$Z$2:$Z$100,$AA$2:$AA$100)&"",TRUE, ""),"")} | G46: {=IFERROR(IF($F46<>"",_xlfn.IFS($F$1="LM7 31 ClPRODUCT4 ms","LM7",$F$1="LMS1 31 ClPRODUCT4 ms","CV",$F$1="LMS2 31 ClPRODUCT4 ms","CL",$F$1="LMS5 31 ClPRODUCT4 ms","JZ",$F$1="LMS8 31 ClPRODUCT4 ms","DL",$F$1="LMS6 31 ClPRODUCT4 ms","MD",TRUE, ""),IF(AND($E$1="GENINTEGRATION 22 Attributes",$E46<>""),"22","")),"")} | H46: user_image | I46: picture | J46: Yes | K46: Yes | L46: Yes | M46: Yes | N46: Yes | O46: Yes | P46: =IF(AND($H46<>"",Q46<>""),$H46,"") -> user_image | Q46: =IF($J46="yes",$I46,"") -> picture | R46: =IF(AND($H46<>"",S46<>""),$H46,"") -> user_image | S46: =IF($K46="yes",$I46,"") -> picture | T46: =IF(AND($H46<>"",U46<>""),$H46,"") -> user_image | U46: =IF($L46="yes",$I46,"") -> picture | V46: =IF(AND($H46<>"",W46<>""),$H46,"") -> user_image | W46: =IF($M46="yes",$I46,"") -> picture | X46: =IF(AND($H46<>"",Y46<>""),$H46,"") -> user_image | Y46: =IF($N46="yes",$I46,"") -> picture | Z46: =IF(AND($H46<>"",AA46<>""),$H46,"") -> user_image | AA46: =IF($L46="yes",$I46,"") -> picture
E47: {=IFERROR(_xlfn.IFS($E$1="GENINTEGRATION 22 Parameters",(_xlfn.IFS($F$1=$Q$1,INDEX($P$2:$P$100,MATCH(0,INDEX(COUNTIF($E$1:$E46,$P$2:$P$100)+(COUNTIF($P$2:$P$100,$P$2:$P$100)<>1),0,0),0)),$F$1=$S$1,INDEX($R$2:$R$100,MATCH(0,INDEX(COUNTIF($E$1:$E46,$R$2:$R$100)+(COUNTIF($R$2:$R$100,$R$2:$R$100)<>1),0,0),0)),$F$1=$U$1,INDEX($T$2:$T$100,MATCH(0,INDEX(COUNTIF($E$1:$E46,$T$2:$T$100)+(COUNTIF($T$2:$T$100,$T$2:$T$100)<>1),0,0),0)),$F$1=$W$1,INDEX($V$2:$V$100,MATCH(0,INDEX(COUNTIF($E$1:$E46,$V$2:$V$100)+(COUNTIF($V$2:$V$100,$V$2:$V$100)<>1),0,0),0)),$F$1=$Y$1,INDEX($X$2:$X$100,MATCH(0,INDEX(COUNTIF($E$1:$E46,$X$2:$X$100)+(COUNTIF($X$2:$X$100,$X$2:$X$100)<>1),0,0),0)),$F$1=$AA$1,INDEX($Z$2:$Z$100,MATCH(0,INDEX(COUNTIF($E$1:$E46,$Z$2:$Z$100)+(COUNTIF($Z$2:$Z$100,$Z$2:$Z$100)<>1),0,0),0)),TRUE,"")),$E$1="GENINTEGRATION 22 Attributes",INDEX($H$2:$H$100,MATCH(0,INDEX(COUNTIF($E$1:$E46,$H$2:$H$100)+(COUNTIF($H$2:$H$100,$H$2:$H$100)<>1),0,0),0)),TRUE,""),"")} | F47: {=IFERROR(_xlfn.IFS($F$1=$Q$1,_xlfn.XLOOKUP($E47,$P$2:$P$100,Q$2:Q$100)&"",$F$1=$S$1,_xlfn.XLOOKUP($E47,$R$2:$R$100,$S$2:$S$100)&"",$F$1=$Y$1,_xlfn.XLOOKUP($E47,$X$2:$X$100,$Y$2:$Y$100)&"",$F$1=$U$1,_xlfn.XLOOKUP($E47,$T$2:$T$100,$U$2:$U$100)&"",$F$1=$W$1,_xlfn.XLOOKUP($E47,$V$2:$V$100,$W$2:$W$100)&"",$F$1=$AA$1,_xlfn.XLOOKUP($E47,$Z$2:$Z$100,$AA$2:$AA$100)&"",TRUE, ""),"")} | G47: {=IFERROR(IF($F47<>"",_xlfn.IFS($F$1="LM7 31 ClPRODUCT4 ms","LM7",$F$1="LMS1 31 ClPRODUCT4 ms","CV",$F$1="LMS2 31 ClPRODUCT4 ms","CL",$F$1="LMS5 31 ClPRODUCT4 ms","JZ",$F$1="LMS8 31 ClPRODUCT4 ms","DL",$F$1="LMS6 31 ClPRODUCT4 ms","MD",TRUE, ""),IF(AND($E$1="GENINTEGRATION 22 Attributes",$E47<>""),"22","")),"")} | P47: =IF(AND($H47<>"",Q47<>""),$H47,"") | Q47: =IF($J47="yes",$I47,"") | R47: =IF(AND($H47<>"",S47<>""),$H47,"") | S47: =IF($K47="yes",$I47,"") | T47: =IF(AND($H47<>"",U47<>""),$H47,"") | U47: =IF($L47="yes",$I47,"") | V47: =IF(AND($H47<>"",W47<>""),$H47,"") | W47: =IF($M47="yes",$I47,"") | X47: =IF(AND($H47<>"",Y47<>""),$H47,"") | Y47: =IF($N47="yes",$I47,"") | Z47: =IF(AND($H47<>"",AA47<>""),$H47,"") | AA47: =IF($L47="yes",$I47,"")
E48: {=IFERROR(_xlfn.IFS($E$1="GENINTEGRATION 22 Parameters",(_xlfn.IFS($F$1=$Q$1,INDEX($P$2:$P$100,MATCH(0,INDEX(COUNTIF($E$1:$E47,$P$2:$P$100)+(COUNTIF($P$2:$P$100,$P$2:$P$100)<>1),0,0),0)),$F$1=$S$1,INDEX($R$2:$R$100,MATCH(0,INDEX(COUNTIF($E$1:$E47,$R$2:$R$100)+(COUNTIF($R$2:$R$100,$R$2:$R$100)<>1),0,0),0)),$F$1=$U$1,INDEX($T$2:$T$100,MATCH(0,INDEX(COUNTIF($E$1:$E47,$T$2:$T$100)+(COUNTIF($T$2:$T$100,$T$2:$T$100)<>1),0,0),0)),$F$1=$W$1,INDEX($V$2:$V$100,MATCH(0,INDEX(COUNTIF($E$1:$E47,$V$2:$V$100)+(COUNTIF($V$2:$V$100,$V$2:$V$100)<>1),0,0),0)),$F$1=$Y$1,INDEX($X$2:$X$100,MATCH(0,INDEX(COUNTIF($E$1:$E47,$X$2:$X$100)+(COUNTIF($X$2:$X$100,$X$2:$X$100)<>1),0,0),0)),$F$1=$AA$1,INDEX($Z$2:$Z$100,MATCH(0,INDEX(COUNTIF($E$1:$E47,$Z$2:$Z$100)+(COUNTIF($Z$2:$Z$100,$Z$2:$Z$100)<>1),0,0),0)),TRUE,"")),$E$1="GENINTEGRATION 22 Attributes",INDEX($H$2:$H$100,MATCH(0,INDEX(COUNTIF($E$1:$E47,$H$2:$H$100)+(COUNTIF($H$2:$H$100,$H$2:$H$100)<>1),0,0),0)),TRUE,""),"")} | F48: {=IFERROR(_xlfn.IFS($F$1=$Q$1,_xlfn.XLOOKUP($E48,$P$2:$P$100,Q$2:Q$100)&"",$F$1=$S$1,_xlfn.XLOOKUP($E48,$R$2:$R$100,$S$2:$S$100)&"",$F$1=$Y$1,_xlfn.XLOOKUP($E48,$X$2:$X$100,$Y$2:$Y$100)&"",$F$1=$U$1,_xlfn.XLOOKUP($E48,$T$2:$T$100,$U$2:$U$100)&"",$F$1=$W$1,_xlfn.XLOOKUP($E48,$V$2:$V$100,$W$2:$W$100)&"",$F$1=$AA$1,_xlfn.XLOOKUP($E48,$Z$2:$Z$100,$AA$2:$AA$100)&"",TRUE, ""),"")} | G48: {=IFERROR(IF($F48<>"",_xlfn.IFS($F$1="LM7 31 ClPRODUCT4 ms","LM7",$F$1="LMS1 31 ClPRODUCT4 ms","CV",$F$1="LMS2 31 ClPRODUCT4 ms","CL",$F$1="LMS5 31 ClPRODUCT4 ms","JZ",$F$1="LMS8 31 ClPRODUCT4 ms","DL",$F$1="LMS6 31 ClPRODUCT4 ms","MD",TRUE, ""),IF(AND($E$1="GENINTEGRATION 22 Attributes",$E48<>""),"22","")),"")} | P48: =IF(AND($H48<>"",Q48<>""),$H48,"") | Q48: =IF($J48="yes",$I48,"") | R48: =IF(AND($H48<>"",S48<>""),$H48,"") | S48: =IF($K48="yes",$I48,"") | T48: =IF(AND($H48<>"",U48<>""),$H48,"") | U48: =IF($L48="yes",$I48,"") | V48: =IF(AND($H48<>"",W48<>""),$H48,"") | W48: =IF($M48="yes",$I48,"") | X48: =IF(AND($H48<>"",Y48<>""),$H48,"") | Y48: =IF($N48="yes",$I48,"") | Z48: =IF(AND($H48<>"",AA48<>""),$H48,"") | AA48: =IF($L48="yes",$I48,"")
E49: {=IFERROR(_xlfn.IFS($E$1="GENINTEGRATION 22 Parameters",(_xlfn.IFS($F$1=$Q$1,INDEX($P$2:$P$100,MATCH(0,INDEX(COUNTIF($E$1:$E48,$P$2:$P$100)+(COUNTIF($P$2:$P$100,$P$2:$P$100)<>1),0,0),0)),$F$1=$S$1,INDEX($R$2:$R$100,MATCH(0,INDEX(COUNTIF($E$1:$E48,$R$2:$R$100)+(COUNTIF($R$2:$R$100,$R$2:$R$100)<>1),0,0),0)),$F$1=$U$1,INDEX($T$2:$T$100,MATCH(0,INDEX(COUNTIF($E$1:$E48,$T$2:$T$100)+(COUNTIF($T$2:$T$100,$T$2:$T$100)<>1),0,0),0)),$F$1=$W$1,INDEX($V$2:$V$100,MATCH(0,INDEX(COUNTIF($E$1:$E48,$V$2:$V$100)+(COUNTIF($V$2:$V$100,$V$2:$V$100)<>1),0,0),0)),$F$1=$Y$1,INDEX($X$2:$X$100,MATCH(0,INDEX(COUNTIF($E$1:$E48,$X$2:$X$100)+(COUNTIF($X$2:$X$100,$X$2:$X$100)<>1),0,0),0)),$F$1=$AA$1,INDEX($Z$2:$Z$100,MATCH(0,INDEX(COUNTIF($E$1:$E48,$Z$2:$Z$100)+(COUNTIF($Z$2:$Z$100,$Z$2:$Z$100)<>1),0,0),0)),TRUE,"")),$E$1="GENINTEGRATION 22 Attributes",INDEX($H$2:$H$100,MATCH(0,INDEX(COUNTIF($E$1:$E48,$H$2:$H$100)+(COUNTIF($H$2:$H$100,$H$2:$H$100)<>1),0,0),0)),TRUE,""),"")} | F49: {=IFERROR(_xlfn.IFS($F$1=$Q$1,_xlfn.XLOOKUP($E49,$P$2:$P$100,Q$2:Q$100)&"",$F$1=$S$1,_xlfn.XLOOKUP($E49,$R$2:$R$100,$S$2:$S$100)&"",$F$1=$Y$1,_xlfn.XLOOKUP($E49,$X$2:$X$100,$Y$2:$Y$100)&"",$F$1=$U$1,_xlfn.XLOOKUP($E49,$T$2:$T$100,$U$2:$U$100)&"",$F$1=$W$1,_xlfn.XLOOKUP($E49,$V$2:$V$100,$W$2:$W$100)&"",$F$1=$AA$1,_xlfn.XLOOKUP($E49,$Z$2:$Z$100,$AA$2:$AA$100)&"",TRUE, ""),"")} | G49: {=IFERROR(IF($F49<>"",_xlfn.IFS($F$1="LM7 31 ClPRODUCT4 ms","LM7",$F$1="LMS1 31 ClPRODUCT4 ms","CV",$F$1="LMS2 31 ClPRODUCT4 ms","CL",$F$1="LMS5 31 ClPRODUCT4 ms","JZ",$F$1="LMS8 31 ClPRODUCT4 ms","DL",$F$1="LMS6 31 ClPRODUCT4 ms","MD",TRUE, ""),IF(AND($E$1="GENINTEGRATION 22 Attributes",$E49<>""),"22","")),"")} | P49: =IF(AND($H49<>"",Q49<>""),$H49,"") | Q49: =IF($J49="yes",$I49,"") | R49: =IF(AND($H49<>"",S49<>""),$H49,"") | S49: =IF($K49="yes",$I49,"") | T49: =IF(AND($H49<>"",U49<>""),$H49,"") | U49: =IF($L49="yes",$I49,"") | V49: =IF(AND($H49<>"",W49<>""),$H49,"") | W49: =IF($M49="yes",$I49,"") | X49: =IF(AND($H49<>"",Y49<>""),$H49,"") | Y49: =IF($N49="yes",$I49,"") | Z49: =IF(AND($H49<>"",AA49<>""),$H49,"") | AA49: =IF($L49="yes",$I49,"")
E50: {=IFERROR(_xlfn.IFS($E$1="GENINTEGRATION 22 Parameters",(_xlfn.IFS($F$1=$Q$1,INDEX($P$2:$P$100,MATCH(0,INDEX(COUNTIF($E$1:$E49,$P$2:$P$100)+(COUNTIF($P$2:$P$100,$P$2:$P$100)<>1),0,0),0)),$F$1=$S$1,INDEX($R$2:$R$100,MATCH(0,INDEX(COUNTIF($E$1:$E49,$R$2:$R$100)+(COUNTIF($R$2:$R$100,$R$2:$R$100)<>1),0,0),0)),$F$1=$U$1,INDEX($T$2:$T$100,MATCH(0,INDEX(COUNTIF($E$1:$E49,$T$2:$T$100)+(COUNTIF($T$2:$T$100,$T$2:$T$100)<>1),0,0),0)),$F$1=$W$1,INDEX($V$2:$V$100,MATCH(0,INDEX(COUNTIF($E$1:$E49,$V$2:$V$100)+(COUNTIF($V$2:$V$100,$V$2:$V$100)<>1),0,0),0)),$F$1=$Y$1,INDEX($X$2:$X$100,MATCH(0,INDEX(COUNTIF($E$1:$E49,$X$2:$X$100)+(COUNTIF($X$2:$X$100,$X$2:$X$100)<>1),0,0),0)),$F$1=$AA$1,INDEX($Z$2:$Z$100,MATCH(0,INDEX(COUNTIF($E$1:$E49,$Z$2:$Z$100)+(COUNTIF($Z$2:$Z$100,$Z$2:$Z$100)<>1),0,0),0)),TRUE,"")),$E$1="GENINTEGRATION 22 Attributes",INDEX($H$2:$H$100,MATCH(0,INDEX(COUNTIF($E$1:$E49,$H$2:$H$100)+(COUNTIF($H$2:$H$100,$H$2:$H$100)<>1),0,0),0)),TRUE,""),"")} | F50: {=IFERROR(_xlfn.IFS($F$1=$Q$1,_xlfn.XLOOKUP($E50,$P$2:$P$100,Q$2:Q$100)&"",$F$1=$S$1,_xlfn.XLOOKUP($E50,$R$2:$R$100,$S$2:$S$100)&"",$F$1=$Y$1,_xlfn.XLOOKUP($E50,$X$2:$X$100,$Y$2:$Y$100)&"",$F$1=$U$1,_xlfn.XLOOKUP($E50,$T$2:$T$100,$U$2:$U$100)&"",$F$1=$W$1,_xlfn.XLOOKUP($E50,$V$2:$V$100,$W$2:$W$100)&"",$F$1=$AA$1,_xlfn.XLOOKUP($E50,$Z$2:$Z$100,$AA$2:$AA$100)&"",TRUE, ""),"")} | G50: {=IFERROR(IF($F50<>"",_xlfn.IFS($F$1="LM7 31 ClPRODUCT4 ms","LM7",$F$1="LMS1 31 ClPRODUCT4 ms","CV",$F$1="LMS2 31 ClPRODUCT4 ms","CL",$F$1="LMS5 31 ClPRODUCT4 ms","JZ",$F$1="LMS8 31 ClPRODUCT4 ms","DL",$F$1="LMS6 31 ClPRODUCT4 ms","MD",TRUE, ""),IF(AND($E$1="GENINTEGRATION 22 Attributes",$E50<>""),"22","")),"")} | P50: =IF(AND($H50<>"",Q50<>""),$H50,"") | Q50: =IF($J50="yes",$I50,"") | R50: =IF(AND($H50<>"",S50<>""),$H50,"") | S50: =IF($K50="yes",$I50,"") | T50: =IF(AND($H50<>"",U50<>""),$H50,"") | U50: =IF($L50="yes",$I50,"") | V50: =IF(AND($H50<>"",W50<>""),$H50,"") | W50: =IF($M50="yes",$I50,"") | X50: =IF(AND($H50<>"",Y50<>""),$H50,"") | Y50: =IF($N50="yes",$I50,"") | Z50: =IF(AND($H50<>"",AA50<>""),$H50,"") | AA50: =IF($L50="yes",$I50,"")
E51: {=IFERROR(_xlfn.IFS($E$1="GENINTEGRATION 22 Parameters",(_xlfn.IFS($F$1=$Q$1,INDEX($P$2:$P$100,MATCH(0,INDEX(COUNTIF($E$1:$E50,$P$2:$P$100)+(COUNTIF($P$2:$P$100,$P$2:$P$100)<>1),0,0),0)),$F$1=$S$1,INDEX($R$2:$R$100,MATCH(0,INDEX(COUNTIF($E$1:$E50,$R$2:$R$100)+(COUNTIF($R$2:$R$100,$R$2:$R$100)<>1),0,0),0)),$F$1=$U$1,INDEX($T$2:$T$100,MATCH(0,INDEX(COUNTIF($E$1:$E50,$T$2:$T$100)+(COUNTIF($T$2:$T$100,$T$2:$T$100)<>1),0,0),0)),$F$1=$W$1,INDEX($V$2:$V$100,MATCH(0,INDEX(COUNTIF($E$1:$E50,$V$2:$V$100)+(COUNTIF($V$2:$V$100,$V$2:$V$100)<>1),0,0),0)),$F$1=$Y$1,INDEX($X$2:$X$100,MATCH(0,INDEX(COUNTIF($E$1:$E50,$X$2:$X$100)+(COUNTIF($X$2:$X$100,$X$2:$X$100)<>1),0,0),0)),$F$1=$AA$1,INDEX($Z$2:$Z$100,MATCH(0,INDEX(COUNTIF($E$1:$E50,$Z$2:$Z$100)+(COUNTIF($Z$2:$Z$100,$Z$2:$Z$100)<>1),0,0),0)),TRUE,"")),$E$1="GENINTEGRATION 22 Attributes",INDEX($H$2:$H$100,MATCH(0,INDEX(COUNTIF($E$1:$E50,$H$2:$H$100)+(COUNTIF($H$2:$H$100,$H$2:$H$100)<>1),0,0),0)),TRUE,""),"")} | F51: {=IFERROR(_xlfn.IFS($F$1=$Q$1,_xlfn.XLOOKUP($E51,$P$2:$P$100,Q$2:Q$100)&"",$F$1=$S$1,_xlfn.XLOOKUP($E51,$R$2:$R$100,$S$2:$S$100)&"",$F$1=$Y$1,_xlfn.XLOOKUP($E51,$X$2:$X$100,$Y$2:$Y$100)&"",$F$1=$U$1,_xlfn.XLOOKUP($E51,$T$2:$T$100,$U$2:$U$100)&"",$F$1=$W$1,_xlfn.XLOOKUP($E51,$V$2:$V$100,$W$2:$W$100)&"",$F$1=$AA$1,_xlfn.XLOOKUP($E51,$Z$2:$Z$100,$AA$2:$AA$100)&"",TRUE, ""),"")} | G51: {=IFERROR(IF($F51<>"",_xlfn.IFS($F$1="LM7 31 ClPRODUCT4 ms","LM7",$F$1="LMS1 31 ClPRODUCT4 ms","CV",$F$1="LMS2 31 ClPRODUCT4 ms","CL",$F$1="LMS5 31 ClPRODUCT4 ms","JZ",$F$1="LMS8 31 ClPRODUCT4 ms","DL",$F$1="LMS6 31 ClPRODUCT4 ms","MD",TRUE, ""),IF(AND($E$1="GENINTEGRATION 22 Attributes",$E51<>""),"22","")),"")} | P51: =IF(AND($H51<>"",Q51<>""),$H51,"") | Q51: =IF($J51="yes",$I51,"") | R51: =IF(AND($H51<>"",S51<>""),$H51,"") | S51: =IF($K51="yes",$I51,"") | T51: =IF(AND($H51<>"",U51<>""),$H51,"") | U51: =IF($L51="yes",$I51,"") | V51: =IF(AND($H51<>"",W51<>""),$H51,"") | W51: =IF($M51="yes",$I51,"") | X51: =IF(AND($H51<>"",Y51<>""),$H51,"") | Y51: =IF($N51="yes",$I51,"") | Z51: =IF(AND($H51<>"",AA51<>""),$H51,"") | AA51: =IF($L51="yes",$I51,"")
E52: {=IFERROR(_xlfn.IFS($E$1="GENINTEGRATION 22 Parameters",(_xlfn.IFS($F$1=$Q$1,INDEX($P$2:$P$100,MATCH(0,INDEX(COUNTIF($E$1:$E51,$P$2:$P$100)+(COUNTIF($P$2:$P$100,$P$2:$P$100)<>1),0,0),0)),$F$1=$S$1,INDEX($R$2:$R$100,MATCH(0,INDEX(COUNTIF($E$1:$E51,$R$2:$R$100)+(COUNTIF($R$2:$R$100,$R$2:$R$100)<>1),0,0),0)),$F$1=$U$1,INDEX($T$2:$T$100,MATCH(0,INDEX(COUNTIF($E$1:$E51,$T$2:$T$100)+(COUNTIF($T$2:$T$100,$T$2:$T$100)<>1),0,0),0)),$F$1=$W$1,INDEX($V$2:$V$100,MATCH(0,INDEX(COUNTIF($E$1:$E51,$V$2:$V$100)+(COUNTIF($V$2:$V$100,$V$2:$V$100)<>1),0,0),0)),$F$1=$Y$1,INDEX($X$2:$X$100,MATCH(0,INDEX(COUNTIF($E$1:$E51,$X$2:$X$100)+(COUNTIF($X$2:$X$100,$X$2:$X$100)<>1),0,0),0)),$F$1=$AA$1,INDEX($Z$2:$Z$100,MATCH(0,INDEX(COUNTIF($E$1:$E51,$Z$2:$Z$100)+(COUNTIF($Z$2:$Z$100,$Z$2:$Z$100)<>1),0,0),0)),TRUE,"")),$E$1="GENINTEGRATION 22 Attributes",INDEX($H$2:$H$100,MATCH(0,INDEX(COUNTIF($E$1:$E51,$H$2:$H$100)+(COUNTIF($H$2:$H$100,$H$2:$H$100)<>1),0,0),0)),TRUE,""),"")} | F52: {=IFERROR(_xlfn.IFS($F$1=$Q$1,_xlfn.XLOOKUP($E52,$P$2:$P$100,Q$2:Q$100)&"",$F$1=$S$1,_xlfn.XLOOKUP($E52,$R$2:$R$100,$S$2:$S$100)&"",$F$1=$Y$1,_xlfn.XLOOKUP($E52,$X$2:$X$100,$Y$2:$Y$100)&"",$F$1=$U$1,_xlfn.XLOOKUP($E52,$T$2:$T$100,$U$2:$U$100)&"",$F$1=$W$1,_xlfn.XLOOKUP($E52,$V$2:$V$100,$W$2:$W$100)&"",$F$1=$AA$1,_xlfn.XLOOKUP($E52,$Z$2:$Z$100,$AA$2:$AA$100)&"",TRUE, ""),"")} | G52: {=IFERROR(IF($F52<>"",_xlfn.IFS($F$1="LM7 31 ClPRODUCT4 ms","LM7",$F$1="LMS1 31 ClPRODUCT4 ms","CV",$F$1="LMS2 31 ClPRODUCT4 ms","CL",$F$1="LMS5 31 ClPRODUCT4 ms","JZ",$F$1="LMS8 31 ClPRODUCT4 ms","DL",$F$1="LMS6 31 ClPRODUCT4 ms","MD",TRUE, ""),IF(AND($E$1="GENINTEGRATION 22 Attributes",$E52<>""),"22","")),"")} | P52: =IF(AND($H52<>"",Q52<>""),$H52,"") | Q52: =IF($J52="yes",$I52,"") | R52: =IF(AND($H52<>"",S52<>""),$H52,"") | S52: =IF($K52="yes",$I52,"") | T52: =IF(AND($H52<>"",U52<>""),$H52,"") | U52: =IF($L52="yes",$I52,"") | V52: =IF(AND($H52<>"",W52<>""),$H52,"") | W52: =IF($M52="yes",$I52,"") | X52: =IF(AND($H52<>"",Y52<>""),$H52,"") | Y52: =IF($N52="yes",$I52,"") | Z52: =IF(AND($H52<>"",AA52<>""),$H52,"") | AA52: =IF($L52="yes",$I52,"")
